Workbook
Name ActiveMonthlyRain: 'Rainfall Data'!$C$15:$C$26
Name ActiveRainyDays: 'Rainfall Data'!$D$15:$D$26
Name CF_Range: Economics!$F$36:$F$55
Name CollectionEff: Inputs!$C$16
Name ConveyEff: Inputs!$C$13
Name DailyDate: 'Rainfall Data'!$J$32:$J$396
Name DailyDemand_L: Inputs!$H$9
Name DailyRainfall: 'Rainfall Data'!$P$32:$P$396
Name DeadStorage_L: Inputs!$C$21
Name DemandPerCapita_L: Inputs!$H$7
Name DiscountRate: Inputs!$H$21
Name ElecTariff_PKR_kWh: Inputs!$H$20
Name FilterEff: Inputs!$C$12
Name FirstFlush_mm: Inputs!$C$9
Name InstallCost_PKR: Inputs!$H$18
Name IRR_Range: Economics!$F$35:$F$55
Name MaintCost_PKR: Inputs!$H$19
Name Month_AvgStorage: 'Monthly Summary'!$I$6:$I$17
Name Month_Collected: 'Monthly Summary'!$D$6:$D$17
Name Month_Demand: 'Monthly Summary'!$E$6:$E$17
Name Month_Names: 'Monthly Summary'!$B$6:$B$17
Name Month_Overflow: 'Monthly Summary'!$G$6:$G$17
Name Month_Rain: 'Monthly Summary'!$C$6:$C$17
Name Month_Reliab: 'Monthly Summary'!$K$6:$K$17
Name Month_Shortage: 'Monthly Summary'!$H$6:$H$17
Name Month_Supplied: 'Monthly Summary'!$F$6:$F$17
Name Month_Util: 'Monthly Summary'!$J$6:$J$17
Name Occupants: Inputs!$H$6
Name ProjectLife_yrs: Inputs!$H$22
Name PumpEff: Inputs!$C$14
Name RainfallStation: Inputs!$H$12
Name RainTable: 'Rainfall Data'!$C$5:$N$10
Name RoofArea_m2: Inputs!$C$6
Name RoofMaterial: Inputs!$C$7
Name RunoffCoeff: Inputs!$C$8
Name Sim_Collected: 'Daily Simulation'!$E$6:$E$370
Name Sim_CollectEff: 'Daily Simulation'!$L$6:$L$370
Name Sim_CumCollected: 'Daily Simulation'!$M$6:$M$370
Name Sim_CumOverflow: 'Daily Simulation'!$O$6:$O$370
Name Sim_CumShortage: 'Daily Simulation'!$P$6:$P$370
Name Sim_CumUsed: 'Daily Simulation'!$N$6:$N$370
Name Sim_Date: 'Daily Simulation'!$C$6:$C$370
Name Sim_Day: 'Daily Simulation'!$B$6:$B$370
Name Sim_Demand: 'Daily Simulation'!$G$6:$G$370
Name Sim_FinalLevel: 'Daily Simulation'!$K$6:$K$370
Name Sim_InitLevel: 'Daily Simulation'!$F$6:$F$370
Name Sim_Overflow: 'Daily Simulation'!$I$6:$I$370
Name Sim_Rainfall: 'Daily Simulation'!$D$6:$D$370
Name Sim_Shortage: 'Daily Simulation'!$J$6:$J$370
Name Sim_Supplied: 'Daily Simulation'!$H$6:$H$370
Name StationNames: 'Rainfall Data'!$B$5:$B$10
Name Sweep_Overflow: 'Tank Optimization'!$D$34:$D$48
Name Sweep_Supplied: 'Tank Optimization'!$C$34:$C$48
Name Sweep_TankSize: 'Tank Optimization'!$B$34:$B$48
Name TankCapacity_L: Inputs!$C$19
Name TankCost_PKR: Inputs!$H$17
Name TankInitial_L: Inputs!$C$20
Name WaterTariff_PKR_L: Inputs!$H$16

Sheet Dashboard
B2: RAINWATER HARVESTING SYSTEM
B3: Design & Performance Simulation: Rooftop System, 365-Day Model
B5: Station | E5: =RainfallStation -> Karachi | F5: Tank Capacity | G5: =TankCapacity_L -> 5000
B7: Total Annual Rainfall | C7: Total Water Collected | D7: Water Supplied | E7: Water Shortage
B8: =('Monthly Summary'!C18) -> 155 | C8: =('Monthly Summary'!D18) -> 22746.306 | D8: =('Monthly Summary'!F18) -> 23546.306 | E8: =('Monthly Summary'!H18) -> 75003.694
C9: gross, before demand | D9: met from storage | E9: unmet demand
B11: Annual Overflow | C11: Tank Utilization | D11: Supply Reliability | E11: Collection Efficiency
B12: =('Monthly Summary'!G18) -> 0 | C12: =('Monthly Summary'!J18) -> 0.13486003 | D12: =('Monthly Summary'!K18) -> 0.23892751 | E12: =CollectionEff -> 0.783275
B13: spilled once full | C13: avg storage / capacity | D13: supplied / demand | E13: runoff x filter x conveyance
B15: Annual Water Savings | C15: Annual Cost Savings | D15: Simple Payback | E15: Net Present Value
B16: =Economics!C19 -> 28255.567 | C16: =Economics!C20 -> 18457.286 | D16: =Economics!C23 -> 7.043289 | E16: =Economics!C28 -> 7865.6569
B17: gross litres offset | C17: net, after O&M | D17: capital / net savings | E17: @ 12% discount, 20 yr
B20: MONTHLY PERFORMANCE -Supply vs Demand vs Shortage

Sheet Inputs
B2: USER INPUTS: Rainwater Harvesting Design Parameters
B3: Yellow-filled cells are editable. All other sheets read from named ranges defined here.
B5: ROOF & SITE | G5: WATER DEMAND
B6: Roof Area | C6: 220 | D6: m2 | E6: Plan (footprint) area of the collection roof, not sloped surface area. | G6: Number of Occupants | H6: 6 | I6: people
B7: Roof Material | C7: Corrugated Metal | E7: Drives default runoff coefficient below via lookup table. | G7: Per-Capita Daily Demand | H7: 45 | I7: L/person/day
B8: Runoff Coefficient (C) | C8: 0.85 | E8: Fraction of rainfall that becomes runoff. Overridable -see Sheet 6 lookup table.
B9: First-Flush Diversion | C9: 1 | D9: mm | E9: Depth of initial rainfall diverted per event to flush roof contaminants. Set to 0 to disable. | G9: Total Daily Demand | H9: =Occupants*DemandPerCapita_L -> 270
B11: SYSTEM PERFORMANCE | G11: LOCATION
B12: Filter Efficiency | C12: 0.95 | E12: Fraction of pre-filtered water passing the leaf/debris filter to storage. | G12: Rainfall Station | H12: Karachi
B13: Conveyance Efficiency | C13: 0.97 | E13: Fraction retained after gutter/downpipe losses and minor leakage. | G13: Manual entry overrides the station table on the Rainfall Data sheet.
B14: Pump Efficiency | C14: 0.8 | E14: Applied only in energy cost calc on Sheet 9; does not affect water balance.
G15: ECONOMIC PARAMETERS
B16: Overall Collection Efficiency | C16: =RunoffCoeff*FilterEff*ConveyEff -> 0.783275 | E16: Runoff Coeff x Filter Eff x Conveyance Eff (Sheet 6, Eq. 3) | G16: Municipal Water Tariff | H16: 1.2 | I16: PKR/L
G17: Tank Capital Cost | H17: 85000 | I17: PKR
B18: STORAGE TANK | G18: Installation Cost | H18: 45000 | I18: PKR
B19: Tank Capacity | C19: 5000 | D19: L | E19: Design storage volume. Optimized on Sheet 7 (Solver). | G19: Annual Maintenance Cost | H19: 6000 | I19: PKR/yr
B20: Initial Tank Level (Day 0) | C20: 1000 | D20: L | E20: Starting stored volume on 1 January. | G20: Electricity Tariff | H20: 45 | I20: PKR/kWh
B21: Dead Storage (unusable) | C21: 200 | D21: L | E21: Sediment zone below outlet; excluded from usable supply. | G21: Discount Rate | H21: 0.12
G22: Analysis Horizon | H22: 20 | I22: yrs

Sheet Rainfall Data
B2: RAINFALL DATA Monthly Normals by Station (mm)
B4: Station | C4: Jan | D4: Feb | E4: Mar | F4: Apr | G4: May | H4: Jun | I4: Jul | J4: Aug | K4: Sep | L4: Oct | M4: Nov | N4: Dec | O4: Annual
B5: Karachi | C5: 3 | D5: 2 | E5: 2 | F5: 1 | G5: 1 | H5: 3 | I5: 65 | J5: 57 | K5: 15 | L5: 2 | M5: 2 | N5: 4 | O5: =SUM(C5:N5) -> 157
B6: Lahore | C6: 22 | D6: 28 | E6: 40 | F6: 20 | G6: 15 | H6: 55 | I6: 145 | J6: 125 | K6: 45 | L6: 8 | M6: 5 | N6: 12 | O6: =SUM(C6:N6) -> 520
B7: Islamabad | C7: 55 | D7: 65 | E7: 85 | F7: 62 | G7: 38 | H7: 55 | I7: 235 | J7: 210 | K7: 75 | L7: 20 | M7: 12 | N7: 35 | O7: =SUM(C7:N7) -> 947
B8: Peshawar | C8: 35 | D8: 42 | E8: 68 | F8: 45 | G8: 18 | H8: 12 | I8: 45 | J8: 40 | K8: 15 | L8: 10 | M8: 8 | N8: 20 | O8: =SUM(C8:N8) -> 358
B9: Quetta | C9: 35 | D9: 30 | E9: 42 | F9: 15 | G9: 3 | H9: 1 | I9: 8 | J9: 5 | K9: 2 | L9: 3 | M9: 8 | N9: 22 | O9: =SUM(C9:N9) -> 174
B10: Manual Entry | C10: 0 | D10: 0 | E10: 0 | F10: 0 | G10: 0 | H10: 0 | I10: 0 | J10: 0 | K10: 0 | L10: 0 | M10: 0 | N10: 0 | O10: =SUM(C10:N10) -> 0
B11: Used only when Inputs!RainfallStation = "Manual Entry"
B13: ACTIVE MONTHLY SERIES (driven by Inputs!RainfallStation)
B14: Month | C14: Rainfall (mm) | D14: Rainy Days | E14: Days in Month
B15: Jan | C15: =INDEX($C$5:$N$10,MATCH(Inputs!$H$12,$B$5:$B$10,0),1) -> 3 | D15: 1 | E15: 31
B16: Feb | C16: =INDEX($C$5:$N$10,MATCH(Inputs!$H$12,$B$5:$B$10,0),2) -> 2 | D16: 1 | E16: 28
B17: Mar | C17: =INDEX($C$5:$N$10,MATCH(Inputs!$H$12,$B$5:$B$10,0),3) -> 2 | D17: 2 | E17: 31
B18: Apr | C18: =INDEX($C$5:$N$10,MATCH(Inputs!$H$12,$B$5:$B$10,0),4) -> 1 | D18: 0 | E18: 30
B19: May | C19: =INDEX($C$5:$N$10,MATCH(Inputs!$H$12,$B$5:$B$10,0),5) -> 1 | D19: 0 | E19: 31
B20: Jun | C20: =INDEX($C$5:$N$10,MATCH(Inputs!$H$12,$B$5:$B$10,0),6) -> 3 | D20: 2 | E20: 30
B21: Jul | C21: =INDEX($C$5:$N$10,MATCH(Inputs!$H$12,$B$5:$B$10,0),7) -> 65 | D21: 6 | E21: 31
B22: Aug | C22: =INDEX($C$5:$N$10,MATCH(Inputs!$H$12,$B$5:$B$10,0),8) -> 57 | D22: 5 | E22: 31
B23: Sep | C23: =INDEX($C$5:$N$10,MATCH(Inputs!$H$12,$B$5:$B$10,0),9) -> 15 | D23: 3 | E23: 30
B24: Oct | C24: =INDEX($C$5:$N$10,MATCH(Inputs!$H$12,$B$5:$B$10,0),10) -> 2 | D24: 1 | E24: 31
B25: Nov | C25: =INDEX($C$5:$N$10,MATCH(Inputs!$H$12,$B$5:$B$10,0),11) -> 2 | D25: 1 | E25: 30
B26: Dec | C26: =INDEX($C$5:$N$10,MATCH(Inputs!$H$12,$B$5:$B$10,0),12) -> 4 | D26: 1 | E26: 31
B27: Annual Total | C27: =SUM(C15:C26) -> 157
I30: DAILY RAINFALL SERIES (365 Days)
I31: Day | J31: Date | K31: Month # | L31: Monthly Total (mm) | M31: Rainy Days | N31: Day-of-Month | O31: Rain Slot? | P31: Daily Rainfall (mm)
I32: 1 | J32: 46023 | K32: =MONTH(J32) -> 1 | L32: =INDEX($C$15:$C$26,K32) -> 3 | M32: =INDEX($D$15:$D$26,K32) -> 1 | N32: =DAY(J32) -> 1 | O32: 0 | P32: =IF(O32=1,IF(M32>0,L32/M32,0),0) -> 0
I33: 2 | J33: 46024 | K33: =MONTH(J33) -> 1 | L33: =INDEX($C$15:$C$26,K33) -> 3 | M33: =INDEX($D$15:$D$26,K33) -> 1 | N33: =DAY(J33) -> 2 | O33: 0 | P33: =IF(O33=1,IF(M33>0,L33/M33,0),0) -> 0
I34: 3 | J34: 46025 | K34: =MONTH(J34) -> 1 | L34: =INDEX($C$15:$C$26,K34) -> 3 | M34: =INDEX($D$15:$D$26,K34) -> 1 | N34: =DAY(J34) -> 3 | O34: 0 | P34: =IF(O34=1,IF(M34>0,L34/M34,0),0) -> 0
I35: 4 | J35: 46026 | K35: =MONTH(J35) -> 1 | L35: =INDEX($C$15:$C$26,K35) -> 3 | M35: =INDEX($D$15:$D$26,K35) -> 1 | N35: =DAY(J35) -> 4 | O35: 0 | P35: =IF(O35=1,IF(M35>0,L35/M35,0),0) -> 0
I36: 5 | J36: 46027 | K36: =MONTH(J36) -> 1 | L36: =INDEX($C$15:$C$26,K36) -> 3 | M36: =INDEX($D$15:$D$26,K36) -> 1 | N36: =DAY(J36) -> 5 | O36: 0 | P36: =IF(O36=1,IF(M36>0,L36/M36,0),0) -> 0
I37: 6 | J37: 46028 | K37: =MONTH(J37) -> 1 | L37: =INDEX($C$15:$C$26,K37) -> 3 | M37: =INDEX($D$15:$D$26,K37) -> 1 | N37: =DAY(J37) -> 6 | O37: 0 | P37: =IF(O37=1,IF(M37>0,L37/M37,0),0) -> 0
I38: 7 | J38: 46029 | K38: =MONTH(J38) -> 1 | L38: =INDEX($C$15:$C$26,K38) -> 3 | M38: =INDEX($D$15:$D$26,K38) -> 1 | N38: =DAY(J38) -> 7 | O38: 0 | P38: =IF(O38=1,IF(M38>0,L38/M38,0),0) -> 0
I39: 8 | J39: 46030 | K39: =MONTH(J39) -> 1 | L39: =INDEX($C$15:$C$26,K39) -> 3 | M39: =INDEX($D$15:$D$26,K39) -> 1 | N39: =DAY(J39) -> 8 | O39: 0 | P39: =IF(O39=1,IF(M39>0,L39/M39,0),0) -> 0
I40: 9 | J40: 46031 | K40: =MONTH(J40) -> 1 | L40: =INDEX($C$15:$C$26,K40) -> 3 | M40: =INDEX($D$15:$D$26,K40) -> 1 | N40: =DAY(J40) -> 9 | O40: 0 | P40: =IF(O40=1,IF(M40>0,L40/M40,0),0) -> 0
I41: 10 | J41: 46032 | K41: =MONTH(J41) -> 1 | L41: =INDEX($C$15:$C$26,K41) -> 3 | M41: =INDEX($D$15:$D$26,K41) -> 1 | N41: =DAY(J41) -> 10 | O41: 0 | P41: =IF(O41=1,IF(M41>0,L41/M41,0),0) -> 0
I42: 11 | J42: 46033 | K42: =MONTH(J42) -> 1 | L42: =INDEX($C$15:$C$26,K42) -> 3 | M42: =INDEX($D$15:$D$26,K42) -> 1 | N42: =DAY(J42) -> 11 | O42: 0 | P42: =IF(O42=1,IF(M42>0,L42/M42,0),0) -> 0
I43: 12 | J43: 46034 | K43: =MONTH(J43) -> 1 | L43: =INDEX($C$15:$C$26,K43) -> 3 | M43: =INDEX($D$15:$D$26,K43) -> 1 | N43: =DAY(J43) -> 12 | O43: 0 | P43: =IF(O43=1,IF(M43>0,L43/M43,0),0) -> 0
... I396: 365 | J396: 46387 | K396: =MONTH(J396) -> 12 | L396: =INDEX($C$15:$C$26,K396) -> 4 | M396: =INDEX($D$15:$D$26,K396) -> 1 | N396: =DAY(J396) -> 31 | O396: 0 | P396: =IF(O396=1,IF(M396>0,L396/M396,0),0) -> 0
I398: Method: monthly rainfall is split equally across a fixed number of rain-days per month, placed at even day-of-month intervals (see Engineering Calcs, Assumption A4). This is a simplification of real storm clustering; for site-specific design, replace this block with observed daily station records.

Sheet Daily Simulation
B2: DAILY SIMULATION - 365-Day Tank Mass Balance
B3: Conservation of mass: Final Level = Initial Level + Collected − Supplied − Overflow. Overflow occurs only when the tank would exceed capacity.
B5: Day | C5: Date | D5: Rainfall (mm) | E5: Collected Water (L) | F5: Initial Tank Level (L) | G5: Water Demand (L) | H5: Water Supplied (L) | I5: Overflow (L) | J5: Shortage (L) | K5: Final Tank Level (L) | L5: Collection Efficiency | M5: Cum. Water Collected (L) | N5: Cum. Water Used (L) | O5: Cum. Overflow (L) | P5: Cum. Shortage (L)
B6: 1 | C6: ='Rainfall Data'!J32 -> 46023 | D6: ='Rainfall Data'!P32 -> 0 | E6: =MAX(D6-FirstFlush_mm,0)*RoofArea_m2*CollectionEff -> 0 | F6: =TankInitial_L -> 1000 | G6: =DailyDemand_L -> 270 | H6: =MIN(G6,MAX(F6+E6-DeadStorage_L,0)) -> 270 | I6: =MAX(F6+E6-H6-TankCapacity_L,0) -> 0 | J6: =G6-H6 -> 0 | K6: =MIN(F6+E6-H6-I6,TankCapacity_L) -> 730 | L6: =IF(D6>0,CollectionEff,0) -> 0 | M6: =0+E6 -> 0 | N6: =0+H6 -> 270 | O6: =0+I6 -> 0 | P6: =0+J6 -> 0
B7: 2 | C7: ='Rainfall Data'!J33 -> 46024 | D7: ='Rainfall Data'!P33 -> 0 | E7: =MAX(D7-FirstFlush_mm,0)*RoofArea_m2*CollectionEff -> 0 | F7: =K6 -> 730 | G7: =DailyDemand_L -> 270 | H7: =MIN(G7,MAX(F7+E7-DeadStorage_L,0)) -> 270 | I7: =MAX(F7+E7-H7-TankCapacity_L,0) -> 0 | J7: =G7-H7 -> 0 | K7: =MIN(F7+E7-H7-I7,TankCapacity_L) -> 460 | L7: =IF(D7>0,CollectionEff,0) -> 0 | M7: =M6+E7 -> 0 | N7: =N6+H7 -> 540 | O7: =O6+I7 -> 0 | P7: =P6+J7 -> 0
B8: 3 | C8: ='Rainfall Data'!J34 -> 46025 | D8: ='Rainfall Data'!P34 -> 0 | E8: =MAX(D8-FirstFlush_mm,0)*RoofArea_m2*CollectionEff -> 0 | F8: =K7 -> 460 | G8: =DailyDemand_L -> 270 | H8: =MIN(G8,MAX(F8+E8-DeadStorage_L,0)) -> 260 | I8: =MAX(F8+E8-H8-TankCapacity_L,0) -> 0 | J8: =G8-H8 -> 10 | K8: =MIN(F8+E8-H8-I8,TankCapacity_L) -> 200 | L8: =IF(D8>0,CollectionEff,0) -> 0 | M8: =M7+E8 -> 0 | N8: =N7+H8 -> 800 | O8: =O7+I8 -> 0 | P8: =P7+J8 -> 10
B9: 4 | C9: ='Rainfall Data'!J35 -> 46026 | D9: ='Rainfall Data'!P35 -> 0 | E9: =MAX(D9-FirstFlush_mm,0)*RoofArea_m2*CollectionEff -> 0 | F9: =K8 -> 200 | G9: =DailyDemand_L -> 270 | H9: =MIN(G9,MAX(F9+E9-DeadStorage_L,0)) -> 0 | I9: =MAX(F9+E9-H9-TankCapacity_L,0) -> 0 | J9: =G9-H9 -> 270 | K9: =MIN(F9+E9-H9-I9,TankCapacity_L) -> 200 | L9: =IF(D9>0,CollectionEff,0) -> 0 | M9: =M8+E9 -> 0 | N9: =N8+H9 -> 800 | O9: =O8+I9 -> 0 | P9: =P8+J9 -> 280
B10: 5 | C10: ='Rainfall Data'!J36 -> 46027 | D10: ='Rainfall Data'!P36 -> 0 | E10: =MAX(D10-FirstFlush_mm,0)*RoofArea_m2*CollectionEff -> 0 | F10: =K9 -> 200 | G10: =DailyDemand_L -> 270 | H10: =MIN(G10,MAX(F10+E10-DeadStorage_L,0)) -> 0 | I10: =MAX(F10+E10-H10-TankCapacity_L,0) -> 0 | J10: =G10-H10 -> 270 | K10: =MIN(F10+E10-H10-I10,TankCapacity_L) -> 200 | L10: =IF(D10>0,CollectionEff,0) -> 0 | M10: =M9+E10 -> 0 | N10: =N9+H10 -> 800 | O10: =O9+I10 -> 0 | P10: =P9+J10 -> 550
B11: 6 | C11: ='Rainfall Data'!J37 -> 46028 | D11: ='Rainfall Data'!P37 -> 0 | E11: =MAX(D11-FirstFlush_mm,0)*RoofArea_m2*CollectionEff -> 0 | F11: =K10 -> 200 | G11: =DailyDemand_L -> 270 | H11: =MIN(G11,MAX(F11+E11-DeadStorage_L,0)) -> 0 | I11: =MAX(F11+E11-H11-TankCapacity_L,0) -> 0 | J11: =G11-H11 -> 270 | K11: =MIN(F11+E11-H11-I11,TankCapacity_L) -> 200 | L11: =IF(D11>0,CollectionEff,0) -> 0 | M11: =M10+E11 -> 0 | N11: =N10+H11 -> 800 | O11: =O10+I11 -> 0 | P11: =P10+J11 -> 820
B12: 7 | C12: ='Rainfall Data'!J38 -> 46029 | D12: ='Rainfall Data'!P38 -> 0 | E12: =MAX(D12-FirstFlush_mm,0)*RoofArea_m2*CollectionEff -> 0 | F12: =K11 -> 200 | G12: =DailyDemand_L -> 270 | H12: =MIN(G12,MAX(F12+E12-DeadStorage_L,0)) -> 0 | I12: =MAX(F12+E12-H12-TankCapacity_L,0) -> 0 | J12: =G12-H12 -> 270 | K12: =MIN(F12+E12-H12-I12,TankCapacity_L) -> 200 | L12: =IF(D12>0,CollectionEff,0) -> 0 | M12: =M11+E12 -> 0 | N12: =N11+H12 -> 800 | O12: =O11+I12 -> 0 | P12: =P11+J12 -> 1090
B13: 8 | C13: ='Rainfall Data'!J39 -> 46030 | D13: ='Rainfall Data'!P39 -> 0 | E13: =MAX(D13-FirstFlush_mm,0)*RoofArea_m2*CollectionEff -> 0 | F13: =K12 -> 200 | G13: =DailyDemand_L -> 270 | H13: =MIN(G13,MAX(F13+E13-DeadStorage_L,0)) -> 0 | I13: =MAX(F13+E13-H13-TankCapacity_L,0) -> 0 | J13: =G13-H13 -> 270 | K13: =MIN(F13+E13-H13-I13,TankCapacity_L) -> 200 | L13: =IF(D13>0,CollectionEff,0) -> 0 | M13: =M12+E13 -> 0 | N13: =N12+H13 -> 800 | O13: =O12+I13 -> 0 | P13: =P12+J13 -> 1360
B14: 9 | C14: ='Rainfall Data'!J40 -> 46031 | D14: ='Rainfall Data'!P40 -> 0 | E14: =MAX(D14-FirstFlush_mm,0)*RoofArea_m2*CollectionEff -> 0 | F14: =K13 -> 200 | G14: =DailyDemand_L -> 270 | H14: =MIN(G14,MAX(F14+E14-DeadStorage_L,0)) -> 0 | I14: =MAX(F14+E14-H14-TankCapacity_L,0) -> 0 | J14: =G14-H14 -> 270 | K14: =MIN(F14+E14-H14-I14,TankCapacity_L) -> 200 | L14: =IF(D14>0,CollectionEff,0) -> 0 | M14: =M13+E14 -> 0 | N14: =N13+H14 -> 800 | O14: =O13+I14 -> 0 | P14: =P13+J14 -> 1630
B15: 10 | C15: ='Rainfall Data'!J41 -> 46032 | D15: ='Rainfall Data'!P41 -> 0 | E15: =MAX(D15-FirstFlush_mm,0)*RoofArea_m2*CollectionEff -> 0 | F15: =K14 -> 200 | G15: =DailyDemand_L -> 270 | H15: =MIN(G15,MAX(F15+E15-DeadStorage_L,0)) -> 0 | I15: =MAX(F15+E15-H15-TankCapacity_L,0) -> 0 | J15: =G15-H15 -> 270 | K15: =MIN(F15+E15-H15-I15,TankCapacity_L) -> 200 | L15: =IF(D15>0,CollectionEff,0) -> 0 | M15: =M14+E15 -> 0 | N15: =N14+H15 -> 800 | O15: =O14+I15 -> 0 | P15: =P14+J15 -> 1900
B16: 11 | C16: ='Rainfall Data'!J42 -> 46033 | D16: ='Rainfall Data'!P42 -> 0 | E16: =MAX(D16-FirstFlush_mm,0)*RoofArea_m2*CollectionEff -> 0 | F16: =K15 -> 200 | G16: =DailyDemand_L -> 270 | H16: =MIN(G16,MAX(F16+E16-DeadStorage_L,0)) -> 0 | I16: =MAX(F16+E16-H16-TankCapacity_L,0) -> 0 | J16: =G16-H16 -> 270 | K16: =MIN(F16+E16-H16-I16,TankCapacity_L) -> 200 | L16: =IF(D16>0,CollectionEff,0) -> 0 | M16: =M15+E16 -> 0 | N16: =N15+H16 -> 800 | O16: =O15+I16 -> 0 | P16: =P15+J16 -> 2170
B17: 12 | C17: ='Rainfall Data'!J43 -> 46034 | D17: ='Rainfall Data'!P43 -> 0 | E17: =MAX(D17-FirstFlush_mm,0)*RoofArea_m2*CollectionEff -> 0 | F17: =K16 -> 200 | G17: =DailyDemand_L -> 270 | H17: =MIN(G17,MAX(F17+E17-DeadStorage_L,0)) -> 0 | I17: =MAX(F17+E17-H17-TankCapacity_L,0) -> 0 | J17: =G17-H17 -> 270 | K17: =MIN(F17+E17-H17-I17,TankCapacity_L) -> 200 | L17: =IF(D17>0,CollectionEff,0) -> 0 | M17: =M16+E17 -> 0 | N17: =N16+H17 -> 800 | O17: =O16+I17 -> 0 | P17: =P16+J17 -> 2440
B18: 13 | C18: ='Rainfall Data'!J44 -> 46035 | D18: ='Rainfall Data'!P44 -> 0 | E18: =MAX(D18-FirstFlush_mm,0)*RoofArea_m2*CollectionEff -> 0 | F18: =K17 -> 200 | G18: =DailyDemand_L -> 270 | H18: =MIN(G18,MAX(F18+E18-DeadStorage_L,0)) -> 0 | I18: =MAX(F18+E18-H18-TankCapacity_L,0) -> 0 | J18: =G18-H18 -> 270 | K18: =MIN(F18+E18-H18-I18,TankCapacity_L) -> 200 | L18: =IF(D18>0,CollectionEff,0) -> 0 | M18: =M17+E18 -> 0 | N18: =N17+H18 -> 800 | O18: =O17+I18 -> 0 | P18: =P17+J18 -> 2710
... B370: 365 | C370: ='Rainfall Data'!J396 -> 46387 | D370: ='Rainfall Data'!P396 -> 0 | E370: =MAX(D370-FirstFlush_mm,0)*RoofArea_m2*CollectionEff -> 0 | F370: =K369 -> 200 | G370: =DailyDemand_L -> 270 | H370: =MIN(G370,MAX(F370+E370-DeadStorage_L,0)) -> 0 | I370: =MAX(F370+E370-H370-TankCapacity_L,0) -> 0 | J370: =G370-H370 -> 270 | K370: =MIN(F370+E370-H370-I370,TankCapacity_L) -> 200 | L370: =IF(D370>0,CollectionEff,0) -> 0 | M370: =M369+E370 -> 22746.306 | N370: =N369+H370 -> 23546.306 | O370: =O369+I370 -> 0 | P370: =P369+J370 -> 75003.694

Sheet Monthly Summary
B2: MONTHLY SUMMARY - Aggregated from Daily Simulation
B3: Aggregated by calendar month using SUMPRODUCT / AVERAGEIFS over the 365-day simulation.
B5: Month | C5: Rainfall (mm) | D5: Collected Water (L) | E5: Demand (L) | F5: Water Supplied (L) | G5: Overflow (L) | H5: Shortage (L) | I5: Avg. Storage (L) | J5: Tank Utilization | K5: Reliability
B6: January | C6: =SUMPRODUCT((MONTH(Sim_Date)=1)*Sim_Rainfall) -> 3 | D6: =SUMPRODUCT((MONTH(Sim_Date)=1)*Sim_Collected) -> 344.641 | E6: =SUMPRODUCT((MONTH(Sim_Date)=1)*Sim_Demand) -> 8370 | F6: =SUMPRODUCT((MONTH(Sim_Date)=1)*Sim_Supplied) -> 1144.641 | G6: =SUMPRODUCT((MONTH(Sim_Date)=1)*Sim_Overflow) -> 0 | H6: =SUMPRODUCT((MONTH(Sim_Date)=1)*Sim_Shortage) -> 7225.359 | I6: =AVERAGEIFS(Sim_FinalLevel,Sim_Date,">="&DATE(2026,1,1),Sim_Date,"<"&EDATE(DATE(2026,1,1),1)) -> 227.89165 | J6: =I6/TankCapacity_L -> 0.045578329 | K6: =IF(E6=0,1,F6/E6) -> 0.1367552
B7: February | C7: =SUMPRODUCT((MONTH(Sim_Date)=2)*Sim_Rainfall) -> 2 | D7: =SUMPRODUCT((MONTH(Sim_Date)=2)*Sim_Collected) -> 172.3205 | E7: =SUMPRODUCT((MONTH(Sim_Date)=2)*Sim_Demand) -> 7560 | F7: =SUMPRODUCT((MONTH(Sim_Date)=2)*Sim_Supplied) -> 172.3205 | G7: =SUMPRODUCT((MONTH(Sim_Date)=2)*Sim_Overflow) -> 0 | H7: =SUMPRODUCT((MONTH(Sim_Date)=2)*Sim_Shortage) -> 7387.6795 | I7: =AVERAGEIFS(Sim_FinalLevel,Sim_Date,">="&DATE(2026,2,1),Sim_Date,"<"&EDATE(DATE(2026,2,1),1)) -> 200 | J7: =I7/TankCapacity_L -> 0.04 | K7: =IF(E7=0,1,F7/E7) -> 0.022793717
B8: March | C8: =SUMPRODUCT((MONTH(Sim_Date)=3)*Sim_Rainfall) -> 2 | D8: =SUMPRODUCT((MONTH(Sim_Date)=3)*Sim_Collected) -> 0 | E8: =SUMPRODUCT((MONTH(Sim_Date)=3)*Sim_Demand) -> 8370 | F8: =SUMPRODUCT((MONTH(Sim_Date)=3)*Sim_Supplied) -> 0 | G8: =SUMPRODUCT((MONTH(Sim_Date)=3)*Sim_Overflow) -> 0 | H8: =SUMPRODUCT((MONTH(Sim_Date)=3)*Sim_Shortage) -> 8370 | I8: =AVERAGEIFS(Sim_FinalLevel,Sim_Date,">="&DATE(2026,3,1),Sim_Date,"<"&EDATE(DATE(2026,3,1),1)) -> 200 | J8: =I8/TankCapacity_L -> 0.04 | K8: =IF(E8=0,1,F8/E8) -> 0
B9: April | C9: =SUMPRODUCT((MONTH(Sim_Date)=4)*Sim_Rainfall) -> 0 | D9: =SUMPRODUCT((MONTH(Sim_Date)=4)*Sim_Collected) -> 0 | E9: =SUMPRODUCT((MONTH(Sim_Date)=4)*Sim_Demand) -> 8100 | F9: =SUMPRODUCT((MONTH(Sim_Date)=4)*Sim_Supplied) -> 0 | G9: =SUMPRODUCT((MONTH(Sim_Date)=4)*Sim_Overflow) -> 0 | H9: =SUMPRODUCT((MONTH(Sim_Date)=4)*Sim_Shortage) -> 8100 | I9: =AVERAGEIFS(Sim_FinalLevel,Sim_Date,">="&DATE(2026,4,1),Sim_Date,"<"&EDATE(DATE(2026,4,1),1)) -> 200 | J9: =I9/TankCapacity_L -> 0.04 | K9: =IF(E9=0,1,F9/E9) -> 0
B10: May | C10: =SUMPRODUCT((MONTH(Sim_Date)=5)*Sim_Rainfall) -> 0 | D10: =SUMPRODUCT((MONTH(Sim_Date)=5)*Sim_Collected) -> 0 | E10: =SUMPRODUCT((MONTH(Sim_Date)=5)*Sim_Demand) -> 8370 | F10: =SUMPRODUCT((MONTH(Sim_Date)=5)*Sim_Supplied) -> 0 | G10: =SUMPRODUCT((MONTH(Sim_Date)=5)*Sim_Overflow) -> 0 | H10: =SUMPRODUCT((MONTH(Sim_Date)=5)*Sim_Shortage) -> 8370 | I10: =AVERAGEIFS(Sim_FinalLevel,Sim_Date,">="&DATE(2026,5,1),Sim_Date,"<"&EDATE(DATE(2026,5,1),1)) -> 200 | J10: =I10/TankCapacity_L -> 0.04 | K10: =IF(E10=0,1,F10/E10) -> 0
B11: June | C11: =SUMPRODUCT((MONTH(Sim_Date)=6)*Sim_Rainfall) -> 3 | D11: =SUMPRODUCT((MONTH(Sim_Date)=6)*Sim_Collected) -> 172.3205 | E11: =SUMPRODUCT((MONTH(Sim_Date)=6)*Sim_Demand) -> 8100 | F11: =SUMPRODUCT((MONTH(Sim_Date)=6)*Sim_Supplied) -> 172.3205 | G11: =SUMPRODUCT((MONTH(Sim_Date)=6)*Sim_Overflow) -> 0 | H11: =SUMPRODUCT((MONTH(Sim_Date)=6)*Sim_Shortage) -> 7927.6795 | I11: =AVERAGEIFS(Sim_FinalLevel,Sim_Date,">="&DATE(2026,6,1),Sim_Date,"<"&EDATE(DATE(2026,6,1),1)) -> 200 | J11: =I11/TankCapacity_L -> 0.04 | K11: =IF(E11=0,1,F11/E11) -> 0.021274136
B12: July | C12: =SUMPRODUCT((MONTH(Sim_Date)=7)*Sim_Rainfall) -> 65 | D12: =SUMPRODUCT((MONTH(Sim_Date)=7)*Sim_Collected) -> 10166.909 | E12: =SUMPRODUCT((MONTH(Sim_Date)=7)*Sim_Demand) -> 8370 | F12: =SUMPRODUCT((MONTH(Sim_Date)=7)*Sim_Supplied) -> 7560 | G12: =SUMPRODUCT((MONTH(Sim_Date)=7)*Sim_Overflow) -> 0 | H12: =SUMPRODUCT((MONTH(Sim_Date)=7)*Sim_Shortage) -> 810 | I12: =AVERAGEIFS(Sim_FinalLevel,Sim_Date,">="&DATE(2026,7,1),Sim_Date,"<"&EDATE(DATE(2026,7,1),1)) -> 2075.2905 | J12: =I12/TankCapacity_L -> 0.41505811 | K12: =IF(E12=0,1,F12/E12) -> 0.90322581
B13: August | C13: =SUMPRODUCT((MONTH(Sim_Date)=8)*Sim_Rainfall) -> 57 | D13: =SUMPRODUCT((MONTH(Sim_Date)=8)*Sim_Collected) -> 8960.666 | E13: =SUMPRODUCT((MONTH(Sim_Date)=8)*Sim_Demand) -> 8370 | F13: =SUMPRODUCT((MONTH(Sim_Date)=8)*Sim_Supplied) -> 8370 | G13: =SUMPRODUCT((MONTH(Sim_Date)=8)*Sim_Overflow) -> 0 | H13: =SUMPRODUCT((MONTH(Sim_Date)=8)*Sim_Shortage) -> 0 | I13: =AVERAGEIFS(Sim_FinalLevel,Sim_Date,">="&DATE(2026,8,1),Sim_Date,"<"&EDATE(DATE(2026,8,1),1)) -> 3227.3909 | J13: =I13/TankCapacity_L -> 0.64547817 | K13: =IF(E13=0,1,F13/E13) -> 1
B14: September | C14: =SUMPRODUCT((MONTH(Sim_Date)=9)*Sim_Rainfall) -> 15 | D14: =SUMPRODUCT((MONTH(Sim_Date)=9)*Sim_Collected) -> 2067.846 | E14: =SUMPRODUCT((MONTH(Sim_Date)=9)*Sim_Demand) -> 8100 | F14: =SUMPRODUCT((MONTH(Sim_Date)=9)*Sim_Supplied) -> 5265.4215 | G14: =SUMPRODUCT((MONTH(Sim_Date)=9)*Sim_Overflow) -> 0 | H14: =SUMPRODUCT((MONTH(Sim_Date)=9)*Sim_Shortage) -> 2834.5785 | I14: =AVERAGEIFS(Sim_FinalLevel,Sim_Date,">="&DATE(2026,9,1),Sim_Date,"<"&EDATE(DATE(2026,9,1),1)) -> 953.06247 | J14: =I14/TankCapacity_L -> 0.19061249 | K14: =IF(E14=0,1,F14/E14) -> 0.65005204
B15: October | C15: =SUMPRODUCT((MONTH(Sim_Date)=10)*Sim_Rainfall) -> 2 | D15: =SUMPRODUCT((MONTH(Sim_Date)=10)*Sim_Collected) -> 172.3205 | E15: =SUMPRODUCT((MONTH(Sim_Date)=10)*Sim_Demand) -> 8370 | F15: =SUMPRODUCT((MONTH(Sim_Date)=10)*Sim_Supplied) -> 172.3205 | G15: =SUMPRODUCT((MONTH(Sim_Date)=10)*Sim_Overflow) -> 0 | H15: =SUMPRODUCT((MONTH(Sim_Date)=10)*Sim_Shortage) -> 8197.6795 | I15: =AVERAGEIFS(Sim_FinalLevel,Sim_Date,">="&DATE(2026,10,1),Sim_Date,"<"&EDATE(DATE(2026,10,1),1)) -> 200 | J15: =I15/TankCapacity_L -> 0.04 | K15: =IF(E15=0,1,F15/E15) -> 0.020587873
B16: November | C16: =SUMPRODUCT((MONTH(Sim_Date)=11)*Sim_Rainfall) -> 2 | D16: =SUMPRODUCT((MONTH(Sim_Date)=11)*Sim_Collected) -> 172.3205 | E16: =SUMPRODUCT((MONTH(Sim_Date)=11)*Sim_Demand) -> 8100 | F16: =SUMPRODUCT((MONTH(Sim_Date)=11)*Sim_Supplied) -> 172.3205 | G16: =SUMPRODUCT((MONTH(Sim_Date)=11)*Sim_Overflow) -> 0 | H16: =SUMPRODUCT((MONTH(Sim_Date)=11)*Sim_Shortage) -> 7927.6795 | I16: =AVERAGEIFS(Sim_FinalLevel,Sim_Date,">="&DATE(2026,11,1),Sim_Date,"<"&EDATE(DATE(2026,11,1),1)) -> 200 | J16: =I16/TankCapacity_L -> 0.04 | K16: =IF(E16=0,1,F16/E16) -> 0.021274136
B17: December | C17: =SUMPRODUCT((MONTH(Sim_Date)=12)*Sim_Rainfall) -> 4 | D17: =SUMPRODUCT((MONTH(Sim_Date)=12)*Sim_Collected) -> 516.9615 | E17: =SUMPRODUCT((MONTH(Sim_Date)=12)*Sim_Demand) -> 8370 | F17: =SUMPRODUCT((MONTH(Sim_Date)=12)*Sim_Supplied) -> 516.9615 | G17: =SUMPRODUCT((MONTH(Sim_Date)=12)*Sim_Overflow) -> 0 | H17: =SUMPRODUCT((MONTH(Sim_Date)=12)*Sim_Shortage) -> 7853.0385 | I17: =AVERAGEIFS(Sim_FinalLevel,Sim_Date,">="&DATE(2026,12,1),Sim_Date,"<"&EDATE(DATE(2026,12,1),1)) -> 207.9665 | J17: =I17/TankCapacity_L -> 0.0415933 | K17: =IF(E17=0,1,F17/E17) -> 0.06176362
B18: ANNUAL TOTAL | C18: =SUM(C6:C17) -> 155 | D18: =SUM(D6:D17) -> 22746.306 | E18: =SUM(E6:E17) -> 98550 | F18: =SUM(F6:F17) -> 23546.306 | G18: =SUM(G6:G17) -> 0 | H18: =SUM(H6:H17) -> 75003.694 | I18: =AVERAGE(I6:I17) -> 674.30017 | J18: =I18/TankCapacity_L -> 0.13486003 | K18: =IF(E18=0,1,F18/E18) -> 0.23892751

Sheet Engineering Calcs
B2: ENGINEERING CALCULATIONS - Governing Equations & Assumptions
B4: Eq. 1 | C4: Rainfall Collection Volume
C5: V_collect = (P − D_ff) × A × 1,000 [litres, per event, when P > D_ff]
C6: V_collect | D6: Volume of water collected (L)
C7: P | D7: Rainfall depth for the period (mm)
C8: D_ff | D8: First-flush depth diverted before collection begins (mm)
C9: A | D9: Roof plan area (m2)
C10: 1,000 | D10: Unit conversion: 1 mm over 1 m2 = 1 L
C11: 1 mm of rain over 1 m2 of roof yields exactly 1 litre, so mm x m2 already gives litres directly with no further conversion factor needed.
B13: Eq. 2 | C13: Runoff Coefficient
C14: V_runoff = C × P × A
C15: C | D15: Runoff coefficient (0-1), fraction of incident rainfall that leaves the roof as runoff
C16: Typical C | D16: Metal roof 0.80-0.90 · Concrete flat 0.70-0.85 · Clay tile 0.60-0.80 · Green roof 0.30-0.50 · Asphalt shingle 0.75-0.85
C17: Losses are due to surface wetting, evaporation during the event, and minor ponding. C is lower for porous or vegetated roofs.
B19: Eq. 3 | C19: Overall Collection Efficiency
C20: eta_collect = C × eta_filter × eta_convey
C21: eta_filter | D21: Fraction retained through the leaf/debris screen
C22: eta_convey | D22: Fraction retained through gutters and downpipes (minor leakage, splash-out)
C23: The three multiplicative losses are treated as independent, which is standard practice for a preliminary design tool; a detailed hydraulic model would treat gutter losses as a function of rainfall intensity.
B25: Eq. 4 | C25: Tank Mass Balance (Daily)
C26: S(t) = MIN[ S(t-1) + V_collect(t) − Q_supply(t) − Q_overflow(t) , S_cap ]
C27: S(t) | D27: Tank storage at end of day t (L)
C28: Q_supply(t) | D28: Water withdrawn to meet demand on day t (L)
C29: Q_overflow(t) | D29: Water spilled once the tank is full (L)
C30: S_cap | D30: Tank capacity (L)
C31: This is a direct statement of conservation of mass applied to the tank as a control volume: everything entering must either leave (supply, overflow) or accumulate (storage).
B33: Eq. 5 | C33: Water Supplied (Demand Satisfaction)
C34: Q_supply(t) = MIN[ Q_demand(t) , S(t-1) + V_collect(t) − S_dead ]
C35: Q_demand(t) | D35: Water demand on day t (L)
C36: S_dead | D36: Dead storage below the outlet, physically unusable (L)
C37: The tank can only supply what is both demanded and physically available above the dead-storage line.
B39: Eq. 6 | C39: Overflow
C40: Q_overflow(t) = MAX[ S(t-1) + V_collect(t) − Q_supply(t) − S_cap , 0 ]
C41: Overflow is zero unless the incoming volume, net of what is drawn out, would push storage above capacity.
B43: Eq. 7 | C43: Shortage (Unmet Demand)
C44: Q_shortage(t) = Q_demand(t) − Q_supply(t)
C45: Non-negative by construction because Q_supply <= Q_demand always.
B47: Eq. 8 | C47: Water Supply Reliability
C48: R = SUM[ Q_supply(t) ] / SUM[ Q_demand(t) ] over the analysis period
C49: Volumetric reliability: the fraction of total annual demand actually met by the system. An alternative time-based reliability (fraction of days with zero shortage) is reported alongside it on the Dashboard for comparison.
B51: Eq. 9 | C51: Tank Utilization
C52: U = S_avg / S_cap
C53: S_avg | D53: Time-averaged storage level over the period
C54: Indicates how much of the installed capacity is actually being used on average; a persistently low U across a full year signals the tank may be oversized.
B56: Eq. 10 | C56: Annual Water & Cost Savings
C57: Savings_L = SUM[ Q_supply(t) ] Savings_PKR = Savings_L × Tariff
C58: Savings are valued at the avoided cost of municipal/tanker water the household would otherwise have purchased.
B60: Eq. 11 | C60: Simple Payback Period
C61: Payback = (Capital Cost + Installation Cost) / Annual Net Savings
C62: A first-order screening metric. Sheet 9 (Economics) supplements this with NPV and IRR, which properly discount cash flows over the full project life.
B66: DESIGN ASSUMPTIONS
B68: A1 | C68: Rainfall is uniformly distributed within each rain-day.
C69: Why reasonable: Sub-daily intensity data is rarely available for preliminary design; treating each rain-day as a single depth is standard for a screening-level water balance and does not affect annual totals.
B71: A2 | C71: Monthly rainfall is spread across a fixed number of rain-days per month, evenly spaced.
C72: Why reasonable: This approximates real storm clustering (Karachi's monsoon in Jul-Aug) without requiring a historical daily record. Replace the Rainfall Data daily block with observed station data for a detailed design.
B74: A3 | C74: Demand is constant day-to-day unless the user overrides it.
C75: Why reasonable: Non-potable demand (flushing, washing, irrigation) is far steadier than potable demand; a constant daily draw is a reasonable simplification for sizing.
B77: A4 | C77: No evaporation losses are modeled in the tank balance.
C78: Why reasonable: Tanks in this design are assumed closed/covered (standard practice for potable-adjacent storage in Pakistan), making evaporation negligible relative to inflow/outflow volumes.
B80: A5 | C80: No leakage from the tank or piping.
C81: Why reasonable: A well-installed, inspected system should have negligible leakage; the Annual Maintenance Cost input implicitly covers minor repairs that would otherwise introduce loss.
B83: A6 | C83: First-flush diversion is optional and, when enabled, removes a fixed depth (mm) at the start of every rain-day.
C84: Why reasonable: Simpler than a volume-based diverter but standard for preliminary sizing; the depth is adjustable in Inputs.
B86: A7 | C86: Pump efficiency affects only the energy cost line in the Economics sheet, not the water balance.
C87: Why reasonable: The water balance is gravity/volume based; pumping is a downstream energy cost, not a water-loss mechanism, unless the user separately models pump-limited delivery.
B89: A8 | C89: The runoff coefficient (C) is treated as constant year-round.
C90: Why reasonable: In reality C varies slightly with rainfall intensity and roof wetness; a constant value is standard for annual-scale water balance models.

Sheet Tank Optimization
B2: TANK SIZE OPTIMIZATION - Excel Solver Setup
B4: OBJECTIVE
B5: Maximize Annual Water Supplied (Monthly Summary!F18) by adjusting Tank Capacity (Inputs!C19), subject to practical and physical constraints.
B7: SOLVER SETUP -STEP BY STEP
B8: 1. Data tab -> Analysis group -> Solver. (If not visible: File -> Options -> Add-ins -> Manage: Excel Add-ins -> Go -> check Solver Add-in -> OK.)
B9: 2. Set Objective: click the cell selector and choose Monthly Summary!$F$18 (Annual Water Supplied).
B10: 3. To: select Max.
B11: 4. By Changing Variable Cells: select Inputs!$C$19 (Tank Capacity).
B12: 5. Add Constraint: Inputs!$C$19 >= 500 (minimum practical tank size, litres).
B13: 6. Add Constraint: Inputs!$C$19 <= 20000 (maximum practical tank size for a residential roof, litres).
B14: 7. Add Constraint: Inputs!$C$19 = integer (optional -commercial tank sizes are sold in discrete increments).
B15: 8. Select Solving Method: GRG Nonlinear (the MIN/MAX logic in the daily balance is piecewise-linear, which GRG handles well; Simplex LP is not valid because of the MIN/MAX terms).
... B23: CONSTRAINT SUMMARY
B24: Constraint | C24: Cell | D24: Type | E24: Value
B25: Tank capacity - lower bound | C25: Inputs!C19 | D25: >= | E25: 500 L
B26: Tank capacity - upper bound | C26: Inputs!C19 | D26: <= | E26: 20,000 L
B27: Storage cannot exceed capacity | C27: Daily Simulation!K6:K370 | D27: <= | E27: Inputs!C19 (enforced by MIN() in the balance formula)
B28: Storage cannot be negative | C28: Daily Simulation!K6:K370 | D28: >= | E28: 0 (enforced by MAX() in the balance formula)
B30: TANK SIZE SWEEP - Approximate Monthly Balance (for chart / cross-check only)
B31: Independent of Solver: recomputes a simplified MONTHLY mass balance (12 steps, not 365) for each candidate tank size, so this table updates live and the curve shape can be sanity-checked against the Solver's daily-resolution result.
B33: Tank Size (L) | C33: Est. Annual Supplied (L) | D33: Est. Annual Overflow (L) | E33: Est. Annual Shortage (L) | F33: Est. Reliability | G33: Marginal Gain vs prior step (L)
B34: 500 | C34: =MIN(DailyDemand_L*INDEX('Rainfall Data'!$E$15:$E$26,1),MAX(TankInitial_L+INDEX(ActiveMonthlyRain,1)*RoofArea_m2*CollectionEff-DeadStorage_L,0))+MIN(DailyDemand_L*INDEX('Rainfall Data'!$E$15:$E$26,2),MAX(M34+INDEX(ActiveMonthlyRain,2)*RoofArea_m2*CollectionEff-DeadStorage_L,0))+MIN(DailyDemand_L*INDEX('Rainfall Data'!$E$15:$E$26,3),MAX(N34+INDEX(ActiveMonthlyRain,3)*RoofArea_m2*CollectionEff-DeadStorage_L,0))+MIN(DailyDemand_L*INDEX('Rainfall Data'!$E$15:$E$26,4),MAX(O34+INDEX(ActiveMonthlyRain,4)*RoofArea_m2*CollectionEff-DeadStorage_L,0))+MIN(DailyDemand_L*INDEX('Rainfall Data'!$E$15:$E$26,5),MAX(P34+INDEX(ActiveMonthlyRain,5)*RoofArea_m2*CollectionEff-DeadStorage_L,0))+MIN(DailyDemand_L*INDEX('Rainfall Data'!$E$15:$E$26,6),MAX(Q34+INDEX(ActiveMonthlyRain,6)*RoofArea_m2*CollectionEff-DeadStorage_L,0))+MIN(DailyDemand_L*INDEX('Rainfall Data'!$E$15:$E$26,7),MAX(R34+INDEX(ActiveMonthlyRain,7)*RoofArea_m2*CollectionEff-DeadStorage_L,0))+MIN(DailyDemand_L*INDEX('Rainfall Data'!$E$15:$E$26,8),MAX(S34+INDEX(ActiveMonthlyRain,8)*RoofArea_m2*CollectionEff-DeadStorage_L,0))+MIN(DailyDemand_L*INDEX('Rainfall Data'!$E$15:$E$26,9),MAX(T34+INDEX(ActiveMonthlyRain,9)*RoofArea_m2*CollectionEff-DeadStorage_L,0))+MIN(DailyDemand_L*INDEX('Rainfall Data'!$E$15:$E$26,10),MAX(U34+INDEX(ActiveMonthlyRain,10)*RoofArea_m2*CollectionEff-DeadStorage_L,0))+MIN(DailyDemand_L*INDEX('Rainfall Data'!$E$15:$E$26,11),MAX(V34+INDEX(ActiveMonthlyRain,11)*RoofArea_m2*CollectionEff-DeadStorage_L,0))+MIN(DailyDemand_L*INDEX('Rainfall Data'!$E$15:$E$26,12),MAX(W34+INDEX(ActiveMonthlyRain,12)*RoofArea_m2*CollectionEff-DeadStorage_L,0)) -> 22326.576 | D34: =MAX(TankInitial_L+INDEX(ActiveMonthlyRain,1)*RoofArea_m2*CollectionEff-MIN(DailyDemand_L*INDEX('Rainfall Data'!$E$15:$E$26,1),MAX(TankInitial_L+INDEX(ActiveMonthlyRain,1)*RoofArea_m2*CollectionEff-DeadStorage_L,0))-$B34,0)+MAX(M34+INDEX(ActiveMonthlyRain,2)*RoofArea_m2*CollectionEff-MIN(DailyDemand_L*INDEX('Rainfall Data'!$E$15:$E$26,2),MAX(M34+INDEX(ActiveMonthlyRain,2)*RoofArea_m2*CollectionEff-DeadStorage_L,0))-$B34,0)+MAX(N34+INDEX(ActiveMonthlyRain,3)*RoofArea_m2*CollectionEff-MIN(DailyDemand_L*INDEX('Rainfall Data'!$E$15:$E$26,3),MAX(N34+INDEX(ActiveMonthlyRain,3)*RoofArea_m2*CollectionEff-DeadStorage_L,0))-$B34,0)+MAX(O34+INDEX(ActiveMonthlyRain,4)*RoofArea_m2*CollectionEff-MIN(DailyDemand_L*INDEX('Rainfall Data'!$E$15:$E$26,4),MAX(O34+INDEX(ActiveMonthlyRain,4)*RoofArea_m2*CollectionEff-DeadStorage_L,0))-$B34,0)+MAX(P34+INDEX(ActiveMonthlyRain,5)*RoofArea_m2*CollectionEff-MIN(DailyDemand_L*INDEX('Rainfall Data'!$E$15:$E$26,5),MAX(P34+INDEX(ActiveMonthlyRain,5)*RoofArea_m2*CollectionEff-DeadStorage_L,0))-$B34,0)+MAX(Q34+INDEX(ActiveMonthlyRain,6)*RoofArea_m2*CollectionEff-MIN(DailyDemand_L*INDEX('Rainfall Data'!$E$15:$E$26,6),MAX(Q34+INDEX(ActiveMonthlyRain,6)*RoofArea_m2*CollectionEff-DeadStorage_L,0))-$B34,0)+MAX(R34+INDEX(ActiveMonthlyRain,7)*RoofArea_m2*CollectionEff-MIN(DailyDemand_L*INDEX('Rainfall Data'!$E$15:$E$26,7),MAX(R34+INDEX(ActiveMonthlyRain,7)*RoofArea_m2*CollectionEff-DeadStorage_L,0))-$B34,0)+MAX(S34+INDEX(ActiveMonthlyRain,8)*RoofArea_m2*CollectionEff-MIN(DailyDemand_L*INDEX('Rainfall Data'!$E$15:$E$26,8),MAX(S34+INDEX(ActiveMonthlyRain,8)*RoofArea_m2*CollectionEff-DeadStorage_L,0))-$B34,0)+MAX(T34+INDEX(ActiveMonthlyRain,9)*RoofArea_m2*CollectionEff-MIN(DailyDemand_L*INDEX('Rainfall Data'!$E$15:$E$26,9),MAX(T34+INDEX(ActiveMonthlyRain,9)*RoofArea_m2*CollectionEff-DeadStorage_L,0))-$B34,0)+MAX(U34+INDEX(ActiveMonthlyRain,10)*RoofArea_m2*CollectionEff-MIN(DailyDemand_L*INDEX('Rainfall Data'!$E$15:$E$26,10),MAX(U34+INDEX(ActiveMonthlyRain,10)*RoofArea_m2*CollectionEff-DeadStorage_L,0))-$B34,0)+MAX(V34+INDEX(ActiveMonthlyRain,11)*RoofArea_m2*CollectionEff-MIN(DailyDemand_L*INDEX('Rainfall Data'!$E$15:$E$26,11),MAX(V34+INDEX(ActiveMonthlyRain,11)*RoofArea_m2*CollectionEff-DeadStorage_L,0))-$B34,0)+MAX(W34+INDEX(ActiveMonthlyRain,12)*RoofArea_m2*CollectionEff-MIN(DailyDemand_L*INDEX('Rainfall Data'!$E$15:$E$26,12),MAX(W34+INDEX(ActiveMonthlyRain,12)*RoofArea_m2*CollectionEff-DeadStorage_L,0))-$B34,0) -> 3783.101 | E34: =SUMPRODUCT(DailyDemand_L*'Rainfall Data'!$E$15:$E$26)-C34 -> 76223.424 | F34: =C34/SUMPRODUCT(DailyDemand_L*'Rainfall Data'!$E$15:$E$26) -> 0.22655075 | M34: =MIN(MAX(TankInitial_L+INDEX(ActiveMonthlyRain,1)*RoofArea_m2*CollectionEff-DailyDemand_L*INDEX('Rainfall Data'!$E$15:$E$26,1),0),$B34) -> 0 | N34: =MIN(MAX(M34+INDEX(ActiveMonthlyRain,2)*RoofArea_m2*CollectionEff-DailyDemand_L*INDEX('Rainfall Data'!$E$15:$E$26,2),0),$B34) -> 0 | O34: =MIN(MAX(N34+INDEX(ActiveMonthlyRain,3)*RoofArea_m2*CollectionEff-DailyDemand_L*INDEX('Rainfall Data'!$E$15:$E$26,3),0),$B34) -> 0 | P34: =MIN(MAX(O34+INDEX(ActiveMonthlyRain,4)*RoofArea_m2*CollectionEff-DailyDemand_L*INDEX('Rainfall Data'!$E$15:$E$26,4),0),$B34) -> 0 | Q34: =MIN(MAX(P34+INDEX(ActiveMonthlyRain,5)*RoofArea_m2*CollectionEff-DailyDemand_L*INDEX('Rainfall Data'!$E$15:$E$26,5),0),$B34) -> 0 | R34: =MIN(MAX(Q34+INDEX(ActiveMonthlyRain,6)*RoofArea_m2*CollectionEff-DailyDemand_L*INDEX('Rainfall Data'!$E$15:$E$26,6),0),$B34) -> 0 | S34: =MIN(MAX(R34+INDEX(ActiveMonthlyRain,7)*RoofArea_m2*CollectionEff-DailyDemand_L*INDEX('Rainfall Data'!$E$15:$E$26,7),0),$B34) -> 500 | T34: =MIN(MAX(S34+INDEX(ActiveMonthlyRain,8)*RoofArea_m2*CollectionEff-DailyDemand_L*INDEX('Rainfall Data'!$E$15:$E$26,8),0),$B34) -> 500 | U34: =MIN(MAX(T34+INDEX(ActiveMonthlyRain,9)*RoofArea_m2*CollectionEff-DailyDemand_L*INDEX('Rainfall Data'!$E$15:$E$26,9),0),$B34) -> 0 | V34: =MIN(MAX(U34+INDEX(ActiveMonthlyRain,10)*RoofArea_m2*CollectionEff-DailyDemand_L*INDEX('Rainfall Data'!$E$15:$E$26,10),0),$B34) -> 0 | W34: =MIN(MAX(V34+INDEX(ActiveMonthlyRain,11)*RoofArea_m2*CollectionEff-DailyDemand_L*INDEX('Rainfall Data'!$E$15:$E$26,11),0),$B34) -> 0 | X34: =MIN(MAX(W34+INDEX(ActiveMonthlyRain,12)*RoofArea_m2*CollectionEff-DailyDemand_L*INDEX('Rainfall Data'!$E$15:$E$26,12),0),$B34) -> 0
B35: 1000 | C35: =MIN(DailyDemand_L*INDEX('Rainfall Data'!$E$15:$E$26,1),MAX(TankInitial_L+INDEX(ActiveMonthlyRain,1)*RoofArea_m2*CollectionEff-DeadStorage_L,0))+MIN(DailyDemand_L*INDEX('Rainfall Data'!$E$15:$E$26,2),MAX(M35+INDEX(ActiveMonthlyRain,2)*RoofArea_m2*CollectionEff-DeadStorage_L,0))+MIN(DailyDemand_L*INDEX('Rainfall Data'!$E$15:$E$26,3),MAX(N35+INDEX(ActiveMonthlyRain,3)*RoofArea_m2*CollectionEff-DeadStorage_L,0))+MIN(DailyDemand_L*INDEX('Rainfall Data'!$E$15:$E$26,4),MAX(O35+INDEX(ActiveMonthlyRain,4)*RoofArea_m2*CollectionEff-DeadStorage_L,0))+MIN(DailyDemand_L*INDEX('Rainfall Data'!$E$15:$E$26,5),MAX(P35+INDEX(ActiveMonthlyRain,5)*RoofArea_m2*CollectionEff-DeadStorage_L,0))+MIN(DailyDemand_L*INDEX('Rainfall Data'!$E$15:$E$26,6),MAX(Q35+INDEX(ActiveMonthlyRain,6)*RoofArea_m2*CollectionEff-DeadStorage_L,0))+MIN(DailyDemand_L*INDEX('Rainfall Data'!$E$15:$E$26,7),MAX(R35+INDEX(ActiveMonthlyRain,7)*RoofArea_m2*CollectionEff-DeadStorage_L,0))+MIN(DailyDemand_L*INDEX('Rainfall Data'!$E$15:$E$26,8),MAX(S35+INDEX(ActiveMonthlyRain,8)*RoofArea_m2*CollectionEff-DeadStorage_L,0))+MIN(DailyDemand_L*INDEX('Rainfall Data'!$E$15:$E$26,9),MAX(T35+INDEX(ActiveMonthlyRain,9)*RoofArea_m2*CollectionEff-DeadStorage_L,0))+MIN(DailyDemand_L*INDEX('Rainfall Data'!$E$15:$E$26,10),MAX(U35+INDEX(ActiveMonthlyRain,10)*RoofArea_m2*CollectionEff-DeadStorage_L,0))+MIN(DailyDemand_L*INDEX('Rainfall Data'!$E$15:$E$26,11),MAX(V35+INDEX(ActiveMonthlyRain,11)*RoofArea_m2*CollectionEff-DeadStorage_L,0))+MIN(DailyDemand_L*INDEX('Rainfall Data'!$E$15:$E$26,12),MAX(W35+INDEX(ActiveMonthlyRain,12)*RoofArea_m2*CollectionEff-DeadStorage_L,0)) -> 22826.576 | D35: =MAX(TankInitial_L+INDEX(ActiveMonthlyRain,1)*RoofArea_m2*CollectionEff-MIN(DailyDemand_L*INDEX('Rainfall Data'!$E$15:$E$26,1),MAX(TankInitial_L+INDEX(ActiveMonthlyRain,1)*RoofArea_m2*CollectionEff-DeadStorage_L,0))-$B35,0)+MAX(M35+INDEX(ActiveMonthlyRain,2)*RoofArea_m2*CollectionEff-MIN(DailyDemand_L*INDEX('Rainfall Data'!$E$15:$E$26,2),MAX(M35+INDEX(ActiveMonthlyRain,2)*RoofArea_m2*CollectionEff-DeadStorage_L,0))-$B35,0)+MAX(N35+INDEX(ActiveMonthlyRain,3)*RoofArea_m2*CollectionEff-MIN(DailyDemand_L*INDEX('Rainfall Data'!$E$15:$E$26,3),MAX(N35+INDEX(ActiveMonthlyRain,3)*RoofArea_m2*CollectionEff-DeadStorage_L,0))-$B35,0)+MAX(O35+INDEX(ActiveMonthlyRain,4)*RoofArea_m2*CollectionEff-MIN(DailyDemand_L*INDEX('Rainfall Data'!$E$15:$E$26,4),MAX(O35+INDEX(ActiveMonthlyRain,4)*RoofArea_m2*CollectionEff-DeadStorage_L,0))-$B35,0)+MAX(P35+INDEX(ActiveMonthlyRain,5)*RoofArea_m2*CollectionEff-MIN(DailyDemand_L*INDEX('Rainfall Data'!$E$15:$E$26,5),MAX(P35+INDEX(ActiveMonthlyRain,5)*RoofArea_m2*CollectionEff-DeadStorage_L,0))-$B35,0)+MAX(Q35+INDEX(ActiveMonthlyRain,6)*RoofArea_m2*CollectionEff-MIN(DailyDemand_L*INDEX('Rainfall Data'!$E$15:$E$26,6),MAX(Q35+INDEX(ActiveMonthlyRain,6)*RoofArea_m2*CollectionEff-DeadStorage_L,0))-$B35,0)+MAX(R35+INDEX(ActiveMonthlyRain,7)*RoofArea_m2*CollectionEff-MIN(DailyDemand_L*INDEX('Rainfall Data'!$E$15:$E$26,7),MAX(R35+INDEX(ActiveMonthlyRain,7)*RoofArea_m2*CollectionEff-DeadStorage_L,0))-$B35,0)+MAX(S35+INDEX(ActiveMonthlyRain,8)*RoofArea_m2*CollectionEff-MIN(DailyDemand_L*INDEX('Rainfall Data'!$E$15:$E$26,8),MAX(S35+INDEX(ActiveMonthlyRain,8)*RoofArea_m2*CollectionEff-DeadStorage_L,0))-$B35,0)+MAX(T35+INDEX(ActiveMonthlyRain,9)*RoofArea_m2*CollectionEff-MIN(DailyDemand_L*INDEX('Rainfall Data'!$E$15:$E$26,9),MAX(T35+INDEX(ActiveMonthlyRain,9)*RoofArea_m2*CollectionEff-DeadStorage_L,0))-$B35,0)+MAX(U35+INDEX(ActiveMonthlyRain,10)*RoofArea_m2*CollectionEff-MIN(DailyDemand_L*INDEX('Rainfall Data'!$E$15:$E$26,10),MAX(U35+INDEX(ActiveMonthlyRain,10)*RoofArea_m2*CollectionEff-DeadStorage_L,0))-$B35,0)+MAX(V35+INDEX(ActiveMonthlyRain,11)*RoofArea_m2*CollectionEff-MIN(DailyDemand_L*INDEX('Rainfall Data'!$E$15:$E$26,11),MAX(V35+INDEX(ActiveMonthlyRain,11)*RoofArea_m2*CollectionEff-DeadStorage_L,0))-$B35,0)+MAX(W35+INDEX(ActiveMonthlyRain,12)*RoofArea_m2*CollectionEff-MIN(DailyDemand_L*INDEX('Rainfall Data'!$E$15:$E$26,12),MAX(W35+INDEX(ActiveMonthlyRain,12)*RoofArea_m2*CollectionEff-DeadStorage_L,0))-$B35,0) -> 3283.101 | E35: =SUMPRODUCT(DailyDemand_L*'Rainfall Data'!$E$15:$E$26)-C35 -> 75723.424 | F35: =C35/SUMPRODUCT(DailyDemand_L*'Rainfall Data'!$E$15:$E$26) -> 0.23162432 | G35: =C35-C34 -> 500 | M35: =MIN(MAX(TankInitial_L+INDEX(ActiveMonthlyRain,1)*RoofArea_m2*CollectionEff-DailyDemand_L*INDEX('Rainfall Data'!$E$15:$E$26,1),0),$B35) -> 0 | N35: =MIN(MAX(M35+INDEX(ActiveMonthlyRain,2)*RoofArea_m2*CollectionEff-DailyDemand_L*INDEX('Rainfall Data'!$E$15:$E$26,2),0),$B35) -> 0 | O35: =MIN(MAX(N35+INDEX(ActiveMonthlyRain,3)*RoofArea_m2*CollectionEff-DailyDemand_L*INDEX('Rainfall Data'!$E$15:$E$26,3),0),$B35) -> 0 | P35: =MIN(MAX(O35+INDEX(ActiveMonthlyRain,4)*RoofArea_m2*CollectionEff-DailyDemand_L*INDEX('Rainfall Data'!$E$15:$E$26,4),0),$B35) -> 0 | Q35: =MIN(MAX(P35+INDEX(ActiveMonthlyRain,5)*RoofArea_m2*CollectionEff-DailyDemand_L*INDEX('Rainfall Data'!$E$15:$E$26,5),0),$B35) -> 0 | R35: =MIN(MAX(Q35+INDEX(ActiveMonthlyRain,6)*RoofArea_m2*CollectionEff-DailyDemand_L*INDEX('Rainfall Data'!$E$15:$E$26,6),0),$B35) -> 0 | S35: =MIN(MAX(R35+INDEX(ActiveMonthlyRain,7)*RoofArea_m2*CollectionEff-DailyDemand_L*INDEX('Rainfall Data'!$E$15:$E$26,7),0),$B35) -> 1000 | T35: =MIN(MAX(S35+INDEX(ActiveMonthlyRain,8)*RoofArea_m2*CollectionEff-DailyDemand_L*INDEX('Rainfall Data'!$E$15:$E$26,8),0),$B35) -> 1000 | U35: =MIN(MAX(T35+INDEX(ActiveMonthlyRain,9)*RoofArea_m2*CollectionEff-DailyDemand_L*INDEX('Rainfall Data'!$E$15:$E$26,9),0),$B35) -> 0 | V35: =MIN(MAX(U35+INDEX(ActiveMonthlyRain,10)*RoofArea_m2*CollectionEff-DailyDemand_L*INDEX('Rainfall Data'!$E$15:$E$26,10),0),$B35) -> 0 | W35: =MIN(MAX(V35+INDEX(ActiveMonthlyRain,11)*RoofArea_m2*CollectionEff-DailyDemand_L*INDEX('Rainfall Data'!$E$15:$E$26,11),0),$B35) -> 0 | X35: =MIN(MAX(W35+INDEX(ActiveMonthlyRain,12)*RoofArea_m2*CollectionEff-DailyDemand_L*INDEX('Rainfall Data'!$E$15:$E$26,12),0),$B35) -> 0
B36: 1500 | C36: =MIN(DailyDemand_L*INDEX('Rainfall Data'!$E$15:$E$26,1),MAX(TankInitial_L+INDEX(ActiveMonthlyRain,1)*RoofArea_m2*CollectionEff-DeadStorage_L,0))+MIN(DailyDemand_L*INDEX('Rainfall Data'!$E$15:$E$26,2),MAX(M36+INDEX(ActiveMonthlyRain,2)*RoofArea_m2*CollectionEff-DeadStorage_L,0))+MIN(DailyDemand_L*INDEX('Rainfall Data'!$E$15:$E$26,3),MAX(N36+INDEX(ActiveMonthlyRain,3)*RoofArea_m2*CollectionEff-DeadStorage_L,0))+MIN(DailyDemand_L*INDEX('Rainfall Data'!$E$15:$E$26,4),MAX(O36+INDEX(ActiveMonthlyRain,4)*RoofArea_m2*CollectionEff-DeadStorage_L,0))+MIN(DailyDemand_L*INDEX('Rainfall Data'!$E$15:$E$26,5),MAX(P36+INDEX(ActiveMonthlyRain,5)*RoofArea_m2*CollectionEff-DeadStorage_L,0))+MIN(DailyDemand_L*INDEX('Rainfall Data'!$E$15:$E$26,6),MAX(Q36+INDEX(ActiveMonthlyRain,6)*RoofArea_m2*CollectionEff-DeadStorage_L,0))+MIN(DailyDemand_L*INDEX('Rainfall Data'!$E$15:$E$26,7),MAX(R36+INDEX(ActiveMonthlyRain,7)*RoofArea_m2*CollectionEff-DeadStorage_L,0))+MIN(DailyDemand_L*INDEX('Rainfall Data'!$E$15:$E$26,8),MAX(S36+INDEX(ActiveMonthlyRain,8)*RoofArea_m2*CollectionEff-DeadStorage_L,0))+MIN(DailyDemand_L*INDEX('Rainfall Data'!$E$15:$E$26,9),MAX(T36+INDEX(ActiveMonthlyRain,9)*RoofArea_m2*CollectionEff-DeadStorage_L,0))+MIN(DailyDemand_L*INDEX('Rainfall Data'!$E$15:$E$26,10),MAX(U36+INDEX(ActiveMonthlyRain,10)*RoofArea_m2*CollectionEff-DeadStorage_L,0))+MIN(DailyDemand_L*INDEX('Rainfall Data'!$E$15:$E$26,11),MAX(V36+INDEX(ActiveMonthlyRain,11)*RoofArea_m2*CollectionEff-DeadStorage_L,0))+MIN(DailyDemand_L*INDEX('Rainfall Data'!$E$15:$E$26,12),MAX(W36+INDEX(ActiveMonthlyRain,12)*RoofArea_m2*CollectionEff-DeadStorage_L,0)) -> 23326.576 | D36: =MAX(TankInitial_L+INDEX(ActiveMonthlyRain,1)*RoofArea_m2*CollectionEff-MIN(DailyDemand_L*INDEX('Rainfall Data'!$E$15:$E$26,1),MAX(TankInitial_L+INDEX(ActiveMonthlyRain,1)*RoofArea_m2*CollectionEff-DeadStorage_L,0))-$B36,0)+MAX(M36+INDEX(ActiveMonthlyRain,2)*RoofArea_m2*CollectionEff-MIN(DailyDemand_L*INDEX('Rainfall Data'!$E$15:$E$26,2),MAX(M36+INDEX(ActiveMonthlyRain,2)*RoofArea_m2*CollectionEff-DeadStorage_L,0))-$B36,0)+MAX(N36+INDEX(ActiveMonthlyRain,3)*RoofArea_m2*CollectionEff-MIN(DailyDemand_L*INDEX('Rainfall Data'!$E$15:$E$26,3),MAX(N36+INDEX(ActiveMonthlyRain,3)*RoofArea_m2*CollectionEff-DeadStorage_L,0))-$B36,0)+MAX(O36+INDEX(ActiveMonthlyRain,4)*RoofArea_m2*CollectionEff-MIN(DailyDemand_L*INDEX('Rainfall Data'!$E$15:$E$26,4),MAX(O36+INDEX(ActiveMonthlyRain,4)*RoofArea_m2*CollectionEff-DeadStorage_L,0))-$B36,0)+MAX(P36+INDEX(ActiveMonthlyRain,5)*RoofArea_m2*CollectionEff-MIN(DailyDemand_L*INDEX('Rainfall Data'!$E$15:$E$26,5),MAX(P36+INDEX(ActiveMonthlyRain,5)*RoofArea_m2*CollectionEff-DeadStorage_L,0))-$B36,0)+MAX(Q36+INDEX(ActiveMonthlyRain,6)*RoofArea_m2*CollectionEff-MIN(DailyDemand_L*INDEX('Rainfall Data'!$E$15:$E$26,6),MAX(Q36+INDEX(ActiveMonthlyRain,6)*RoofArea_m2*CollectionEff-DeadStorage_L,0))-$B36,0)+MAX(R36+INDEX(ActiveMonthlyRain,7)*RoofArea_m2*CollectionEff-MIN(DailyDemand_L*INDEX('Rainfall Data'!$E$15:$E$26,7),MAX(R36+INDEX(ActiveMonthlyRain,7)*RoofArea_m2*CollectionEff-DeadStorage_L,0))-$B36,0)+MAX(S36+INDEX(ActiveMonthlyRain,8)*RoofArea_m2*CollectionEff-MIN(DailyDemand_L*INDEX('Rainfall Data'!$E$15:$E$26,8),MAX(S36+INDEX(ActiveMonthlyRain,8)*RoofArea_m2*CollectionEff-DeadStorage_L,0))-$B36,0)+MAX(T36+INDEX(ActiveMonthlyRain,9)*RoofArea_m2*CollectionEff-MIN(DailyDemand_L*INDEX('Rainfall Data'!$E$15:$E$26,9),MAX(T36+INDEX(ActiveMonthlyRain,9)*RoofArea_m2*CollectionEff-DeadStorage_L,0))-$B36,0)+MAX(U36+INDEX(ActiveMonthlyRain,10)*RoofArea_m2*CollectionEff-MIN(DailyDemand_L*INDEX('Rainfall Data'!$E$15:$E$26,10),MAX(U36+INDEX(ActiveMonthlyRain,10)*RoofArea_m2*CollectionEff-DeadStorage_L,0))-$B36,0)+MAX(V36+INDEX(ActiveMonthlyRain,11)*RoofArea_m2*CollectionEff-MIN(DailyDemand_L*INDEX('Rainfall Data'!$E$15:$E$26,11),MAX(V36+INDEX(ActiveMonthlyRain,11)*RoofArea_m2*CollectionEff-DeadStorage_L,0))-$B36,0)+MAX(W36+INDEX(ActiveMonthlyRain,12)*RoofArea_m2*CollectionEff-MIN(DailyDemand_L*INDEX('Rainfall Data'!$E$15:$E$26,12),MAX(W36+INDEX(ActiveMonthlyRain,12)*RoofArea_m2*CollectionEff-DeadStorage_L,0))-$B36,0) -> 2783.101 | E36: =SUMPRODUCT(DailyDemand_L*'Rainfall Data'!$E$15:$E$26)-C36 -> 75223.424 | F36: =C36/SUMPRODUCT(DailyDemand_L*'Rainfall Data'!$E$15:$E$26) -> 0.23669788 | G36: =C36-C35 -> 500 | M36: =MIN(MAX(TankInitial_L+INDEX(ActiveMonthlyRain,1)*RoofArea_m2*CollectionEff-DailyDemand_L*INDEX('Rainfall Data'!$E$15:$E$26,1),0),$B36) -> 0 | N36: =MIN(MAX(M36+INDEX(ActiveMonthlyRain,2)*RoofArea_m2*CollectionEff-DailyDemand_L*INDEX('Rainfall Data'!$E$15:$E$26,2),0),$B36) -> 0 | O36: =MIN(MAX(N36+INDEX(ActiveMonthlyRain,3)*RoofArea_m2*CollectionEff-DailyDemand_L*INDEX('Rainfall Data'!$E$15:$E$26,3),0),$B36) -> 0 | P36: =MIN(MAX(O36+INDEX(ActiveMonthlyRain,4)*RoofArea_m2*CollectionEff-DailyDemand_L*INDEX('Rainfall Data'!$E$15:$E$26,4),0),$B36) -> 0 | Q36: =MIN(MAX(P36+INDEX(ActiveMonthlyRain,5)*RoofArea_m2*CollectionEff-DailyDemand_L*INDEX('Rainfall Data'!$E$15:$E$26,5),0),$B36) -> 0 | R36: =MIN(MAX(Q36+INDEX(ActiveMonthlyRain,6)*RoofArea_m2*CollectionEff-DailyDemand_L*INDEX('Rainfall Data'!$E$15:$E$26,6),0),$B36) -> 0 | S36: =MIN(MAX(R36+INDEX(ActiveMonthlyRain,7)*RoofArea_m2*CollectionEff-DailyDemand_L*INDEX('Rainfall Data'!$E$15:$E$26,7),0),$B36) -> 1500 | T36: =MIN(MAX(S36+INDEX(ActiveMonthlyRain,8)*RoofArea_m2*CollectionEff-DailyDemand_L*INDEX('Rainfall Data'!$E$15:$E$26,8),0),$B36) -> 1500 | U36: =MIN(MAX(T36+INDEX(ActiveMonthlyRain,9)*RoofArea_m2*CollectionEff-DailyDemand_L*INDEX('Rainfall Data'!$E$15:$E$26,9),0),$B36) -> 0 | V36: =MIN(MAX(U36+INDEX(ActiveMonthlyRain,10)*RoofArea_m2*CollectionEff-DailyDemand_L*INDEX('Rainfall Data'!$E$15:$E$26,10),0),$B36) -> 0 | W36: =MIN(MAX(V36+INDEX(ActiveMonthlyRain,11)*RoofArea_m2*CollectionEff-DailyDemand_L*INDEX('Rainfall Data'!$E$15:$E$26,11),0),$B36) -> 0 | X36: =MIN(MAX(W36+INDEX(ActiveMonthlyRain,12)*RoofArea_m2*CollectionEff-DailyDemand_L*INDEX('Rainfall Data'!$E$15:$E$26,12),0),$B36) -> 0
B37: 2000 | C37: =MIN(DailyDemand_L*INDEX('Rainfall Data'!$E$15:$E$26,1),MAX(TankInitial_L+INDEX(ActiveMonthlyRain,1)*RoofArea_m2*CollectionEff-DeadStorage_L,0))+MIN(DailyDemand_L*INDEX('Rainfall Data'!$E$15:$E$26,2),MAX(M37+INDEX(ActiveMonthlyRain,2)*RoofArea_m2*CollectionEff-DeadStorage_L,0))+MIN(DailyDemand_L*INDEX('Rainfall Data'!$E$15:$E$26,3),MAX(N37+INDEX(ActiveMonthlyRain,3)*RoofArea_m2*CollectionEff-DeadStorage_L,0))+MIN(DailyDemand_L*INDEX('Rainfall Data'!$E$15:$E$26,4),MAX(O37+INDEX(ActiveMonthlyRain,4)*RoofArea_m2*CollectionEff-DeadStorage_L,0))+MIN(DailyDemand_L*INDEX('Rainfall Data'!$E$15:$E$26,5),MAX(P37+INDEX(ActiveMonthlyRain,5)*RoofArea_m2*CollectionEff-DeadStorage_L,0))+MIN(DailyDemand_L*INDEX('Rainfall Data'!$E$15:$E$26,6),MAX(Q37+INDEX(ActiveMonthlyRain,6)*RoofArea_m2*CollectionEff-DeadStorage_L,0))+MIN(DailyDemand_L*INDEX('Rainfall Data'!$E$15:$E$26,7),MAX(R37+INDEX(ActiveMonthlyRain,7)*RoofArea_m2*CollectionEff-DeadStorage_L,0))+MIN(DailyDemand_L*INDEX('Rainfall Data'!$E$15:$E$26,8),MAX(S37+INDEX(ActiveMonthlyRain,8)*RoofArea_m2*CollectionEff-DeadStorage_L,0))+MIN(DailyDemand_L*INDEX('Rainfall Data'!$E$15:$E$26,9),MAX(T37+INDEX(ActiveMonthlyRain,9)*RoofArea_m2*CollectionEff-DeadStorage_L,0))+MIN(DailyDemand_L*INDEX('Rainfall Data'!$E$15:$E$26,10),MAX(U37+INDEX(ActiveMonthlyRain,10)*RoofArea_m2*CollectionEff-DeadStorage_L,0))+MIN(DailyDemand_L*INDEX('Rainfall Data'!$E$15:$E$26,11),MAX(V37+INDEX(ActiveMonthlyRain,11)*RoofArea_m2*CollectionEff-DeadStorage_L,0))+MIN(DailyDemand_L*INDEX('Rainfall Data'!$E$15:$E$26,12),MAX(W37+INDEX(ActiveMonthlyRain,12)*RoofArea_m2*CollectionEff-DeadStorage_L,0)) -> 23826.576 | D37: =MAX(TankInitial_L+INDEX(ActiveMonthlyRain,1)*RoofArea_m2*CollectionEff-MIN(DailyDemand_L*INDEX('Rainfall Data'!$E$15:$E$26,1),MAX(TankInitial_L+INDEX(ActiveMonthlyRain,1)*RoofArea_m2*CollectionEff-DeadStorage_L,0))-$B37,0)+MAX(M37+INDEX(ActiveMonthlyRain,2)*RoofArea_m2*CollectionEff-MIN(DailyDemand_L*INDEX('Rainfall Data'!$E$15:$E$26,2),MAX(M37+INDEX(ActiveMonthlyRain,2)*RoofArea_m2*CollectionEff-DeadStorage_L,0))-$B37,0)+MAX(N37+INDEX(ActiveMonthlyRain,3)*RoofArea_m2*CollectionEff-MIN(DailyDemand_L*INDEX('Rainfall Data'!$E$15:$E$26,3),MAX(N37+INDEX(ActiveMonthlyRain,3)*RoofArea_m2*CollectionEff-DeadStorage_L,0))-$B37,0)+MAX(O37+INDEX(ActiveMonthlyRain,4)*RoofArea_m2*CollectionEff-MIN(DailyDemand_L*INDEX('Rainfall Data'!$E$15:$E$26,4),MAX(O37+INDEX(ActiveMonthlyRain,4)*RoofArea_m2*CollectionEff-DeadStorage_L,0))-$B37,0)+MAX(P37+INDEX(ActiveMonthlyRain,5)*RoofArea_m2*CollectionEff-MIN(DailyDemand_L*INDEX('Rainfall Data'!$E$15:$E$26,5),MAX(P37+INDEX(ActiveMonthlyRain,5)*RoofArea_m2*CollectionEff-DeadStorage_L,0))-$B37,0)+MAX(Q37+INDEX(ActiveMonthlyRain,6)*RoofArea_m2*CollectionEff-MIN(DailyDemand_L*INDEX('Rainfall Data'!$E$15:$E$26,6),MAX(Q37+INDEX(ActiveMonthlyRain,6)*RoofArea_m2*CollectionEff-DeadStorage_L,0))-$B37,0)+MAX(R37+INDEX(ActiveMonthlyRain,7)*RoofArea_m2*CollectionEff-MIN(DailyDemand_L*INDEX('Rainfall Data'!$E$15:$E$26,7),MAX(R37+INDEX(ActiveMonthlyRain,7)*RoofArea_m2*CollectionEff-DeadStorage_L,0))-$B37,0)+MAX(S37+INDEX(ActiveMonthlyRain,8)*RoofArea_m2*CollectionEff-MIN(DailyDemand_L*INDEX('Rainfall Data'!$E$15:$E$26,8),MAX(S37+INDEX(ActiveMonthlyRain,8)*RoofArea_m2*CollectionEff-DeadStorage_L,0))-$B37,0)+MAX(T37+INDEX(ActiveMonthlyRain,9)*RoofArea_m2*CollectionEff-MIN(DailyDemand_L*INDEX('Rainfall Data'!$E$15:$E$26,9),MAX(T37+INDEX(ActiveMonthlyRain,9)*RoofArea_m2*CollectionEff-DeadStorage_L,0))-$B37,0)+MAX(U37+INDEX(ActiveMonthlyRain,10)*RoofArea_m2*CollectionEff-MIN(DailyDemand_L*INDEX('Rainfall Data'!$E$15:$E$26,10),MAX(U37+INDEX(ActiveMonthlyRain,10)*RoofArea_m2*CollectionEff-DeadStorage_L,0))-$B37,0)+MAX(V37+INDEX(ActiveMonthlyRain,11)*RoofArea_m2*CollectionEff-MIN(DailyDemand_L*INDEX('Rainfall Data'!$E$15:$E$26,11),MAX(V37+INDEX(ActiveMonthlyRain,11)*RoofArea_m2*CollectionEff-DeadStorage_L,0))-$B37,0)+MAX(W37+INDEX(ActiveMonthlyRain,12)*RoofArea_m2*CollectionEff-MIN(DailyDemand_L*INDEX('Rainfall Data'!$E$15:$E$26,12),MAX(W37+INDEX(ActiveMonthlyRain,12)*RoofArea_m2*CollectionEff-DeadStorage_L,0))-$B37,0) -> 2283.101 | E37: =SUMPRODUCT(DailyDemand_L*'Rainfall Data'!$E$15:$E$26)-C37 -> 74723.424 | F37: =C37/SUMPRODUCT(DailyDemand_L*'Rainfall Data'!$E$15:$E$26) -> 0.24177145 | G37: =C37-C36 -> 500 | M37: =MIN(MAX(TankInitial_L+INDEX(ActiveMonthlyRain,1)*RoofArea_m2*CollectionEff-DailyDemand_L*INDEX('Rainfall Data'!$E$15:$E$26,1),0),$B37) -> 0 | N37: =MIN(MAX(M37+INDEX(ActiveMonthlyRain,2)*RoofArea_m2*CollectionEff-DailyDemand_L*INDEX('Rainfall Data'!$E$15:$E$26,2),0),$B37) -> 0 | O37: =MIN(MAX(N37+INDEX(ActiveMonthlyRain,3)*RoofArea_m2*CollectionEff-DailyDemand_L*INDEX('Rainfall Data'!$E$15:$E$26,3),0),$B37) -> 0 | P37: =MIN(MAX(O37+INDEX(ActiveMonthlyRain,4)*RoofArea_m2*CollectionEff-DailyDemand_L*INDEX('Rainfall Data'!$E$15:$E$26,4),0),$B37) -> 0 | Q37: =MIN(MAX(P37+INDEX(ActiveMonthlyRain,5)*RoofArea_m2*CollectionEff-DailyDemand_L*INDEX('Rainfall Data'!$E$15:$E$26,5),0),$B37) -> 0 | R37: =MIN(MAX(Q37+INDEX(ActiveMonthlyRain,6)*RoofArea_m2*CollectionEff-DailyDemand_L*INDEX('Rainfall Data'!$E$15:$E$26,6),0),$B37) -> 0 | S37: =MIN(MAX(R37+INDEX(ActiveMonthlyRain,7)*RoofArea_m2*CollectionEff-DailyDemand_L*INDEX('Rainfall Data'!$E$15:$E$26,7),0),$B37) -> 2000 | T37: =MIN(MAX(S37+INDEX(ActiveMonthlyRain,8)*RoofArea_m2*CollectionEff-DailyDemand_L*INDEX('Rainfall Data'!$E$15:$E$26,8),0),$B37) -> 2000 | U37: =MIN(MAX(T37+INDEX(ActiveMonthlyRain,9)*RoofArea_m2*CollectionEff-DailyDemand_L*INDEX('Rainfall Data'!$E$15:$E$26,9),0),$B37) -> 0 | V37: =MIN(MAX(U37+INDEX(ActiveMonthlyRain,10)*RoofArea_m2*CollectionEff-DailyDemand_L*INDEX('Rainfall Data'!$E$15:$E$26,10),0),$B37) -> 0 | W37: =MIN(MAX(V37+INDEX(ActiveMonthlyRain,11)*RoofArea_m2*CollectionEff-DailyDemand_L*INDEX('Rainfall Data'!$E$15:$E$26,11),0),$B37) -> 0 | X37: =MIN(MAX(W37+INDEX(ActiveMonthlyRain,12)*RoofArea_m2*CollectionEff-DailyDemand_L*INDEX('Rainfall Data'!$E$15:$E$26,12),0),$B37) -> 0
B38: 2500 | C38: =MIN(DailyDemand_L*INDEX('Rainfall Data'!$E$15:$E$26,1),MAX(TankInitial_L+INDEX(ActiveMonthlyRain,1)*RoofArea_m2*CollectionEff-DeadStorage_L,0))+MIN(DailyDemand_L*INDEX('Rainfall Data'!$E$15:$E$26,2),MAX(M38+INDEX(ActiveMonthlyRain,2)*RoofArea_m2*CollectionEff-DeadStorage_L,0))+MIN(DailyDemand_L*INDEX('Rainfall Data'!$E$15:$E$26,3),MAX(N38+INDEX(ActiveMonthlyRain,3)*RoofArea_m2*CollectionEff-DeadStorage_L,0))+MIN(DailyDemand_L*INDEX('Rainfall Data'!$E$15:$E$26,4),MAX(O38+INDEX(ActiveMonthlyRain,4)*RoofArea_m2*CollectionEff-DeadStorage_L,0))+MIN(DailyDemand_L*INDEX('Rainfall Data'!$E$15:$E$26,5),MAX(P38+INDEX(ActiveMonthlyRain,5)*RoofArea_m2*CollectionEff-DeadStorage_L,0))+MIN(DailyDemand_L*INDEX('Rainfall Data'!$E$15:$E$26,6),MAX(Q38+INDEX(ActiveMonthlyRain,6)*RoofArea_m2*CollectionEff-DeadStorage_L,0))+MIN(DailyDemand_L*INDEX('Rainfall Data'!$E$15:$E$26,7),MAX(R38+INDEX(ActiveMonthlyRain,7)*RoofArea_m2*CollectionEff-DeadStorage_L,0))+MIN(DailyDemand_L*INDEX('Rainfall Data'!$E$15:$E$26,8),MAX(S38+INDEX(ActiveMonthlyRain,8)*RoofArea_m2*CollectionEff-DeadStorage_L,0))+MIN(DailyDemand_L*INDEX('Rainfall Data'!$E$15:$E$26,9),MAX(T38+INDEX(ActiveMonthlyRain,9)*RoofArea_m2*CollectionEff-DeadStorage_L,0))+MIN(DailyDemand_L*INDEX('Rainfall Data'!$E$15:$E$26,10),MAX(U38+INDEX(ActiveMonthlyRain,10)*RoofArea_m2*CollectionEff-DeadStorage_L,0))+MIN(DailyDemand_L*INDEX('Rainfall Data'!$E$15:$E$26,11),MAX(V38+INDEX(ActiveMonthlyRain,11)*RoofArea_m2*CollectionEff-DeadStorage_L,0))+MIN(DailyDemand_L*INDEX('Rainfall Data'!$E$15:$E$26,12),MAX(W38+INDEX(ActiveMonthlyRain,12)*RoofArea_m2*CollectionEff-DeadStorage_L,0)) -> 24326.576 | D38: =MAX(TankInitial_L+INDEX(ActiveMonthlyRain,1)*RoofArea_m2*CollectionEff-MIN(DailyDemand_L*INDEX('Rainfall Data'!$E$15:$E$26,1),MAX(TankInitial_L+INDEX(ActiveMonthlyRain,1)*RoofArea_m2*CollectionEff-DeadStorage_L,0))-$B38,0)+MAX(M38+INDEX(ActiveMonthlyRain,2)*RoofArea_m2*CollectionEff-MIN(DailyDemand_L*INDEX('Rainfall Data'!$E$15:$E$26,2),MAX(M38+INDEX(ActiveMonthlyRain,2)*RoofArea_m2*CollectionEff-DeadStorage_L,0))-$B38,0)+MAX(N38+INDEX(ActiveMonthlyRain,3)*RoofArea_m2*CollectionEff-MIN(DailyDemand_L*INDEX('Rainfall Data'!$E$15:$E$26,3),MAX(N38+INDEX(ActiveMonthlyRain,3)*RoofArea_m2*CollectionEff-DeadStorage_L,0))-$B38,0)+MAX(O38+INDEX(ActiveMonthlyRain,4)*RoofArea_m2*CollectionEff-MIN(DailyDemand_L*INDEX('Rainfall Data'!$E$15:$E$26,4),MAX(O38+INDEX(ActiveMonthlyRain,4)*RoofArea_m2*CollectionEff-DeadStorage_L,0))-$B38,0)+MAX(P38+INDEX(ActiveMonthlyRain,5)*RoofArea_m2*CollectionEff-MIN(DailyDemand_L*INDEX('Rainfall Data'!$E$15:$E$26,5),MAX(P38+INDEX(ActiveMonthlyRain,5)*RoofArea_m2*CollectionEff-DeadStorage_L,0))-$B38,0)+MAX(Q38+INDEX(ActiveMonthlyRain,6)*RoofArea_m2*CollectionEff-MIN(DailyDemand_L*INDEX('Rainfall Data'!$E$15:$E$26,6),MAX(Q38+INDEX(ActiveMonthlyRain,6)*RoofArea_m2*CollectionEff-DeadStorage_L,0))-$B38,0)+MAX(R38+INDEX(ActiveMonthlyRain,7)*RoofArea_m2*CollectionEff-MIN(DailyDemand_L*INDEX('Rainfall Data'!$E$15:$E$26,7),MAX(R38+INDEX(ActiveMonthlyRain,7)*RoofArea_m2*CollectionEff-DeadStorage_L,0))-$B38,0)+MAX(S38+INDEX(ActiveMonthlyRain,8)*RoofArea_m2*CollectionEff-MIN(DailyDemand_L*INDEX('Rainfall Data'!$E$15:$E$26,8),MAX(S38+INDEX(ActiveMonthlyRain,8)*RoofArea_m2*CollectionEff-DeadStorage_L,0))-$B38,0)+MAX(T38+INDEX(ActiveMonthlyRain,9)*RoofArea_m2*CollectionEff-MIN(DailyDemand_L*INDEX('Rainfall Data'!$E$15:$E$26,9),MAX(T38+INDEX(ActiveMonthlyRain,9)*RoofArea_m2*CollectionEff-DeadStorage_L,0))-$B38,0)+MAX(U38+INDEX(ActiveMonthlyRain,10)*RoofArea_m2*CollectionEff-MIN(DailyDemand_L*INDEX('Rainfall Data'!$E$15:$E$26,10),MAX(U38+INDEX(ActiveMonthlyRain,10)*RoofArea_m2*CollectionEff-DeadStorage_L,0))-$B38,0)+MAX(V38+INDEX(ActiveMonthlyRain,11)*RoofArea_m2*CollectionEff-MIN(DailyDemand_L*INDEX('Rainfall Data'!$E$15:$E$26,11),MAX(V38+INDEX(ActiveMonthlyRain,11)*RoofArea_m2*CollectionEff-DeadStorage_L,0))-$B38,0)+MAX(W38+INDEX(ActiveMonthlyRain,12)*RoofArea_m2*CollectionEff-MIN(DailyDemand_L*INDEX('Rainfall Data'!$E$15:$E$26,12),MAX(W38+INDEX(ActiveMonthlyRain,12)*RoofArea_m2*CollectionEff-DeadStorage_L,0))-$B38,0) -> 1783.101 | E38: =SUMPRODUCT(DailyDemand_L*'Rainfall Data'!$E$15:$E$26)-C38 -> 74223.424 | F38: =C38/SUMPRODUCT(DailyDemand_L*'Rainfall Data'!$E$15:$E$26) -> 0.24684502 | G38: =C38-C37 -> 500 | M38: =MIN(MAX(TankInitial_L+INDEX(ActiveMonthlyRain,1)*RoofArea_m2*CollectionEff-DailyDemand_L*INDEX('Rainfall Data'!$E$15:$E$26,1),0),$B38) -> 0 | N38: =MIN(MAX(M38+INDEX(ActiveMonthlyRain,2)*RoofArea_m2*CollectionEff-DailyDemand_L*INDEX('Rainfall Data'!$E$15:$E$26,2),0),$B38) -> 0 | O38: =MIN(MAX(N38+INDEX(ActiveMonthlyRain,3)*RoofArea_m2*CollectionEff-DailyDemand_L*INDEX('Rainfall Data'!$E$15:$E$26,3),0),$B38) -> 0 | P38: =MIN(MAX(O38+INDEX(ActiveMonthlyRain,4)*RoofArea_m2*CollectionEff-DailyDemand_L*INDEX('Rainfall Data'!$E$15:$E$26,4),0),$B38) -> 0 | Q38: =MIN(MAX(P38+INDEX(ActiveMonthlyRain,5)*RoofArea_m2*CollectionEff-DailyDemand_L*INDEX('Rainfall Data'!$E$15:$E$26,5),0),$B38) -> 0 | R38: =MIN(MAX(Q38+INDEX(ActiveMonthlyRain,6)*RoofArea_m2*CollectionEff-DailyDemand_L*INDEX('Rainfall Data'!$E$15:$E$26,6),0),$B38) -> 0 | S38: =MIN(MAX(R38+INDEX(ActiveMonthlyRain,7)*RoofArea_m2*CollectionEff-DailyDemand_L*INDEX('Rainfall Data'!$E$15:$E$26,7),0),$B38) -> 2500 | T38: =MIN(MAX(S38+INDEX(ActiveMonthlyRain,8)*RoofArea_m2*CollectionEff-DailyDemand_L*INDEX('Rainfall Data'!$E$15:$E$26,8),0),$B38) -> 2500 | U38: =MIN(MAX(T38+INDEX(ActiveMonthlyRain,9)*RoofArea_m2*CollectionEff-DailyDemand_L*INDEX('Rainfall Data'!$E$15:$E$26,9),0),$B38) -> 0 | V38: =MIN(MAX(U38+INDEX(ActiveMonthlyRain,10)*RoofArea_m2*CollectionEff-DailyDemand_L*INDEX('Rainfall Data'!$E$15:$E$26,10),0),$B38) -> 0 | W38: =MIN(MAX(V38+INDEX(ActiveMonthlyRain,11)*RoofArea_m2*CollectionEff-DailyDemand_L*INDEX('Rainfall Data'!$E$15:$E$26,11),0),$B38) -> 0 | X38: =MIN(MAX(W38+INDEX(ActiveMonthlyRain,12)*RoofArea_m2*CollectionEff-DailyDemand_L*INDEX('Rainfall Data'!$E$15:$E$26,12),0),$B38) -> 0
B39: 3000 | C39: =MIN(DailyDemand_L*INDEX('Rainfall Data'!$E$15:$E$26,1),MAX(TankInitial_L+INDEX(ActiveMonthlyRain,1)*RoofArea_m2*CollectionEff-DeadStorage_L,0))+MIN(DailyDemand_L*INDEX('Rainfall Data'!$E$15:$E$26,2),MAX(M39+INDEX(ActiveMonthlyRain,2)*RoofArea_m2*CollectionEff-DeadStorage_L,0))+MIN(DailyDemand_L*INDEX('Rainfall Data'!$E$15:$E$26,3),MAX(N39+INDEX(ActiveMonthlyRain,3)*RoofArea_m2*CollectionEff-DeadStorage_L,0))+MIN(DailyDemand_L*INDEX('Rainfall Data'!$E$15:$E$26,4),MAX(O39+INDEX(ActiveMonthlyRain,4)*RoofArea_m2*CollectionEff-DeadStorage_L,0))+MIN(DailyDemand_L*INDEX('Rainfall Data'!$E$15:$E$26,5),MAX(P39+INDEX(ActiveMonthlyRain,5)*RoofArea_m2*CollectionEff-DeadStorage_L,0))+MIN(DailyDemand_L*INDEX('Rainfall Data'!$E$15:$E$26,6),MAX(Q39+INDEX(ActiveMonthlyRain,6)*RoofArea_m2*CollectionEff-DeadStorage_L,0))+MIN(DailyDemand_L*INDEX('Rainfall Data'!$E$15:$E$26,7),MAX(R39+INDEX(ActiveMonthlyRain,7)*RoofArea_m2*CollectionEff-DeadStorage_L,0))+MIN(DailyDemand_L*INDEX('Rainfall Data'!$E$15:$E$26,8),MAX(S39+INDEX(ActiveMonthlyRain,8)*RoofArea_m2*CollectionEff-DeadStorage_L,0))+MIN(DailyDemand_L*INDEX('Rainfall Data'!$E$15:$E$26,9),MAX(T39+INDEX(ActiveMonthlyRain,9)*RoofArea_m2*CollectionEff-DeadStorage_L,0))+MIN(DailyDemand_L*INDEX('Rainfall Data'!$E$15:$E$26,10),MAX(U39+INDEX(ActiveMonthlyRain,10)*RoofArea_m2*CollectionEff-DeadStorage_L,0))+MIN(DailyDemand_L*INDEX('Rainfall Data'!$E$15:$E$26,11),MAX(V39+INDEX(ActiveMonthlyRain,11)*RoofArea_m2*CollectionEff-DeadStorage_L,0))+MIN(DailyDemand_L*INDEX('Rainfall Data'!$E$15:$E$26,12),MAX(W39+INDEX(ActiveMonthlyRain,12)*RoofArea_m2*CollectionEff-DeadStorage_L,0)) -> 24826.576 | D39: =MAX(TankInitial_L+INDEX(ActiveMonthlyRain,1)*RoofArea_m2*CollectionEff-MIN(DailyDemand_L*INDEX('Rainfall Data'!$E$15:$E$26,1),MAX(TankInitial_L+INDEX(ActiveMonthlyRain,1)*RoofArea_m2*CollectionEff-DeadStorage_L,0))-$B39,0)+MAX(M39+INDEX(ActiveMonthlyRain,2)*RoofArea_m2*CollectionEff-MIN(DailyDemand_L*INDEX('Rainfall Data'!$E$15:$E$26,2),MAX(M39+INDEX(ActiveMonthlyRain,2)*RoofArea_m2*CollectionEff-DeadStorage_L,0))-$B39,0)+MAX(N39+INDEX(ActiveMonthlyRain,3)*RoofArea_m2*CollectionEff-MIN(DailyDemand_L*INDEX('Rainfall Data'!$E$15:$E$26,3),MAX(N39+INDEX(ActiveMonthlyRain,3)*RoofArea_m2*CollectionEff-DeadStorage_L,0))-$B39,0)+MAX(O39+INDEX(ActiveMonthlyRain,4)*RoofArea_m2*CollectionEff-MIN(DailyDemand_L*INDEX('Rainfall Data'!$E$15:$E$26,4),MAX(O39+INDEX(ActiveMonthlyRain,4)*RoofArea_m2*CollectionEff-DeadStorage_L,0))-$B39,0)+MAX(P39+INDEX(ActiveMonthlyRain,5)*RoofArea_m2*CollectionEff-MIN(DailyDemand_L*INDEX('Rainfall Data'!$E$15:$E$26,5),MAX(P39+INDEX(ActiveMonthlyRain,5)*RoofArea_m2*CollectionEff-DeadStorage_L,0))-$B39,0)+MAX(Q39+INDEX(ActiveMonthlyRain,6)*RoofArea_m2*CollectionEff-MIN(DailyDemand_L*INDEX('Rainfall Data'!$E$15:$E$26,6),MAX(Q39+INDEX(ActiveMonthlyRain,6)*RoofArea_m2*CollectionEff-DeadStorage_L,0))-$B39,0)+MAX(R39+INDEX(ActiveMonthlyRain,7)*RoofArea_m2*CollectionEff-MIN(DailyDemand_L*INDEX('Rainfall Data'!$E$15:$E$26,7),MAX(R39+INDEX(ActiveMonthlyRain,7)*RoofArea_m2*CollectionEff-DeadStorage_L,0))-$B39,0)+MAX(S39+INDEX(ActiveMonthlyRain,8)*RoofArea_m2*CollectionEff-MIN(DailyDemand_L*INDEX('Rainfall Data'!$E$15:$E$26,8),MAX(S39+INDEX(ActiveMonthlyRain,8)*RoofArea_m2*CollectionEff-DeadStorage_L,0))-$B39,0)+MAX(T39+INDEX(ActiveMonthlyRain,9)*RoofArea_m2*CollectionEff-MIN(DailyDemand_L*INDEX('Rainfall Data'!$E$15:$E$26,9),MAX(T39+INDEX(ActiveMonthlyRain,9)*RoofArea_m2*CollectionEff-DeadStorage_L,0))-$B39,0)+MAX(U39+INDEX(ActiveMonthlyRain,10)*RoofArea_m2*CollectionEff-MIN(DailyDemand_L*INDEX('Rainfall Data'!$E$15:$E$26,10),MAX(U39+INDEX(ActiveMonthlyRain,10)*RoofArea_m2*CollectionEff-DeadStorage_L,0))-$B39,0)+MAX(V39+INDEX(ActiveMonthlyRain,11)*RoofArea_m2*CollectionEff-MIN(DailyDemand_L*INDEX('Rainfall Data'!$E$15:$E$26,11),MAX(V39+INDEX(ActiveMonthlyRain,11)*RoofArea_m2*CollectionEff-DeadStorage_L,0))-$B39,0)+MAX(W39+INDEX(ActiveMonthlyRain,12)*RoofArea_m2*CollectionEff-MIN(DailyDemand_L*INDEX('Rainfall Data'!$E$15:$E$26,12),MAX(W39+INDEX(ActiveMonthlyRain,12)*RoofArea_m2*CollectionEff-DeadStorage_L,0))-$B39,0) -> 1283.101 | E39: =SUMPRODUCT(DailyDemand_L*'Rainfall Data'!$E$15:$E$26)-C39 -> 73723.424 | F39: =C39/SUMPRODUCT(DailyDemand_L*'Rainfall Data'!$E$15:$E$26) -> 0.25191858 | G39: =C39-C38 -> 500 | M39: =MIN(MAX(TankInitial_L+INDEX(ActiveMonthlyRain,1)*RoofArea_m2*CollectionEff-DailyDemand_L*INDEX('Rainfall Data'!$E$15:$E$26,1),0),$B39) -> 0 | N39: =MIN(MAX(M39+INDEX(ActiveMonthlyRain,2)*RoofArea_m2*CollectionEff-DailyDemand_L*INDEX('Rainfall Data'!$E$15:$E$26,2),0),$B39) -> 0 | O39: =MIN(MAX(N39+INDEX(ActiveMonthlyRain,3)*RoofArea_m2*CollectionEff-DailyDemand_L*INDEX('Rainfall Data'!$E$15:$E$26,3),0),$B39) -> 0 | P39: =MIN(MAX(O39+INDEX(ActiveMonthlyRain,4)*RoofArea_m2*CollectionEff-DailyDemand_L*INDEX('Rainfall Data'!$E$15:$E$26,4),0),$B39) -> 0 | Q39: =MIN(MAX(P39+INDEX(ActiveMonthlyRain,5)*RoofArea_m2*CollectionEff-DailyDemand_L*INDEX('Rainfall Data'!$E$15:$E$26,5),0),$B39) -> 0 | R39: =MIN(MAX(Q39+INDEX(ActiveMonthlyRain,6)*RoofArea_m2*CollectionEff-DailyDemand_L*INDEX('Rainfall Data'!$E$15:$E$26,6),0),$B39) -> 0 | S39: =MIN(MAX(R39+INDEX(ActiveMonthlyRain,7)*RoofArea_m2*CollectionEff-DailyDemand_L*INDEX('Rainfall Data'!$E$15:$E$26,7),0),$B39) -> 2830.8325 | T39: =MIN(MAX(S39+INDEX(ActiveMonthlyRain,8)*RoofArea_m2*CollectionEff-DailyDemand_L*INDEX('Rainfall Data'!$E$15:$E$26,8),0),$B39) -> 3000 | U39: =MIN(MAX(T39+INDEX(ActiveMonthlyRain,9)*RoofArea_m2*CollectionEff-DailyDemand_L*INDEX('Rainfall Data'!$E$15:$E$26,9),0),$B39) -> 0 | V39: =MIN(MAX(U39+INDEX(ActiveMonthlyRain,10)*RoofArea_m2*CollectionEff-DailyDemand_L*INDEX('Rainfall Data'!$E$15:$E$26,10),0),$B39) -> 0 | W39: =MIN(MAX(V39+INDEX(ActiveMonthlyRain,11)*RoofArea_m2*CollectionEff-DailyDemand_L*INDEX('Rainfall Data'!$E$15:$E$26,11),0),$B39) -> 0 | X39: =MIN(MAX(W39+INDEX(ActiveMonthlyRain,12)*RoofArea_m2*CollectionEff-DailyDemand_L*INDEX('Rainfall Data'!$E$15:$E$26,12),0),$B39) -> 0
B40: 4000 | C40: =MIN(DailyDemand_L*INDEX('Rainfall Data'!$E$15:$E$26,1),MAX(TankInitial_L+INDEX(ActiveMonthlyRain,1)*RoofArea_m2*CollectionEff-DeadStorage_L,0))+MIN(DailyDemand_L*INDEX('Rainfall Data'!$E$15:$E$26,2),MAX(M40+INDEX(ActiveMonthlyRain,2)*RoofArea_m2*CollectionEff-DeadStorage_L,0))+MIN(DailyDemand_L*INDEX('Rainfall Data'!$E$15:$E$26,3),MAX(N40+INDEX(ActiveMonthlyRain,3)*RoofArea_m2*CollectionEff-DeadStorage_L,0))+MIN(DailyDemand_L*INDEX('Rainfall Data'!$E$15:$E$26,4),MAX(O40+INDEX(ActiveMonthlyRain,4)*RoofArea_m2*CollectionEff-DeadStorage_L,0))+MIN(DailyDemand_L*INDEX('Rainfall Data'!$E$15:$E$26,5),MAX(P40+INDEX(ActiveMonthlyRain,5)*RoofArea_m2*CollectionEff-DeadStorage_L,0))+MIN(DailyDemand_L*INDEX('Rainfall Data'!$E$15:$E$26,6),MAX(Q40+INDEX(ActiveMonthlyRain,6)*RoofArea_m2*CollectionEff-DeadStorage_L,0))+MIN(DailyDemand_L*INDEX('Rainfall Data'!$E$15:$E$26,7),MAX(R40+INDEX(ActiveMonthlyRain,7)*RoofArea_m2*CollectionEff-DeadStorage_L,0))+MIN(DailyDemand_L*INDEX('Rainfall Data'!$E$15:$E$26,8),MAX(S40+INDEX(ActiveMonthlyRain,8)*RoofArea_m2*CollectionEff-DeadStorage_L,0))+MIN(DailyDemand_L*INDEX('Rainfall Data'!$E$15:$E$26,9),MAX(T40+INDEX(ActiveMonthlyRain,9)*RoofArea_m2*CollectionEff-DeadStorage_L,0))+MIN(DailyDemand_L*INDEX('Rainfall Data'!$E$15:$E$26,10),MAX(U40+INDEX(ActiveMonthlyRain,10)*RoofArea_m2*CollectionEff-DeadStorage_L,0))+MIN(DailyDemand_L*INDEX('Rainfall Data'!$E$15:$E$26,11),MAX(V40+INDEX(ActiveMonthlyRain,11)*RoofArea_m2*CollectionEff-DeadStorage_L,0))+MIN(DailyDemand_L*INDEX('Rainfall Data'!$E$15:$E$26,12),MAX(W40+INDEX(ActiveMonthlyRain,12)*RoofArea_m2*CollectionEff-DeadStorage_L,0)) -> 25826.576 | D40: =MAX(TankInitial_L+INDEX(ActiveMonthlyRain,1)*RoofArea_m2*CollectionEff-MIN(DailyDemand_L*INDEX('Rainfall Data'!$E$15:$E$26,1),MAX(TankInitial_L+INDEX(ActiveMonthlyRain,1)*RoofArea_m2*CollectionEff-DeadStorage_L,0))-$B40,0)+MAX(M40+INDEX(ActiveMonthlyRain,2)*RoofArea_m2*CollectionEff-MIN(DailyDemand_L*INDEX('Rainfall Data'!$E$15:$E$26,2),MAX(M40+INDEX(ActiveMonthlyRain,2)*RoofArea_m2*CollectionEff-DeadStorage_L,0))-$B40,0)+MAX(N40+INDEX(ActiveMonthlyRain,3)*RoofArea_m2*CollectionEff-MIN(DailyDemand_L*INDEX('Rainfall Data'!$E$15:$E$26,3),MAX(N40+INDEX(ActiveMonthlyRain,3)*RoofArea_m2*CollectionEff-DeadStorage_L,0))-$B40,0)+MAX(O40+INDEX(ActiveMonthlyRain,4)*RoofArea_m2*CollectionEff-MIN(DailyDemand_L*INDEX('Rainfall Data'!$E$15:$E$26,4),MAX(O40+INDEX(ActiveMonthlyRain,4)*RoofArea_m2*CollectionEff-DeadStorage_L,0))-$B40,0)+MAX(P40+INDEX(ActiveMonthlyRain,5)*RoofArea_m2*CollectionEff-MIN(DailyDemand_L*INDEX('Rainfall Data'!$E$15:$E$26,5),MAX(P40+INDEX(ActiveMonthlyRain,5)*RoofArea_m2*CollectionEff-DeadStorage_L,0))-$B40,0)+MAX(Q40+INDEX(ActiveMonthlyRain,6)*RoofArea_m2*CollectionEff-MIN(DailyDemand_L*INDEX('Rainfall Data'!$E$15:$E$26,6),MAX(Q40+INDEX(ActiveMonthlyRain,6)*RoofArea_m2*CollectionEff-DeadStorage_L,0))-$B40,0)+MAX(R40+INDEX(ActiveMonthlyRain,7)*RoofArea_m2*CollectionEff-MIN(DailyDemand_L*INDEX('Rainfall Data'!$E$15:$E$26,7),MAX(R40+INDEX(ActiveMonthlyRain,7)*RoofArea_m2*CollectionEff-DeadStorage_L,0))-$B40,0)+MAX(S40+INDEX(ActiveMonthlyRain,8)*RoofArea_m2*CollectionEff-MIN(DailyDemand_L*INDEX('Rainfall Data'!$E$15:$E$26,8),MAX(S40+INDEX(ActiveMonthlyRain,8)*RoofArea_m2*CollectionEff-DeadStorage_L,0))-$B40,0)+MAX(T40+INDEX(ActiveMonthlyRain,9)*RoofArea_m2*CollectionEff-MIN(DailyDemand_L*INDEX('Rainfall Data'!$E$15:$E$26,9),MAX(T40+INDEX(ActiveMonthlyRain,9)*RoofArea_m2*CollectionEff-DeadStorage_L,0))-$B40,0)+MAX(U40+INDEX(ActiveMonthlyRain,10)*RoofArea_m2*CollectionEff-MIN(DailyDemand_L*INDEX('Rainfall Data'!$E$15:$E$26,10),MAX(U40+INDEX(ActiveMonthlyRain,10)*RoofArea_m2*CollectionEff-DeadStorage_L,0))-$B40,0)+MAX(V40+INDEX(ActiveMonthlyRain,11)*RoofArea_m2*CollectionEff-MIN(DailyDemand_L*INDEX('Rainfall Data'!$E$15:$E$26,11),MAX(V40+INDEX(ActiveMonthlyRain,11)*RoofArea_m2*CollectionEff-DeadStorage_L,0))-$B40,0)+MAX(W40+INDEX(ActiveMonthlyRain,12)*RoofArea_m2*CollectionEff-MIN(DailyDemand_L*INDEX('Rainfall Data'!$E$15:$E$26,12),MAX(W40+INDEX(ActiveMonthlyRain,12)*RoofArea_m2*CollectionEff-DeadStorage_L,0))-$B40,0) -> 283.101 | E40: =SUMPRODUCT(DailyDemand_L*'Rainfall Data'!$E$15:$E$26)-C40 -> 72723.424 | F40: =C40/SUMPRODUCT(DailyDemand_L*'Rainfall Data'!$E$15:$E$26) -> 0.26206572 | G40: =C40-C39 -> 1000 | M40: =MIN(MAX(TankInitial_L+INDEX(ActiveMonthlyRain,1)*RoofArea_m2*CollectionEff-DailyDemand_L*INDEX('Rainfall Data'!$E$15:$E$26,1),0),$B40) -> 0 | N40: =MIN(MAX(M40+INDEX(ActiveMonthlyRain,2)*RoofArea_m2*CollectionEff-DailyDemand_L*INDEX('Rainfall Data'!$E$15:$E$26,2),0),$B40) -> 0 | O40: =MIN(MAX(N40+INDEX(ActiveMonthlyRain,3)*RoofArea_m2*CollectionEff-DailyDemand_L*INDEX('Rainfall Data'!$E$15:$E$26,3),0),$B40) -> 0 | P40: =MIN(MAX(O40+INDEX(ActiveMonthlyRain,4)*RoofArea_m2*CollectionEff-DailyDemand_L*INDEX('Rainfall Data'!$E$15:$E$26,4),0),$B40) -> 0 | Q40: =MIN(MAX(P40+INDEX(ActiveMonthlyRain,5)*RoofArea_m2*CollectionEff-DailyDemand_L*INDEX('Rainfall Data'!$E$15:$E$26,5),0),$B40) -> 0 | R40: =MIN(MAX(Q40+INDEX(ActiveMonthlyRain,6)*RoofArea_m2*CollectionEff-DailyDemand_L*INDEX('Rainfall Data'!$E$15:$E$26,6),0),$B40) -> 0 | S40: =MIN(MAX(R40+INDEX(ActiveMonthlyRain,7)*RoofArea_m2*CollectionEff-DailyDemand_L*INDEX('Rainfall Data'!$E$15:$E$26,7),0),$B40) -> 2830.8325 | T40: =MIN(MAX(S40+INDEX(ActiveMonthlyRain,8)*RoofArea_m2*CollectionEff-DailyDemand_L*INDEX('Rainfall Data'!$E$15:$E$26,8),0),$B40) -> 4000 | U40: =MIN(MAX(T40+INDEX(ActiveMonthlyRain,9)*RoofArea_m2*CollectionEff-DailyDemand_L*INDEX('Rainfall Data'!$E$15:$E$26,9),0),$B40) -> 0 | V40: =MIN(MAX(U40+INDEX(ActiveMonthlyRain,10)*RoofArea_m2*CollectionEff-DailyDemand_L*INDEX('Rainfall Data'!$E$15:$E$26,10),0),$B40) -> 0 | W40: =MIN(MAX(V40+INDEX(ActiveMonthlyRain,11)*RoofArea_m2*CollectionEff-DailyDemand_L*INDEX('Rainfall Data'!$E$15:$E$26,11),0),$B40) -> 0 | X40: =MIN(MAX(W40+INDEX(ActiveMonthlyRain,12)*RoofArea_m2*CollectionEff-DailyDemand_L*INDEX('Rainfall Data'!$E$15:$E$26,12),0),$B40) -> 0
B41: 5000 | C41: =MIN(DailyDemand_L*INDEX('Rainfall Data'!$E$15:$E$26,1),MAX(TankInitial_L+INDEX(ActiveMonthlyRain,1)*RoofArea_m2*CollectionEff-DeadStorage_L,0))+MIN(DailyDemand_L*INDEX('Rainfall Data'!$E$15:$E$26,2),MAX(M41+INDEX(ActiveMonthlyRain,2)*RoofArea_m2*CollectionEff-DeadStorage_L,0))+MIN(DailyDemand_L*INDEX('Rainfall Data'!$E$15:$E$26,3),MAX(N41+INDEX(ActiveMonthlyRain,3)*RoofArea_m2*CollectionEff-DeadStorage_L,0))+MIN(DailyDemand_L*INDEX('Rainfall Data'!$E$15:$E$26,4),MAX(O41+INDEX(ActiveMonthlyRain,4)*RoofArea_m2*CollectionEff-DeadStorage_L,0))+MIN(DailyDemand_L*INDEX('Rainfall Data'!$E$15:$E$26,5),MAX(P41+INDEX(ActiveMonthlyRain,5)*RoofArea_m2*CollectionEff-DeadStorage_L,0))+MIN(DailyDemand_L*INDEX('Rainfall Data'!$E$15:$E$26,6),MAX(Q41+INDEX(ActiveMonthlyRain,6)*RoofArea_m2*CollectionEff-DeadStorage_L,0))+MIN(DailyDemand_L*INDEX('Rainfall Data'!$E$15:$E$26,7),MAX(R41+INDEX(ActiveMonthlyRain,7)*RoofArea_m2*CollectionEff-DeadStorage_L,0))+MIN(DailyDemand_L*INDEX('Rainfall Data'!$E$15:$E$26,8),MAX(S41+INDEX(ActiveMonthlyRain,8)*RoofArea_m2*CollectionEff-DeadStorage_L,0))+MIN(DailyDemand_L*INDEX('Rainfall Data'!$E$15:$E$26,9),MAX(T41+INDEX(ActiveMonthlyRain,9)*RoofArea_m2*CollectionEff-DeadStorage_L,0))+MIN(DailyDemand_L*INDEX('Rainfall Data'!$E$15:$E$26,10),MAX(U41+INDEX(ActiveMonthlyRain,10)*RoofArea_m2*CollectionEff-DeadStorage_L,0))+MIN(DailyDemand_L*INDEX('Rainfall Data'!$E$15:$E$26,11),MAX(V41+INDEX(ActiveMonthlyRain,11)*RoofArea_m2*CollectionEff-DeadStorage_L,0))+MIN(DailyDemand_L*INDEX('Rainfall Data'!$E$15:$E$26,12),MAX(W41+INDEX(ActiveMonthlyRain,12)*RoofArea_m2*CollectionEff-DeadStorage_L,0)) -> 26109.677 | D41: =MAX(TankInitial_L+INDEX(ActiveMonthlyRain,1)*RoofArea_m2*CollectionEff-MIN(DailyDemand_L*INDEX('Rainfall Data'!$E$15:$E$26,1),MAX(TankInitial_L+INDEX(ActiveMonthlyRain,1)*RoofArea_m2*CollectionEff-DeadStorage_L,0))-$B41,0)+MAX(M41+INDEX(ActiveMonthlyRain,2)*RoofArea_m2*CollectionEff-MIN(DailyDemand_L*INDEX('Rainfall Data'!$E$15:$E$26,2),MAX(M41+INDEX(ActiveMonthlyRain,2)*RoofArea_m2*CollectionEff-DeadStorage_L,0))-$B41,0)+MAX(N41+INDEX(ActiveMonthlyRain,3)*RoofArea_m2*CollectionEff-MIN(DailyDemand_L*INDEX('Rainfall Data'!$E$15:$E$26,3),MAX(N41+INDEX(ActiveMonthlyRain,3)*RoofArea_m2*CollectionEff-DeadStorage_L,0))-$B41,0)+MAX(O41+INDEX(ActiveMonthlyRain,4)*RoofArea_m2*CollectionEff-MIN(DailyDemand_L*INDEX('Rainfall Data'!$E$15:$E$26,4),MAX(O41+INDEX(ActiveMonthlyRain,4)*RoofArea_m2*CollectionEff-DeadStorage_L,0))-$B41,0)+MAX(P41+INDEX(ActiveMonthlyRain,5)*RoofArea_m2*CollectionEff-MIN(DailyDemand_L*INDEX('Rainfall Data'!$E$15:$E$26,5),MAX(P41+INDEX(ActiveMonthlyRain,5)*RoofArea_m2*CollectionEff-DeadStorage_L,0))-$B41,0)+MAX(Q41+INDEX(ActiveMonthlyRain,6)*RoofArea_m2*CollectionEff-MIN(DailyDemand_L*INDEX('Rainfall Data'!$E$15:$E$26,6),MAX(Q41+INDEX(ActiveMonthlyRain,6)*RoofArea_m2*CollectionEff-DeadStorage_L,0))-$B41,0)+MAX(R41+INDEX(ActiveMonthlyRain,7)*RoofArea_m2*CollectionEff-MIN(DailyDemand_L*INDEX('Rainfall Data'!$E$15:$E$26,7),MAX(R41+INDEX(ActiveMonthlyRain,7)*RoofArea_m2*CollectionEff-DeadStorage_L,0))-$B41,0)+MAX(S41+INDEX(ActiveMonthlyRain,8)*RoofArea_m2*CollectionEff-MIN(DailyDemand_L*INDEX('Rainfall Data'!$E$15:$E$26,8),MAX(S41+INDEX(ActiveMonthlyRain,8)*RoofArea_m2*CollectionEff-DeadStorage_L,0))-$B41,0)+MAX(T41+INDEX(ActiveMonthlyRain,9)*RoofArea_m2*CollectionEff-MIN(DailyDemand_L*INDEX('Rainfall Data'!$E$15:$E$26,9),MAX(T41+INDEX(ActiveMonthlyRain,9)*RoofArea_m2*CollectionEff-DeadStorage_L,0))-$B41,0)+MAX(U41+INDEX(ActiveMonthlyRain,10)*RoofArea_m2*CollectionEff-MIN(DailyDemand_L*INDEX('Rainfall Data'!$E$15:$E$26,10),MAX(U41+INDEX(ActiveMonthlyRain,10)*RoofArea_m2*CollectionEff-DeadStorage_L,0))-$B41,0)+MAX(V41+INDEX(ActiveMonthlyRain,11)*RoofArea_m2*CollectionEff-MIN(DailyDemand_L*INDEX('Rainfall Data'!$E$15:$E$26,11),MAX(V41+INDEX(ActiveMonthlyRain,11)*RoofArea_m2*CollectionEff-DeadStorage_L,0))-$B41,0)+MAX(W41+INDEX(ActiveMonthlyRain,12)*RoofArea_m2*CollectionEff-MIN(DailyDemand_L*INDEX('Rainfall Data'!$E$15:$E$26,12),MAX(W41+INDEX(ActiveMonthlyRain,12)*RoofArea_m2*CollectionEff-DeadStorage_L,0))-$B41,0) -> 0 | E41: =SUMPRODUCT(DailyDemand_L*'Rainfall Data'!$E$15:$E$26)-C41 -> 72440.323 | F41: =C41/SUMPRODUCT(DailyDemand_L*'Rainfall Data'!$E$15:$E$26) -> 0.26493838 | G41: =C41-C40 -> 283.101 | M41: =MIN(MAX(TankInitial_L+INDEX(ActiveMonthlyRain,1)*RoofArea_m2*CollectionEff-DailyDemand_L*INDEX('Rainfall Data'!$E$15:$E$26,1),0),$B41) -> 0 | N41: =MIN(MAX(M41+INDEX(ActiveMonthlyRain,2)*RoofArea_m2*CollectionEff-DailyDemand_L*INDEX('Rainfall Data'!$E$15:$E$26,2),0),$B41) -> 0 | O41: =MIN(MAX(N41+INDEX(ActiveMonthlyRain,3)*RoofArea_m2*CollectionEff-DailyDemand_L*INDEX('Rainfall Data'!$E$15:$E$26,3),0),$B41) -> 0 | P41: =MIN(MAX(O41+INDEX(ActiveMonthlyRain,4)*RoofArea_m2*CollectionEff-DailyDemand_L*INDEX('Rainfall Data'!$E$15:$E$26,4),0),$B41) -> 0 | Q41: =MIN(MAX(P41+INDEX(ActiveMonthlyRain,5)*RoofArea_m2*CollectionEff-DailyDemand_L*INDEX('Rainfall Data'!$E$15:$E$26,5),0),$B41) -> 0 | R41: =MIN(MAX(Q41+INDEX(ActiveMonthlyRain,6)*RoofArea_m2*CollectionEff-DailyDemand_L*INDEX('Rainfall Data'!$E$15:$E$26,6),0),$B41) -> 0 | S41: =MIN(MAX(R41+INDEX(ActiveMonthlyRain,7)*RoofArea_m2*CollectionEff-DailyDemand_L*INDEX('Rainfall Data'!$E$15:$E$26,7),0),$B41) -> 2830.8325 | T41: =MIN(MAX(S41+INDEX(ActiveMonthlyRain,8)*RoofArea_m2*CollectionEff-DailyDemand_L*INDEX('Rainfall Data'!$E$15:$E$26,8),0),$B41) -> 4283.101 | U41: =MIN(MAX(T41+INDEX(ActiveMonthlyRain,9)*RoofArea_m2*CollectionEff-DailyDemand_L*INDEX('Rainfall Data'!$E$15:$E$26,9),0),$B41) -> 0 | V41: =MIN(MAX(U41+INDEX(ActiveMonthlyRain,10)*RoofArea_m2*CollectionEff-DailyDemand_L*INDEX('Rainfall Data'!$E$15:$E$26,10),0),$B41) -> 0 | W41: =MIN(MAX(V41+INDEX(ActiveMonthlyRain,11)*RoofArea_m2*CollectionEff-DailyDemand_L*INDEX('Rainfall Data'!$E$15:$E$26,11),0),$B41) -> 0 | X41: =MIN(MAX(W41+INDEX(ActiveMonthlyRain,12)*RoofArea_m2*CollectionEff-DailyDemand_L*INDEX('Rainfall Data'!$E$15:$E$26,12),0),$B41) -> 0
B42: 6000 | C42: =MIN(DailyDemand_L*INDEX('Rainfall Data'!$E$15:$E$26,1),MAX(TankInitial_L+INDEX(ActiveMonthlyRain,1)*RoofArea_m2*CollectionEff-DeadStorage_L,0))+MIN(DailyDemand_L*INDEX('Rainfall Data'!$E$15:$E$26,2),MAX(M42+INDEX(ActiveMonthlyRain,2)*RoofArea_m2*CollectionEff-DeadStorage_L,0))+MIN(DailyDemand_L*INDEX('Rainfall Data'!$E$15:$E$26,3),MAX(N42+INDEX(ActiveMonthlyRain,3)*RoofArea_m2*CollectionEff-DeadStorage_L,0))+MIN(DailyDemand_L*INDEX('Rainfall Data'!$E$15:$E$26,4),MAX(O42+INDEX(ActiveMonthlyRain,4)*RoofArea_m2*CollectionEff-DeadStorage_L,0))+MIN(DailyDemand_L*INDEX('Rainfall Data'!$E$15:$E$26,5),MAX(P42+INDEX(ActiveMonthlyRain,5)*RoofArea_m2*CollectionEff-DeadStorage_L,0))+MIN(DailyDemand_L*INDEX('Rainfall Data'!$E$15:$E$26,6),MAX(Q42+INDEX(ActiveMonthlyRain,6)*RoofArea_m2*CollectionEff-DeadStorage_L,0))+MIN(DailyDemand_L*INDEX('Rainfall Data'!$E$15:$E$26,7),MAX(R42+INDEX(ActiveMonthlyRain,7)*RoofArea_m2*CollectionEff-DeadStorage_L,0))+MIN(DailyDemand_L*INDEX('Rainfall Data'!$E$15:$E$26,8),MAX(S42+INDEX(ActiveMonthlyRain,8)*RoofArea_m2*CollectionEff-DeadStorage_L,0))+MIN(DailyDemand_L*INDEX('Rainfall Data'!$E$15:$E$26,9),MAX(T42+INDEX(ActiveMonthlyRain,9)*RoofArea_m2*CollectionEff-DeadStorage_L,0))+MIN(DailyDemand_L*INDEX('Rainfall Data'!$E$15:$E$26,10),MAX(U42+INDEX(ActiveMonthlyRain,10)*RoofArea_m2*CollectionEff-DeadStorage_L,0))+MIN(DailyDemand_L*INDEX('Rainfall Data'!$E$15:$E$26,11),MAX(V42+INDEX(ActiveMonthlyRain,11)*RoofArea_m2*CollectionEff-DeadStorage_L,0))+MIN(DailyDemand_L*INDEX('Rainfall Data'!$E$15:$E$26,12),MAX(W42+INDEX(ActiveMonthlyRain,12)*RoofArea_m2*CollectionEff-DeadStorage_L,0)) -> 26109.677 | D42: =MAX(TankInitial_L+INDEX(ActiveMonthlyRain,1)*RoofArea_m2*CollectionEff-MIN(DailyDemand_L*INDEX('Rainfall Data'!$E$15:$E$26,1),MAX(TankInitial_L+INDEX(ActiveMonthlyRain,1)*RoofArea_m2*CollectionEff-DeadStorage_L,0))-$B42,0)+MAX(M42+INDEX(ActiveMonthlyRain,2)*RoofArea_m2*CollectionEff-MIN(DailyDemand_L*INDEX('Rainfall Data'!$E$15:$E$26,2),MAX(M42+INDEX(ActiveMonthlyRain,2)*RoofArea_m2*CollectionEff-DeadStorage_L,0))-$B42,0)+MAX(N42+INDEX(ActiveMonthlyRain,3)*RoofArea_m2*CollectionEff-MIN(DailyDemand_L*INDEX('Rainfall Data'!$E$15:$E$26,3),MAX(N42+INDEX(ActiveMonthlyRain,3)*RoofArea_m2*CollectionEff-DeadStorage_L,0))-$B42,0)+MAX(O42+INDEX(ActiveMonthlyRain,4)*RoofArea_m2*CollectionEff-MIN(DailyDemand_L*INDEX('Rainfall Data'!$E$15:$E$26,4),MAX(O42+INDEX(ActiveMonthlyRain,4)*RoofArea_m2*CollectionEff-DeadStorage_L,0))-$B42,0)+MAX(P42+INDEX(ActiveMonthlyRain,5)*RoofArea_m2*CollectionEff-MIN(DailyDemand_L*INDEX('Rainfall Data'!$E$15:$E$26,5),MAX(P42+INDEX(ActiveMonthlyRain,5)*RoofArea_m2*CollectionEff-DeadStorage_L,0))-$B42,0)+MAX(Q42+INDEX(ActiveMonthlyRain,6)*RoofArea_m2*CollectionEff-MIN(DailyDemand_L*INDEX('Rainfall Data'!$E$15:$E$26,6),MAX(Q42+INDEX(ActiveMonthlyRain,6)*RoofArea_m2*CollectionEff-DeadStorage_L,0))-$B42,0)+MAX(R42+INDEX(ActiveMonthlyRain,7)*RoofArea_m2*CollectionEff-MIN(DailyDemand_L*INDEX('Rainfall Data'!$E$15:$E$26,7),MAX(R42+INDEX(ActiveMonthlyRain,7)*RoofArea_m2*CollectionEff-DeadStorage_L,0))-$B42,0)+MAX(S42+INDEX(ActiveMonthlyRain,8)*RoofArea_m2*CollectionEff-MIN(DailyDemand_L*INDEX('Rainfall Data'!$E$15:$E$26,8),MAX(S42+INDEX(ActiveMonthlyRain,8)*RoofArea_m2*CollectionEff-DeadStorage_L,0))-$B42,0)+MAX(T42+INDEX(ActiveMonthlyRain,9)*RoofArea_m2*CollectionEff-MIN(DailyDemand_L*INDEX('Rainfall Data'!$E$15:$E$26,9),MAX(T42+INDEX(ActiveMonthlyRain,9)*RoofArea_m2*CollectionEff-DeadStorage_L,0))-$B42,0)+MAX(U42+INDEX(ActiveMonthlyRain,10)*RoofArea_m2*CollectionEff-MIN(DailyDemand_L*INDEX('Rainfall Data'!$E$15:$E$26,10),MAX(U42+INDEX(ActiveMonthlyRain,10)*RoofArea_m2*CollectionEff-DeadStorage_L,0))-$B42,0)+MAX(V42+INDEX(ActiveMonthlyRain,11)*RoofArea_m2*CollectionEff-MIN(DailyDemand_L*INDEX('Rainfall Data'!$E$15:$E$26,11),MAX(V42+INDEX(ActiveMonthlyRain,11)*RoofArea_m2*CollectionEff-DeadStorage_L,0))-$B42,0)+MAX(W42+INDEX(ActiveMonthlyRain,12)*RoofArea_m2*CollectionEff-MIN(DailyDemand_L*INDEX('Rainfall Data'!$E$15:$E$26,12),MAX(W42+INDEX(ActiveMonthlyRain,12)*RoofArea_m2*CollectionEff-DeadStorage_L,0))-$B42,0) -> 0 | E42: =SUMPRODUCT(DailyDemand_L*'Rainfall Data'!$E$15:$E$26)-C42 -> 72440.323 | F42: =C42/SUMPRODUCT(DailyDemand_L*'Rainfall Data'!$E$15:$E$26) -> 0.26493838 | G42: =C42-C41 -> 0 | M42: =MIN(MAX(TankInitial_L+INDEX(ActiveMonthlyRain,1)*RoofArea_m2*CollectionEff-DailyDemand_L*INDEX('Rainfall Data'!$E$15:$E$26,1),0),$B42) -> 0 | N42: =MIN(MAX(M42+INDEX(ActiveMonthlyRain,2)*RoofArea_m2*CollectionEff-DailyDemand_L*INDEX('Rainfall Data'!$E$15:$E$26,2),0),$B42) -> 0 | O42: =MIN(MAX(N42+INDEX(ActiveMonthlyRain,3)*RoofArea_m2*CollectionEff-DailyDemand_L*INDEX('Rainfall Data'!$E$15:$E$26,3),0),$B42) -> 0 | P42: =MIN(MAX(O42+INDEX(ActiveMonthlyRain,4)*RoofArea_m2*CollectionEff-DailyDemand_L*INDEX('Rainfall Data'!$E$15:$E$26,4),0),$B42) -> 0 | Q42: =MIN(MAX(P42+INDEX(ActiveMonthlyRain,5)*RoofArea_m2*CollectionEff-DailyDemand_L*INDEX('Rainfall Data'!$E$15:$E$26,5),0),$B42) -> 0 | R42: =MIN(MAX(Q42+INDEX(ActiveMonthlyRain,6)*RoofArea_m2*CollectionEff-DailyDemand_L*INDEX('Rainfall Data'!$E$15:$E$26,6),0),$B42) -> 0 | S42: =MIN(MAX(R42+INDEX(ActiveMonthlyRain,7)*RoofArea_m2*CollectionEff-DailyDemand_L*INDEX('Rainfall Data'!$E$15:$E$26,7),0),$B42) -> 2830.8325 | T42: =MIN(MAX(S42+INDEX(ActiveMonthlyRain,8)*RoofArea_m2*CollectionEff-DailyDemand_L*INDEX('Rainfall Data'!$E$15:$E$26,8),0),$B42) -> 4283.101 | U42: =MIN(MAX(T42+INDEX(ActiveMonthlyRain,9)*RoofArea_m2*CollectionEff-DailyDemand_L*INDEX('Rainfall Data'!$E$15:$E$26,9),0),$B42) -> 0 | V42: =MIN(MAX(U42+INDEX(ActiveMonthlyRain,10)*RoofArea_m2*CollectionEff-DailyDemand_L*INDEX('Rainfall Data'!$E$15:$E$26,10),0),$B42) -> 0 | W42: =MIN(MAX(V42+INDEX(ActiveMonthlyRain,11)*RoofArea_m2*CollectionEff-DailyDemand_L*INDEX('Rainfall Data'!$E$15:$E$26,11),0),$B42) -> 0 | X42: =MIN(MAX(W42+INDEX(ActiveMonthlyRain,12)*RoofArea_m2*CollectionEff-DailyDemand_L*INDEX('Rainfall Data'!$E$15:$E$26,12),0),$B42) -> 0
B43: 7000 | C43: =MIN(DailyDemand_L*INDEX('Rainfall Data'!$E$15:$E$26,1),MAX(TankInitial_L+INDEX(ActiveMonthlyRain,1)*RoofArea_m2*CollectionEff-DeadStorage_L,0))+MIN(DailyDemand_L*INDEX('Rainfall Data'!$E$15:$E$26,2),MAX(M43+INDEX(ActiveMonthlyRain,2)*RoofArea_m2*CollectionEff-DeadStorage_L,0))+MIN(DailyDemand_L*INDEX('Rainfall Data'!$E$15:$E$26,3),MAX(N43+INDEX(ActiveMonthlyRain,3)*RoofArea_m2*CollectionEff-DeadStorage_L,0))+MIN(DailyDemand_L*INDEX('Rainfall Data'!$E$15:$E$26,4),MAX(O43+INDEX(ActiveMonthlyRain,4)*RoofArea_m2*CollectionEff-DeadStorage_L,0))+MIN(DailyDemand_L*INDEX('Rainfall Data'!$E$15:$E$26,5),MAX(P43+INDEX(ActiveMonthlyRain,5)*RoofArea_m2*CollectionEff-DeadStorage_L,0))+MIN(DailyDemand_L*INDEX('Rainfall Data'!$E$15:$E$26,6),MAX(Q43+INDEX(ActiveMonthlyRain,6)*RoofArea_m2*CollectionEff-DeadStorage_L,0))+MIN(DailyDemand_L*INDEX('Rainfall Data'!$E$15:$E$26,7),MAX(R43+INDEX(ActiveMonthlyRain,7)*RoofArea_m2*CollectionEff-DeadStorage_L,0))+MIN(DailyDemand_L*INDEX('Rainfall Data'!$E$15:$E$26,8),MAX(S43+INDEX(ActiveMonthlyRain,8)*RoofArea_m2*CollectionEff-DeadStorage_L,0))+MIN(DailyDemand_L*INDEX('Rainfall Data'!$E$15:$E$26,9),MAX(T43+INDEX(ActiveMonthlyRain,9)*RoofArea_m2*CollectionEff-DeadStorage_L,0))+MIN(DailyDemand_L*INDEX('Rainfall Data'!$E$15:$E$26,10),MAX(U43+INDEX(ActiveMonthlyRain,10)*RoofArea_m2*CollectionEff-DeadStorage_L,0))+MIN(DailyDemand_L*INDEX('Rainfall Data'!$E$15:$E$26,11),MAX(V43+INDEX(ActiveMonthlyRain,11)*RoofArea_m2*CollectionEff-DeadStorage_L,0))+MIN(DailyDemand_L*INDEX('Rainfall Data'!$E$15:$E$26,12),MAX(W43+INDEX(ActiveMonthlyRain,12)*RoofArea_m2*CollectionEff-DeadStorage_L,0)) -> 26109.677 | D43: =MAX(TankInitial_L+INDEX(ActiveMonthlyRain,1)*RoofArea_m2*CollectionEff-MIN(DailyDemand_L*INDEX('Rainfall Data'!$E$15:$E$26,1),MAX(TankInitial_L+INDEX(ActiveMonthlyRain,1)*RoofArea_m2*CollectionEff-DeadStorage_L,0))-$B43,0)+MAX(M43+INDEX(ActiveMonthlyRain,2)*RoofArea_m2*CollectionEff-MIN(DailyDemand_L*INDEX('Rainfall Data'!$E$15:$E$26,2),MAX(M43+INDEX(ActiveMonthlyRain,2)*RoofArea_m2*CollectionEff-DeadStorage_L,0))-$B43,0)+MAX(N43+INDEX(ActiveMonthlyRain,3)*RoofArea_m2*CollectionEff-MIN(DailyDemand_L*INDEX('Rainfall Data'!$E$15:$E$26,3),MAX(N43+INDEX(ActiveMonthlyRain,3)*RoofArea_m2*CollectionEff-DeadStorage_L,0))-$B43,0)+MAX(O43+INDEX(ActiveMonthlyRain,4)*RoofArea_m2*CollectionEff-MIN(DailyDemand_L*INDEX('Rainfall Data'!$E$15:$E$26,4),MAX(O43+INDEX(ActiveMonthlyRain,4)*RoofArea_m2*CollectionEff-DeadStorage_L,0))-$B43,0)+MAX(P43+INDEX(ActiveMonthlyRain,5)*RoofArea_m2*CollectionEff-MIN(DailyDemand_L*INDEX('Rainfall Data'!$E$15:$E$26,5),MAX(P43+INDEX(ActiveMonthlyRain,5)*RoofArea_m2*CollectionEff-DeadStorage_L,0))-$B43,0)+MAX(Q43+INDEX(ActiveMonthlyRain,6)*RoofArea_m2*CollectionEff-MIN(DailyDemand_L*INDEX('Rainfall Data'!$E$15:$E$26,6),MAX(Q43+INDEX(ActiveMonthlyRain,6)*RoofArea_m2*CollectionEff-DeadStorage_L,0))-$B43,0)+MAX(R43+INDEX(ActiveMonthlyRain,7)*RoofArea_m2*CollectionEff-MIN(DailyDemand_L*INDEX('Rainfall Data'!$E$15:$E$26,7),MAX(R43+INDEX(ActiveMonthlyRain,7)*RoofArea_m2*CollectionEff-DeadStorage_L,0))-$B43,0)+MAX(S43+INDEX(ActiveMonthlyRain,8)*RoofArea_m2*CollectionEff-MIN(DailyDemand_L*INDEX('Rainfall Data'!$E$15:$E$26,8),MAX(S43+INDEX(ActiveMonthlyRain,8)*RoofArea_m2*CollectionEff-DeadStorage_L,0))-$B43,0)+MAX(T43+INDEX(ActiveMonthlyRain,9)*RoofArea_m2*CollectionEff-MIN(DailyDemand_L*INDEX('Rainfall Data'!$E$15:$E$26,9),MAX(T43+INDEX(ActiveMonthlyRain,9)*RoofArea_m2*CollectionEff-DeadStorage_L,0))-$B43,0)+MAX(U43+INDEX(ActiveMonthlyRain,10)*RoofArea_m2*CollectionEff-MIN(DailyDemand_L*INDEX('Rainfall Data'!$E$15:$E$26,10),MAX(U43+INDEX(ActiveMonthlyRain,10)*RoofArea_m2*CollectionEff-DeadStorage_L,0))-$B43,0)+MAX(V43+INDEX(ActiveMonthlyRain,11)*RoofArea_m2*CollectionEff-MIN(DailyDemand_L*INDEX('Rainfall Data'!$E$15:$E$26,11),MAX(V43+INDEX(ActiveMonthlyRain,11)*RoofArea_m2*CollectionEff-DeadStorage_L,0))-$B43,0)+MAX(W43+INDEX(ActiveMonthlyRain,12)*RoofArea_m2*CollectionEff-MIN(DailyDemand_L*INDEX('Rainfall Data'!$E$15:$E$26,12),MAX(W43+INDEX(ActiveMonthlyRain,12)*RoofArea_m2*CollectionEff-DeadStorage_L,0))-$B43,0) -> 0 | E43: =SUMPRODUCT(DailyDemand_L*'Rainfall Data'!$E$15:$E$26)-C43 -> 72440.323 | F43: =C43/SUMPRODUCT(DailyDemand_L*'Rainfall Data'!$E$15:$E$26) -> 0.26493838 | G43: =C43-C42 -> 0 | M43: =MIN(MAX(TankInitial_L+INDEX(ActiveMonthlyRain,1)*RoofArea_m2*CollectionEff-DailyDemand_L*INDEX('Rainfall Data'!$E$15:$E$26,1),0),$B43) -> 0 | N43: =MIN(MAX(M43+INDEX(ActiveMonthlyRain,2)*RoofArea_m2*CollectionEff-DailyDemand_L*INDEX('Rainfall Data'!$E$15:$E$26,2),0),$B43) -> 0 | O43: =MIN(MAX(N43+INDEX(ActiveMonthlyRain,3)*RoofArea_m2*CollectionEff-DailyDemand_L*INDEX('Rainfall Data'!$E$15:$E$26,3),0),$B43) -> 0 | P43: =MIN(MAX(O43+INDEX(ActiveMonthlyRain,4)*RoofArea_m2*CollectionEff-DailyDemand_L*INDEX('Rainfall Data'!$E$15:$E$26,4),0),$B43) -> 0 | Q43: =MIN(MAX(P43+INDEX(ActiveMonthlyRain,5)*RoofArea_m2*CollectionEff-DailyDemand_L*INDEX('Rainfall Data'!$E$15:$E$26,5),0),$B43) -> 0 | R43: =MIN(MAX(Q43+INDEX(ActiveMonthlyRain,6)*RoofArea_m2*CollectionEff-DailyDemand_L*INDEX('Rainfall Data'!$E$15:$E$26,6),0),$B43) -> 0 | S43: =MIN(MAX(R43+INDEX(ActiveMonthlyRain,7)*RoofArea_m2*CollectionEff-DailyDemand_L*INDEX('Rainfall Data'!$E$15:$E$26,7),0),$B43) -> 2830.8325 | T43: =MIN(MAX(S43+INDEX(ActiveMonthlyRain,8)*RoofArea_m2*CollectionEff-DailyDemand_L*INDEX('Rainfall Data'!$E$15:$E$26,8),0),$B43) -> 4283.101 | U43: =MIN(MAX(T43+INDEX(ActiveMonthlyRain,9)*RoofArea_m2*CollectionEff-DailyDemand_L*INDEX('Rainfall Data'!$E$15:$E$26,9),0),$B43) -> 0 | V43: =MIN(MAX(U43+INDEX(ActiveMonthlyRain,10)*RoofArea_m2*CollectionEff-DailyDemand_L*INDEX('Rainfall Data'!$E$15:$E$26,10),0),$B43) -> 0 | W43: =MIN(MAX(V43+INDEX(ActiveMonthlyRain,11)*RoofArea_m2*CollectionEff-DailyDemand_L*INDEX('Rainfall Data'!$E$15:$E$26,11),0),$B43) -> 0 | X43: =MIN(MAX(W43+INDEX(ActiveMonthlyRain,12)*RoofArea_m2*CollectionEff-DailyDemand_L*INDEX('Rainfall Data'!$E$15:$E$26,12),0),$B43) -> 0
B44: 8000 | C44: =MIN(DailyDemand_L*INDEX('Rainfall Data'!$E$15:$E$26,1),MAX(TankInitial_L+INDEX(ActiveMonthlyRain,1)*RoofArea_m2*CollectionEff-DeadStorage_L,0))+MIN(DailyDemand_L*INDEX('Rainfall Data'!$E$15:$E$26,2),MAX(M44+INDEX(ActiveMonthlyRain,2)*RoofArea_m2*CollectionEff-DeadStorage_L,0))+MIN(DailyDemand_L*INDEX('Rainfall Data'!$E$15:$E$26,3),MAX(N44+INDEX(ActiveMonthlyRain,3)*RoofArea_m2*CollectionEff-DeadStorage_L,0))+MIN(DailyDemand_L*INDEX('Rainfall Data'!$E$15:$E$26,4),MAX(O44+INDEX(ActiveMonthlyRain,4)*RoofArea_m2*CollectionEff-DeadStorage_L,0))+MIN(DailyDemand_L*INDEX('Rainfall Data'!$E$15:$E$26,5),MAX(P44+INDEX(ActiveMonthlyRain,5)*RoofArea_m2*CollectionEff-DeadStorage_L,0))+MIN(DailyDemand_L*INDEX('Rainfall Data'!$E$15:$E$26,6),MAX(Q44+INDEX(ActiveMonthlyRain,6)*RoofArea_m2*CollectionEff-DeadStorage_L,0))+MIN(DailyDemand_L*INDEX('Rainfall Data'!$E$15:$E$26,7),MAX(R44+INDEX(ActiveMonthlyRain,7)*RoofArea_m2*CollectionEff-DeadStorage_L,0))+MIN(DailyDemand_L*INDEX('Rainfall Data'!$E$15:$E$26,8),MAX(S44+INDEX(ActiveMonthlyRain,8)*RoofArea_m2*CollectionEff-DeadStorage_L,0))+MIN(DailyDemand_L*INDEX('Rainfall Data'!$E$15:$E$26,9),MAX(T44+INDEX(ActiveMonthlyRain,9)*RoofArea_m2*CollectionEff-DeadStorage_L,0))+MIN(DailyDemand_L*INDEX('Rainfall Data'!$E$15:$E$26,10),MAX(U44+INDEX(ActiveMonthlyRain,10)*RoofArea_m2*CollectionEff-DeadStorage_L,0))+MIN(DailyDemand_L*INDEX('Rainfall Data'!$E$15:$E$26,11),MAX(V44+INDEX(ActiveMonthlyRain,11)*RoofArea_m2*CollectionEff-DeadStorage_L,0))+MIN(DailyDemand_L*INDEX('Rainfall Data'!$E$15:$E$26,12),MAX(W44+INDEX(ActiveMonthlyRain,12)*RoofArea_m2*CollectionEff-DeadStorage_L,0)) -> 26109.677 | D44: =MAX(TankInitial_L+INDEX(ActiveMonthlyRain,1)*RoofArea_m2*CollectionEff-MIN(DailyDemand_L*INDEX('Rainfall Data'!$E$15:$E$26,1),MAX(TankInitial_L+INDEX(ActiveMonthlyRain,1)*RoofArea_m2*CollectionEff-DeadStorage_L,0))-$B44,0)+MAX(M44+INDEX(ActiveMonthlyRain,2)*RoofArea_m2*CollectionEff-MIN(DailyDemand_L*INDEX('Rainfall Data'!$E$15:$E$26,2),MAX(M44+INDEX(ActiveMonthlyRain,2)*RoofArea_m2*CollectionEff-DeadStorage_L,0))-$B44,0)+MAX(N44+INDEX(ActiveMonthlyRain,3)*RoofArea_m2*CollectionEff-MIN(DailyDemand_L*INDEX('Rainfall Data'!$E$15:$E$26,3),MAX(N44+INDEX(ActiveMonthlyRain,3)*RoofArea_m2*CollectionEff-DeadStorage_L,0))-$B44,0)+MAX(O44+INDEX(ActiveMonthlyRain,4)*RoofArea_m2*CollectionEff-MIN(DailyDemand_L*INDEX('Rainfall Data'!$E$15:$E$26,4),MAX(O44+INDEX(ActiveMonthlyRain,4)*RoofArea_m2*CollectionEff-DeadStorage_L,0))-$B44,0)+MAX(P44+INDEX(ActiveMonthlyRain,5)*RoofArea_m2*CollectionEff-MIN(DailyDemand_L*INDEX('Rainfall Data'!$E$15:$E$26,5),MAX(P44+INDEX(ActiveMonthlyRain,5)*RoofArea_m2*CollectionEff-DeadStorage_L,0))-$B44,0)+MAX(Q44+INDEX(ActiveMonthlyRain,6)*RoofArea_m2*CollectionEff-MIN(DailyDemand_L*INDEX('Rainfall Data'!$E$15:$E$26,6),MAX(Q44+INDEX(ActiveMonthlyRain,6)*RoofArea_m2*CollectionEff-DeadStorage_L,0))-$B44,0)+MAX(R44+INDEX(ActiveMonthlyRain,7)*RoofArea_m2*CollectionEff-MIN(DailyDemand_L*INDEX('Rainfall Data'!$E$15:$E$26,7),MAX(R44+INDEX(ActiveMonthlyRain,7)*RoofArea_m2*CollectionEff-DeadStorage_L,0))-$B44,0)+MAX(S44+INDEX(ActiveMonthlyRain,8)*RoofArea_m2*CollectionEff-MIN(DailyDemand_L*INDEX('Rainfall Data'!$E$15:$E$26,8),MAX(S44+INDEX(ActiveMonthlyRain,8)*RoofArea_m2*CollectionEff-DeadStorage_L,0))-$B44,0)+MAX(T44+INDEX(ActiveMonthlyRain,9)*RoofArea_m2*CollectionEff-MIN(DailyDemand_L*INDEX('Rainfall Data'!$E$15:$E$26,9),MAX(T44+INDEX(ActiveMonthlyRain,9)*RoofArea_m2*CollectionEff-DeadStorage_L,0))-$B44,0)+MAX(U44+INDEX(ActiveMonthlyRain,10)*RoofArea_m2*CollectionEff-MIN(DailyDemand_L*INDEX('Rainfall Data'!$E$15:$E$26,10),MAX(U44+INDEX(ActiveMonthlyRain,10)*RoofArea_m2*CollectionEff-DeadStorage_L,0))-$B44,0)+MAX(V44+INDEX(ActiveMonthlyRain,11)*RoofArea_m2*CollectionEff-MIN(DailyDemand_L*INDEX('Rainfall Data'!$E$15:$E$26,11),MAX(V44+INDEX(ActiveMonthlyRain,11)*RoofArea_m2*CollectionEff-DeadStorage_L,0))-$B44,0)+MAX(W44+INDEX(ActiveMonthlyRain,12)*RoofArea_m2*CollectionEff-MIN(DailyDemand_L*INDEX('Rainfall Data'!$E$15:$E$26,12),MAX(W44+INDEX(ActiveMonthlyRain,12)*RoofArea_m2*CollectionEff-DeadStorage_L,0))-$B44,0) -> 0 | E44: =SUMPRODUCT(DailyDemand_L*'Rainfall Data'!$E$15:$E$26)-C44 -> 72440.323 | F44: =C44/SUMPRODUCT(DailyDemand_L*'Rainfall Data'!$E$15:$E$26) -> 0.26493838 | G44: =C44-C43 -> 0 | M44: =MIN(MAX(TankInitial_L+INDEX(ActiveMonthlyRain,1)*RoofArea_m2*CollectionEff-DailyDemand_L*INDEX('Rainfall Data'!$E$15:$E$26,1),0),$B44) -> 0 | N44: =MIN(MAX(M44+INDEX(ActiveMonthlyRain,2)*RoofArea_m2*CollectionEff-DailyDemand_L*INDEX('Rainfall Data'!$E$15:$E$26,2),0),$B44) -> 0 | O44: =MIN(MAX(N44+INDEX(ActiveMonthlyRain,3)*RoofArea_m2*CollectionEff-DailyDemand_L*INDEX('Rainfall Data'!$E$15:$E$26,3),0),$B44) -> 0 | P44: =MIN(MAX(O44+INDEX(ActiveMonthlyRain,4)*RoofArea_m2*CollectionEff-DailyDemand_L*INDEX('Rainfall Data'!$E$15:$E$26,4),0),$B44) -> 0 | Q44: =MIN(MAX(P44+INDEX(ActiveMonthlyRain,5)*RoofArea_m2*CollectionEff-DailyDemand_L*INDEX('Rainfall Data'!$E$15:$E$26,5),0),$B44) -> 0 | R44: =MIN(MAX(Q44+INDEX(ActiveMonthlyRain,6)*RoofArea_m2*CollectionEff-DailyDemand_L*INDEX('Rainfall Data'!$E$15:$E$26,6),0),$B44) -> 0 | S44: =MIN(MAX(R44+INDEX(ActiveMonthlyRain,7)*RoofArea_m2*CollectionEff-DailyDemand_L*INDEX('Rainfall Data'!$E$15:$E$26,7),0),$B44) -> 2830.8325 | T44: =MIN(MAX(S44+INDEX(ActiveMonthlyRain,8)*RoofArea_m2*CollectionEff-DailyDemand_L*INDEX('Rainfall Data'!$E$15:$E$26,8),0),$B44) -> 4283.101 | U44: =MIN(MAX(T44+INDEX(ActiveMonthlyRain,9)*RoofArea_m2*CollectionEff-DailyDemand_L*INDEX('Rainfall Data'!$E$15:$E$26,9),0),$B44) -> 0 | V44: =MIN(MAX(U44+INDEX(ActiveMonthlyRain,10)*RoofArea_m2*CollectionEff-DailyDemand_L*INDEX('Rainfall Data'!$E$15:$E$26,10),0),$B44) -> 0 | W44: =MIN(MAX(V44+INDEX(ActiveMonthlyRain,11)*RoofArea_m2*CollectionEff-DailyDemand_L*INDEX('Rainfall Data'!$E$15:$E$26,11),0),$B44) -> 0 | X44: =MIN(MAX(W44+INDEX(ActiveMonthlyRain,12)*RoofArea_m2*CollectionEff-DailyDemand_L*INDEX('Rainfall Data'!$E$15:$E$26,12),0),$B44) -> 0
B45: 10000 | C45: =MIN(DailyDemand_L*INDEX('Rainfall Data'!$E$15:$E$26,1),MAX(TankInitial_L+INDEX(ActiveMonthlyRain,1)*RoofArea_m2*CollectionEff-DeadStorage_L,0))+MIN(DailyDemand_L*INDEX('Rainfall Data'!$E$15:$E$26,2),MAX(M45+INDEX(ActiveMonthlyRain,2)*RoofArea_m2*CollectionEff-DeadStorage_L,0))+MIN(DailyDemand_L*INDEX('Rainfall Data'!$E$15:$E$26,3),MAX(N45+INDEX(ActiveMonthlyRain,3)*RoofArea_m2*CollectionEff-DeadStorage_L,0))+MIN(DailyDemand_L*INDEX('Rainfall Data'!$E$15:$E$26,4),MAX(O45+INDEX(ActiveMonthlyRain,4)*RoofArea_m2*CollectionEff-DeadStorage_L,0))+MIN(DailyDemand_L*INDEX('Rainfall Data'!$E$15:$E$26,5),MAX(P45+INDEX(ActiveMonthlyRain,5)*RoofArea_m2*CollectionEff-DeadStorage_L,0))+MIN(DailyDemand_L*INDEX('Rainfall Data'!$E$15:$E$26,6),MAX(Q45+INDEX(ActiveMonthlyRain,6)*RoofArea_m2*CollectionEff-DeadStorage_L,0))+MIN(DailyDemand_L*INDEX('Rainfall Data'!$E$15:$E$26,7),MAX(R45+INDEX(ActiveMonthlyRain,7)*RoofArea_m2*CollectionEff-DeadStorage_L,0))+MIN(DailyDemand_L*INDEX('Rainfall Data'!$E$15:$E$26,8),MAX(S45+INDEX(ActiveMonthlyRain,8)*RoofArea_m2*CollectionEff-DeadStorage_L,0))+MIN(DailyDemand_L*INDEX('Rainfall Data'!$E$15:$E$26,9),MAX(T45+INDEX(ActiveMonthlyRain,9)*RoofArea_m2*CollectionEff-DeadStorage_L,0))+MIN(DailyDemand_L*INDEX('Rainfall Data'!$E$15:$E$26,10),MAX(U45+INDEX(ActiveMonthlyRain,10)*RoofArea_m2*CollectionEff-DeadStorage_L,0))+MIN(DailyDemand_L*INDEX('Rainfall Data'!$E$15:$E$26,11),MAX(V45+INDEX(ActiveMonthlyRain,11)*RoofArea_m2*CollectionEff-DeadStorage_L,0))+MIN(DailyDemand_L*INDEX('Rainfall Data'!$E$15:$E$26,12),MAX(W45+INDEX(ActiveMonthlyRain,12)*RoofArea_m2*CollectionEff-DeadStorage_L,0)) -> 26109.677 | D45: =MAX(TankInitial_L+INDEX(ActiveMonthlyRain,1)*RoofArea_m2*CollectionEff-MIN(DailyDemand_L*INDEX('Rainfall Data'!$E$15:$E$26,1),MAX(TankInitial_L+INDEX(ActiveMonthlyRain,1)*RoofArea_m2*CollectionEff-DeadStorage_L,0))-$B45,0)+MAX(M45+INDEX(ActiveMonthlyRain,2)*RoofArea_m2*CollectionEff-MIN(DailyDemand_L*INDEX('Rainfall Data'!$E$15:$E$26,2),MAX(M45+INDEX(ActiveMonthlyRain,2)*RoofArea_m2*CollectionEff-DeadStorage_L,0))-$B45,0)+MAX(N45+INDEX(ActiveMonthlyRain,3)*RoofArea_m2*CollectionEff-MIN(DailyDemand_L*INDEX('Rainfall Data'!$E$15:$E$26,3),MAX(N45+INDEX(ActiveMonthlyRain,3)*RoofArea_m2*CollectionEff-DeadStorage_L,0))-$B45,0)+MAX(O45+INDEX(ActiveMonthlyRain,4)*RoofArea_m2*CollectionEff-MIN(DailyDemand_L*INDEX('Rainfall Data'!$E$15:$E$26,4),MAX(O45+INDEX(ActiveMonthlyRain,4)*RoofArea_m2*CollectionEff-DeadStorage_L,0))-$B45,0)+MAX(P45+INDEX(ActiveMonthlyRain,5)*RoofArea_m2*CollectionEff-MIN(DailyDemand_L*INDEX('Rainfall Data'!$E$15:$E$26,5),MAX(P45+INDEX(ActiveMonthlyRain,5)*RoofArea_m2*CollectionEff-DeadStorage_L,0))-$B45,0)+MAX(Q45+INDEX(ActiveMonthlyRain,6)*RoofArea_m2*CollectionEff-MIN(DailyDemand_L*INDEX('Rainfall Data'!$E$15:$E$26,6),MAX(Q45+INDEX(ActiveMonthlyRain,6)*RoofArea_m2*CollectionEff-DeadStorage_L,0))-$B45,0)+MAX(R45+INDEX(ActiveMonthlyRain,7)*RoofArea_m2*CollectionEff-MIN(DailyDemand_L*INDEX('Rainfall Data'!$E$15:$E$26,7),MAX(R45+INDEX(ActiveMonthlyRain,7)*RoofArea_m2*CollectionEff-DeadStorage_L,0))-$B45,0)+MAX(S45+INDEX(ActiveMonthlyRain,8)*RoofArea_m2*CollectionEff-MIN(DailyDemand_L*INDEX('Rainfall Data'!$E$15:$E$26,8),MAX(S45+INDEX(ActiveMonthlyRain,8)*RoofArea_m2*CollectionEff-DeadStorage_L,0))-$B45,0)+MAX(T45+INDEX(ActiveMonthlyRain,9)*RoofArea_m2*CollectionEff-MIN(DailyDemand_L*INDEX('Rainfall Data'!$E$15:$E$26,9),MAX(T45+INDEX(ActiveMonthlyRain,9)*RoofArea_m2*CollectionEff-DeadStorage_L,0))-$B45,0)+MAX(U45+INDEX(ActiveMonthlyRain,10)*RoofArea_m2*CollectionEff-MIN(DailyDemand_L*INDEX('Rainfall Data'!$E$15:$E$26,10),MAX(U45+INDEX(ActiveMonthlyRain,10)*RoofArea_m2*CollectionEff-DeadStorage_L,0))-$B45,0)+MAX(V45+INDEX(ActiveMonthlyRain,11)*RoofArea_m2*CollectionEff-MIN(DailyDemand_L*INDEX('Rainfall Data'!$E$15:$E$26,11),MAX(V45+INDEX(ActiveMonthlyRain,11)*RoofArea_m2*CollectionEff-DeadStorage_L,0))-$B45,0)+MAX(W45+INDEX(ActiveMonthlyRain,12)*RoofArea_m2*CollectionEff-MIN(DailyDemand_L*INDEX('Rainfall Data'!$E$15:$E$26,12),MAX(W45+INDEX(ActiveMonthlyRain,12)*RoofArea_m2*CollectionEff-DeadStorage_L,0))-$B45,0) -> 0 | E45: =SUMPRODUCT(DailyDemand_L*'Rainfall Data'!$E$15:$E$26)-C45 -> 72440.323 | F45: =C45/SUMPRODUCT(DailyDemand_L*'Rainfall Data'!$E$15:$E$26) -> 0.26493838 | G45: =C45-C44 -> 0 | M45: =MIN(MAX(TankInitial_L+INDEX(ActiveMonthlyRain,1)*RoofArea_m2*CollectionEff-DailyDemand_L*INDEX('Rainfall Data'!$E$15:$E$26,1),0),$B45) -> 0 | N45: =MIN(MAX(M45+INDEX(ActiveMonthlyRain,2)*RoofArea_m2*CollectionEff-DailyDemand_L*INDEX('Rainfall Data'!$E$15:$E$26,2),0),$B45) -> 0 | O45: =MIN(MAX(N45+INDEX(ActiveMonthlyRain,3)*RoofArea_m2*CollectionEff-DailyDemand_L*INDEX('Rainfall Data'!$E$15:$E$26,3),0),$B45) -> 0 | P45: =MIN(MAX(O45+INDEX(ActiveMonthlyRain,4)*RoofArea_m2*CollectionEff-DailyDemand_L*INDEX('Rainfall Data'!$E$15:$E$26,4),0),$B45) -> 0 | Q45: =MIN(MAX(P45+INDEX(ActiveMonthlyRain,5)*RoofArea_m2*CollectionEff-DailyDemand_L*INDEX('Rainfall Data'!$E$15:$E$26,5),0),$B45) -> 0 | R45: =MIN(MAX(Q45+INDEX(ActiveMonthlyRain,6)*RoofArea_m2*CollectionEff-DailyDemand_L*INDEX('Rainfall Data'!$E$15:$E$26,6),0),$B45) -> 0 | S45: =MIN(MAX(R45+INDEX(ActiveMonthlyRain,7)*RoofArea_m2*CollectionEff-DailyDemand_L*INDEX('Rainfall Data'!$E$15:$E$26,7),0),$B45) -> 2830.8325 | T45: =MIN(MAX(S45+INDEX(ActiveMonthlyRain,8)*RoofArea_m2*CollectionEff-DailyDemand_L*INDEX('Rainfall Data'!$E$15:$E$26,8),0),$B45) -> 4283.101 | U45: =MIN(MAX(T45+INDEX(ActiveMonthlyRain,9)*RoofArea_m2*CollectionEff-DailyDemand_L*INDEX('Rainfall Data'!$E$15:$E$26,9),0),$B45) -> 0 | V45: =MIN(MAX(U45+INDEX(ActiveMonthlyRain,10)*RoofArea_m2*CollectionEff-DailyDemand_L*INDEX('Rainfall Data'!$E$15:$E$26,10),0),$B45) -> 0 | W45: =MIN(MAX(V45+INDEX(ActiveMonthlyRain,11)*RoofArea_m2*CollectionEff-DailyDemand_L*INDEX('Rainfall Data'!$E$15:$E$26,11),0),$B45) -> 0 | X45: =MIN(MAX(W45+INDEX(ActiveMonthlyRain,12)*RoofArea_m2*CollectionEff-DailyDemand_L*INDEX('Rainfall Data'!$E$15:$E$26,12),0),$B45) -> 0
B46: 12000 | C46: =MIN(DailyDemand_L*INDEX('Rainfall Data'!$E$15:$E$26,1),MAX(TankInitial_L+INDEX(ActiveMonthlyRain,1)*RoofArea_m2*CollectionEff-DeadStorage_L,0))+MIN(DailyDemand_L*INDEX('Rainfall Data'!$E$15:$E$26,2),MAX(M46+INDEX(ActiveMonthlyRain,2)*RoofArea_m2*CollectionEff-DeadStorage_L,0))+MIN(DailyDemand_L*INDEX('Rainfall Data'!$E$15:$E$26,3),MAX(N46+INDEX(ActiveMonthlyRain,3)*RoofArea_m2*CollectionEff-DeadStorage_L,0))+MIN(DailyDemand_L*INDEX('Rainfall Data'!$E$15:$E$26,4),MAX(O46+INDEX(ActiveMonthlyRain,4)*RoofArea_m2*CollectionEff-DeadStorage_L,0))+MIN(DailyDemand_L*INDEX('Rainfall Data'!$E$15:$E$26,5),MAX(P46+INDEX(ActiveMonthlyRain,5)*RoofArea_m2*CollectionEff-DeadStorage_L,0))+MIN(DailyDemand_L*INDEX('Rainfall Data'!$E$15:$E$26,6),MAX(Q46+INDEX(ActiveMonthlyRain,6)*RoofArea_m2*CollectionEff-DeadStorage_L,0))+MIN(DailyDemand_L*INDEX('Rainfall Data'!$E$15:$E$26,7),MAX(R46+INDEX(ActiveMonthlyRain,7)*RoofArea_m2*CollectionEff-DeadStorage_L,0))+MIN(DailyDemand_L*INDEX('Rainfall Data'!$E$15:$E$26,8),MAX(S46+INDEX(ActiveMonthlyRain,8)*RoofArea_m2*CollectionEff-DeadStorage_L,0))+MIN(DailyDemand_L*INDEX('Rainfall Data'!$E$15:$E$26,9),MAX(T46+INDEX(ActiveMonthlyRain,9)*RoofArea_m2*CollectionEff-DeadStorage_L,0))+MIN(DailyDemand_L*INDEX('Rainfall Data'!$E$15:$E$26,10),MAX(U46+INDEX(ActiveMonthlyRain,10)*RoofArea_m2*CollectionEff-DeadStorage_L,0))+MIN(DailyDemand_L*INDEX('Rainfall Data'!$E$15:$E$26,11),MAX(V46+INDEX(ActiveMonthlyRain,11)*RoofArea_m2*CollectionEff-DeadStorage_L,0))+MIN(DailyDemand_L*INDEX('Rainfall Data'!$E$15:$E$26,12),MAX(W46+INDEX(ActiveMonthlyRain,12)*RoofArea_m2*CollectionEff-DeadStorage_L,0)) -> 26109.677 | D46: =MAX(TankInitial_L+INDEX(ActiveMonthlyRain,1)*RoofArea_m2*CollectionEff-MIN(DailyDemand_L*INDEX('Rainfall Data'!$E$15:$E$26,1),MAX(TankInitial_L+INDEX(ActiveMonthlyRain,1)*RoofArea_m2*CollectionEff-DeadStorage_L,0))-$B46,0)+MAX(M46+INDEX(ActiveMonthlyRain,2)*RoofArea_m2*CollectionEff-MIN(DailyDemand_L*INDEX('Rainfall Data'!$E$15:$E$26,2),MAX(M46+INDEX(ActiveMonthlyRain,2)*RoofArea_m2*CollectionEff-DeadStorage_L,0))-$B46,0)+MAX(N46+INDEX(ActiveMonthlyRain,3)*RoofArea_m2*CollectionEff-MIN(DailyDemand_L*INDEX('Rainfall Data'!$E$15:$E$26,3),MAX(N46+INDEX(ActiveMonthlyRain,3)*RoofArea_m2*CollectionEff-DeadStorage_L,0))-$B46,0)+MAX(O46+INDEX(ActiveMonthlyRain,4)*RoofArea_m2*CollectionEff-MIN(DailyDemand_L*INDEX('Rainfall Data'!$E$15:$E$26,4),MAX(O46+INDEX(ActiveMonthlyRain,4)*RoofArea_m2*CollectionEff-DeadStorage_L,0))-$B46,0)+MAX(P46+INDEX(ActiveMonthlyRain,5)*RoofArea_m2*CollectionEff-MIN(DailyDemand_L*INDEX('Rainfall Data'!$E$15:$E$26,5),MAX(P46+INDEX(ActiveMonthlyRain,5)*RoofArea_m2*CollectionEff-DeadStorage_L,0))-$B46,0)+MAX(Q46+INDEX(ActiveMonthlyRain,6)*RoofArea_m2*CollectionEff-MIN(DailyDemand_L*INDEX('Rainfall Data'!$E$15:$E$26,6),MAX(Q46+INDEX(ActiveMonthlyRain,6)*RoofArea_m2*CollectionEff-DeadStorage_L,0))-$B46,0)+MAX(R46+INDEX(ActiveMonthlyRain,7)*RoofArea_m2*CollectionEff-MIN(DailyDemand_L*INDEX('Rainfall Data'!$E$15:$E$26,7),MAX(R46+INDEX(ActiveMonthlyRain,7)*RoofArea_m2*CollectionEff-DeadStorage_L,0))-$B46,0)+MAX(S46+INDEX(ActiveMonthlyRain,8)*RoofArea_m2*CollectionEff-MIN(DailyDemand_L*INDEX('Rainfall Data'!$E$15:$E$26,8),MAX(S46+INDEX(ActiveMonthlyRain,8)*RoofArea_m2*CollectionEff-DeadStorage_L,0))-$B46,0)+MAX(T46+INDEX(ActiveMonthlyRain,9)*RoofArea_m2*CollectionEff-MIN(DailyDemand_L*INDEX('Rainfall Data'!$E$15:$E$26,9),MAX(T46+INDEX(ActiveMonthlyRain,9)*RoofArea_m2*CollectionEff-DeadStorage_L,0))-$B46,0)+MAX(U46+INDEX(ActiveMonthlyRain,10)*RoofArea_m2*CollectionEff-MIN(DailyDemand_L*INDEX('Rainfall Data'!$E$15:$E$26,10),MAX(U46+INDEX(ActiveMonthlyRain,10)*RoofArea_m2*CollectionEff-DeadStorage_L,0))-$B46,0)+MAX(V46+INDEX(ActiveMonthlyRain,11)*RoofArea_m2*CollectionEff-MIN(DailyDemand_L*INDEX('Rainfall Data'!$E$15:$E$26,11),MAX(V46+INDEX(ActiveMonthlyRain,11)*RoofArea_m2*CollectionEff-DeadStorage_L,0))-$B46,0)+MAX(W46+INDEX(ActiveMonthlyRain,12)*RoofArea_m2*CollectionEff-MIN(DailyDemand_L*INDEX('Rainfall Data'!$E$15:$E$26,12),MAX(W46+INDEX(ActiveMonthlyRain,12)*RoofArea_m2*CollectionEff-DeadStorage_L,0))-$B46,0) -> 0 | E46: =SUMPRODUCT(DailyDemand_L*'Rainfall Data'!$E$15:$E$26)-C46 -> 72440.323 | F46: =C46/SUMPRODUCT(DailyDemand_L*'Rainfall Data'!$E$15:$E$26) -> 0.26493838 | G46: =C46-C45 -> 0 | M46: =MIN(MAX(TankInitial_L+INDEX(ActiveMonthlyRain,1)*RoofArea_m2*CollectionEff-DailyDemand_L*INDEX('Rainfall Data'!$E$15:$E$26,1),0),$B46) -> 0 | N46: =MIN(MAX(M46+INDEX(ActiveMonthlyRain,2)*RoofArea_m2*CollectionEff-DailyDemand_L*INDEX('Rainfall Data'!$E$15:$E$26,2),0),$B46) -> 0 | O46: =MIN(MAX(N46+INDEX(ActiveMonthlyRain,3)*RoofArea_m2*CollectionEff-DailyDemand_L*INDEX('Rainfall Data'!$E$15:$E$26,3),0),$B46) -> 0 | P46: =MIN(MAX(O46+INDEX(ActiveMonthlyRain,4)*RoofArea_m2*CollectionEff-DailyDemand_L*INDEX('Rainfall Data'!$E$15:$E$26,4),0),$B46) -> 0 | Q46: =MIN(MAX(P46+INDEX(ActiveMonthlyRain,5)*RoofArea_m2*CollectionEff-DailyDemand_L*INDEX('Rainfall Data'!$E$15:$E$26,5),0),$B46) -> 0 | R46: =MIN(MAX(Q46+INDEX(ActiveMonthlyRain,6)*RoofArea_m2*CollectionEff-DailyDemand_L*INDEX('Rainfall Data'!$E$15:$E$26,6),0),$B46) -> 0 | S46: =MIN(MAX(R46+INDEX(ActiveMonthlyRain,7)*RoofArea_m2*CollectionEff-DailyDemand_L*INDEX('Rainfall Data'!$E$15:$E$26,7),0),$B46) -> 2830.8325 | T46: =MIN(MAX(S46+INDEX(ActiveMonthlyRain,8)*RoofArea_m2*CollectionEff-DailyDemand_L*INDEX('Rainfall Data'!$E$15:$E$26,8),0),$B46) -> 4283.101 | U46: =MIN(MAX(T46+INDEX(ActiveMonthlyRain,9)*RoofArea_m2*CollectionEff-DailyDemand_L*INDEX('Rainfall Data'!$E$15:$E$26,9),0),$B46) -> 0 | V46: =MIN(MAX(U46+INDEX(ActiveMonthlyRain,10)*RoofArea_m2*CollectionEff-DailyDemand_L*INDEX('Rainfall Data'!$E$15:$E$26,10),0),$B46) -> 0 | W46: =MIN(MAX(V46+INDEX(ActiveMonthlyRain,11)*RoofArea_m2*CollectionEff-DailyDemand_L*INDEX('Rainfall Data'!$E$15:$E$26,11),0),$B46) -> 0 | X46: =MIN(MAX(W46+INDEX(ActiveMonthlyRain,12)*RoofArea_m2*CollectionEff-DailyDemand_L*INDEX('Rainfall Data'!$E$15:$E$26,12),0),$B46) -> 0
... B48: 20000 | C48: =MIN(DailyDemand_L*INDEX('Rainfall Data'!$E$15:$E$26,1),MAX(TankInitial_L+INDEX(ActiveMonthlyRain,1)*RoofArea_m2*CollectionEff-DeadStorage_L,0))+MIN(DailyDemand_L*INDEX('Rainfall Data'!$E$15:$E$26,2),MAX(M48+INDEX(ActiveMonthlyRain,2)*RoofArea_m2*CollectionEff-DeadStorage_L,0))+MIN(DailyDemand_L*INDEX('Rainfall Data'!$E$15:$E$26,3),MAX(N48+INDEX(ActiveMonthlyRain,3)*RoofArea_m2*CollectionEff-DeadStorage_L,0))+MIN(DailyDemand_L*INDEX('Rainfall Data'!$E$15:$E$26,4),MAX(O48+INDEX(ActiveMonthlyRain,4)*RoofArea_m2*CollectionEff-DeadStorage_L,0))+MIN(DailyDemand_L*INDEX('Rainfall Data'!$E$15:$E$26,5),MAX(P48+INDEX(ActiveMonthlyRain,5)*RoofArea_m2*CollectionEff-DeadStorage_L,0))+MIN(DailyDemand_L*INDEX('Rainfall Data'!$E$15:$E$26,6),MAX(Q48+INDEX(ActiveMonthlyRain,6)*RoofArea_m2*CollectionEff-DeadStorage_L,0))+MIN(DailyDemand_L*INDEX('Rainfall Data'!$E$15:$E$26,7),MAX(R48+INDEX(ActiveMonthlyRain,7)*RoofArea_m2*CollectionEff-DeadStorage_L,0))+MIN(DailyDemand_L*INDEX('Rainfall Data'!$E$15:$E$26,8),MAX(S48+INDEX(ActiveMonthlyRain,8)*RoofArea_m2*CollectionEff-DeadStorage_L,0))+MIN(DailyDemand_L*INDEX('Rainfall Data'!$E$15:$E$26,9),MAX(T48+INDEX(ActiveMonthlyRain,9)*RoofArea_m2*CollectionEff-DeadStorage_L,0))+MIN(DailyDemand_L*INDEX('Rainfall Data'!$E$15:$E$26,10),MAX(U48+INDEX(ActiveMonthlyRain,10)*RoofArea_m2*CollectionEff-DeadStorage_L,0))+MIN(DailyDemand_L*INDEX('Rainfall Data'!$E$15:$E$26,11),MAX(V48+INDEX(ActiveMonthlyRain,11)*RoofArea_m2*CollectionEff-DeadStorage_L,0))+MIN(DailyDemand_L*INDEX('Rainfall Data'!$E$15:$E$26,12),MAX(W48+INDEX(ActiveMonthlyRain,12)*RoofArea_m2*CollectionEff-DeadStorage_L,0)) -> 26109.677 | D48: =MAX(TankInitial_L+INDEX(ActiveMonthlyRain,1)*RoofArea_m2*CollectionEff-MIN(DailyDemand_L*INDEX('Rainfall Data'!$E$15:$E$26,1),MAX(TankInitial_L+INDEX(ActiveMonthlyRain,1)*RoofArea_m2*CollectionEff-DeadStorage_L,0))-$B48,0)+MAX(M48+INDEX(ActiveMonthlyRain,2)*RoofArea_m2*CollectionEff-MIN(DailyDemand_L*INDEX('Rainfall Data'!$E$15:$E$26,2),MAX(M48+INDEX(ActiveMonthlyRain,2)*RoofArea_m2*CollectionEff-DeadStorage_L,0))-$B48,0)+MAX(N48+INDEX(ActiveMonthlyRain,3)*RoofArea_m2*CollectionEff-MIN(DailyDemand_L*INDEX('Rainfall Data'!$E$15:$E$26,3),MAX(N48+INDEX(ActiveMonthlyRain,3)*RoofArea_m2*CollectionEff-DeadStorage_L,0))-$B48,0)+MAX(O48+INDEX(ActiveMonthlyRain,4)*RoofArea_m2*CollectionEff-MIN(DailyDemand_L*INDEX('Rainfall Data'!$E$15:$E$26,4),MAX(O48+INDEX(ActiveMonthlyRain,4)*RoofArea_m2*CollectionEff-DeadStorage_L,0))-$B48,0)+MAX(P48+INDEX(ActiveMonthlyRain,5)*RoofArea_m2*CollectionEff-MIN(DailyDemand_L*INDEX('Rainfall Data'!$E$15:$E$26,5),MAX(P48+INDEX(ActiveMonthlyRain,5)*RoofArea_m2*CollectionEff-DeadStorage_L,0))-$B48,0)+MAX(Q48+INDEX(ActiveMonthlyRain,6)*RoofArea_m2*CollectionEff-MIN(DailyDemand_L*INDEX('Rainfall Data'!$E$15:$E$26,6),MAX(Q48+INDEX(ActiveMonthlyRain,6)*RoofArea_m2*CollectionEff-DeadStorage_L,0))-$B48,0)+MAX(R48+INDEX(ActiveMonthlyRain,7)*RoofArea_m2*CollectionEff-MIN(DailyDemand_L*INDEX('Rainfall Data'!$E$15:$E$26,7),MAX(R48+INDEX(ActiveMonthlyRain,7)*RoofArea_m2*CollectionEff-DeadStorage_L,0))-$B48,0)+MAX(S48+INDEX(ActiveMonthlyRain,8)*RoofArea_m2*CollectionEff-MIN(DailyDemand_L*INDEX('Rainfall Data'!$E$15:$E$26,8),MAX(S48+INDEX(ActiveMonthlyRain,8)*RoofArea_m2*CollectionEff-DeadStorage_L,0))-$B48,0)+MAX(T48+INDEX(ActiveMonthlyRain,9)*RoofArea_m2*CollectionEff-MIN(DailyDemand_L*INDEX('Rainfall Data'!$E$15:$E$26,9),MAX(T48+INDEX(ActiveMonthlyRain,9)*RoofArea_m2*CollectionEff-DeadStorage_L,0))-$B48,0)+MAX(U48+INDEX(ActiveMonthlyRain,10)*RoofArea_m2*CollectionEff-MIN(DailyDemand_L*INDEX('Rainfall Data'!$E$15:$E$26,10),MAX(U48+INDEX(ActiveMonthlyRain,10)*RoofArea_m2*CollectionEff-DeadStorage_L,0))-$B48,0)+MAX(V48+INDEX(ActiveMonthlyRain,11)*RoofArea_m2*CollectionEff-MIN(DailyDemand_L*INDEX('Rainfall Data'!$E$15:$E$26,11),MAX(V48+INDEX(ActiveMonthlyRain,11)*RoofArea_m2*CollectionEff-DeadStorage_L,0))-$B48,0)+MAX(W48+INDEX(ActiveMonthlyRain,12)*RoofArea_m2*CollectionEff-MIN(DailyDemand_L*INDEX('Rainfall Data'!$E$15:$E$26,12),MAX(W48+INDEX(ActiveMonthlyRain,12)*RoofArea_m2*CollectionEff-DeadStorage_L,0))-$B48,0) -> 0 | E48: =SUMPRODUCT(DailyDemand_L*'Rainfall Data'!$E$15:$E$26)-C48 -> 72440.323 | F48: =C48/SUMPRODUCT(DailyDemand_L*'Rainfall Data'!$E$15:$E$26) -> 0.26493838 | G48: =C48-C47 -> 0 | M48: =MIN(MAX(TankInitial_L+INDEX(ActiveMonthlyRain,1)*RoofArea_m2*CollectionEff-DailyDemand_L*INDEX('Rainfall Data'!$E$15:$E$26,1),0),$B48) -> 0 | N48: =MIN(MAX(M48+INDEX(ActiveMonthlyRain,2)*RoofArea_m2*CollectionEff-DailyDemand_L*INDEX('Rainfall Data'!$E$15:$E$26,2),0),$B48) -> 0 | O48: =MIN(MAX(N48+INDEX(ActiveMonthlyRain,3)*RoofArea_m2*CollectionEff-DailyDemand_L*INDEX('Rainfall Data'!$E$15:$E$26,3),0),$B48) -> 0 | P48: =MIN(MAX(O48+INDEX(ActiveMonthlyRain,4)*RoofArea_m2*CollectionEff-DailyDemand_L*INDEX('Rainfall Data'!$E$15:$E$26,4),0),$B48) -> 0 | Q48: =MIN(MAX(P48+INDEX(ActiveMonthlyRain,5)*RoofArea_m2*CollectionEff-DailyDemand_L*INDEX('Rainfall Data'!$E$15:$E$26,5),0),$B48) -> 0 | R48: =MIN(MAX(Q48+INDEX(ActiveMonthlyRain,6)*RoofArea_m2*CollectionEff-DailyDemand_L*INDEX('Rainfall Data'!$E$15:$E$26,6),0),$B48) -> 0 | S48: =MIN(MAX(R48+INDEX(ActiveMonthlyRain,7)*RoofArea_m2*CollectionEff-DailyDemand_L*INDEX('Rainfall Data'!$E$15:$E$26,7),0),$B48) -> 2830.8325 | T48: =MIN(MAX(S48+INDEX(ActiveMonthlyRain,8)*RoofArea_m2*CollectionEff-DailyDemand_L*INDEX('Rainfall Data'!$E$15:$E$26,8),0),$B48) -> 4283.101 | U48: =MIN(MAX(T48+INDEX(ActiveMonthlyRain,9)*RoofArea_m2*CollectionEff-DailyDemand_L*INDEX('Rainfall Data'!$E$15:$E$26,9),0),$B48) -> 0 | V48: =MIN(MAX(U48+INDEX(ActiveMonthlyRain,10)*RoofArea_m2*CollectionEff-DailyDemand_L*INDEX('Rainfall Data'!$E$15:$E$26,10),0),$B48) -> 0 | W48: =MIN(MAX(V48+INDEX(ActiveMonthlyRain,11)*RoofArea_m2*CollectionEff-DailyDemand_L*INDEX('Rainfall Data'!$E$15:$E$26,11),0),$B48) -> 0 | X48: =MIN(MAX(W48+INDEX(ActiveMonthlyRain,12)*RoofArea_m2*CollectionEff-DailyDemand_L*INDEX('Rainfall Data'!$E$15:$E$26,12),0),$B48) -> 0
B51: RECOMMENDED TANK SIZE (from sweep -cross-check against Solver result)
B53: Recommended Capacity | C53: =INDEX(Sweep_TankSize,MATCH(MAX(Sweep_Supplied)*0.98,Sweep_Supplied,1)) -> 3000 | D53: litres -smallest size capturing 98% of the achievable annual supply (avoids oversizing).
B54: Max Achievable Annual Supply | C54: =MAX(Sweep_Supplied) -> 26109.677
B55: Supply at Current Tank Size | C55: =('Monthly Summary'!F18) -> 23546.306

Sheet Sensitivity
B2: SENSITIVITY ANALYSIS - Reliability Response to +/-25% Parameter Swings
B3: One-at-a-time (OAT) sensitivity: each block shifts a single parameter by -25%, 0%, +25%, all others held at base case, and recomputes annual reliability via the same monthly mass-balance approximation used in Tank Optimization.
B5: Scenario | C5: Multiplier | D5: Est. Annual Supplied (L) | E5: Est. Annual Reliability
B6: Roof Area
B7: -25% | C7: 0.75 | D7: =MIN(DailyDemand_L*INDEX('Rainfall Data'!$E$15:$E$26,1),MAX(TankInitial_L+INDEX(ActiveMonthlyRain,1)*RoofArea_m2*0.75*CollectionEff-DeadStorage_L,0))+MIN(DailyDemand_L*INDEX('Rainfall Data'!$E$15:$E$26,2),MAX(J7+INDEX(ActiveMonthlyRain,2)*RoofArea_m2*0.75*CollectionEff-DeadStorage_L,0))+MIN(DailyDemand_L*INDEX('Rainfall Data'!$E$15:$E$26,3),MAX(K7+INDEX(ActiveMonthlyRain,3)*RoofArea_m2*0.75*CollectionEff-DeadStorage_L,0))+MIN(DailyDemand_L*INDEX('Rainfall Data'!$E$15:$E$26,4),MAX(L7+INDEX(ActiveMonthlyRain,4)*RoofArea_m2*0.75*CollectionEff-DeadStorage_L,0))+MIN(DailyDemand_L*INDEX('Rainfall Data'!$E$15:$E$26,5),MAX(M7+INDEX(ActiveMonthlyRain,5)*RoofArea_m2*0.75*CollectionEff-DeadStorage_L,0))+MIN(DailyDemand_L*INDEX('Rainfall Data'!$E$15:$E$26,6),MAX(N7+INDEX(ActiveMonthlyRain,6)*RoofArea_m2*0.75*CollectionEff-DeadStorage_L,0))+MIN(DailyDemand_L*INDEX('Rainfall Data'!$E$15:$E$26,7),MAX(O7+INDEX(ActiveMonthlyRain,7)*RoofArea_m2*0.75*CollectionEff-DeadStorage_L,0))+MIN(DailyDemand_L*INDEX('Rainfall Data'!$E$15:$E$26,8),MAX(P7+INDEX(ActiveMonthlyRain,8)*RoofArea_m2*0.75*CollectionEff-DeadStorage_L,0))+MIN(DailyDemand_L*INDEX('Rainfall Data'!$E$15:$E$26,9),MAX(Q7+INDEX(ActiveMonthlyRain,9)*RoofArea_m2*0.75*CollectionEff-DeadStorage_L,0))+MIN(DailyDemand_L*INDEX('Rainfall Data'!$E$15:$E$26,10),MAX(R7+INDEX(ActiveMonthlyRain,10)*RoofArea_m2*0.75*CollectionEff-DeadStorage_L,0))+MIN(DailyDemand_L*INDEX('Rainfall Data'!$E$15:$E$26,11),MAX(S7+INDEX(ActiveMonthlyRain,11)*RoofArea_m2*0.75*CollectionEff-DeadStorage_L,0))+MIN(DailyDemand_L*INDEX('Rainfall Data'!$E$15:$E$26,12),MAX(T7+INDEX(ActiveMonthlyRain,12)*RoofArea_m2*0.75*CollectionEff-DeadStorage_L,0)) -> 19062.882 | E7: =D7/(SUMPRODUCT(DailyDemand_L*'Rainfall Data'!$E$15:$E$26)) -> 0.19343361 | J7: =MIN(MAX(TankInitial_L+INDEX(ActiveMonthlyRain,1)*RoofArea_m2*0.75*CollectionEff-DailyDemand_L*INDEX('Rainfall Data'!$E$15:$E$26,1),0),TankCapacity_L) -> 0 | K7: =MIN(MAX(J7+INDEX(ActiveMonthlyRain,2)*RoofArea_m2*0.75*CollectionEff-DailyDemand_L*INDEX('Rainfall Data'!$E$15:$E$26,2),0),TankCapacity_L) -> 0 | L7: =MIN(MAX(K7+INDEX(ActiveMonthlyRain,3)*RoofArea_m2*0.75*CollectionEff-DailyDemand_L*INDEX('Rainfall Data'!$E$15:$E$26,3),0),TankCapacity_L) -> 0 | M7: =MIN(MAX(L7+INDEX(ActiveMonthlyRain,4)*RoofArea_m2*0.75*CollectionEff-DailyDemand_L*INDEX('Rainfall Data'!$E$15:$E$26,4),0),TankCapacity_L) -> 0 | N7: =MIN(MAX(M7+INDEX(ActiveMonthlyRain,5)*RoofArea_m2*0.75*CollectionEff-DailyDemand_L*INDEX('Rainfall Data'!$E$15:$E$26,5),0),TankCapacity_L) -> 0 | O7: =MIN(MAX(N7+INDEX(ActiveMonthlyRain,6)*RoofArea_m2*0.75*CollectionEff-DailyDemand_L*INDEX('Rainfall Data'!$E$15:$E$26,6),0),TankCapacity_L) -> 0 | P7: =MIN(MAX(O7+INDEX(ActiveMonthlyRain,7)*RoofArea_m2*0.75*CollectionEff-DailyDemand_L*INDEX('Rainfall Data'!$E$15:$E$26,7),0),TankCapacity_L) -> 30.624375 | Q7: =MIN(MAX(P7+INDEX(ActiveMonthlyRain,8)*RoofArea_m2*0.75*CollectionEff-DailyDemand_L*INDEX('Rainfall Data'!$E$15:$E$26,8),0),TankCapacity_L) -> 0 | R7: =MIN(MAX(Q7+INDEX(ActiveMonthlyRain,9)*RoofArea_m2*0.75*CollectionEff-DailyDemand_L*INDEX('Rainfall Data'!$E$15:$E$26,9),0),TankCapacity_L) -> 0 | S7: =MIN(MAX(R7+INDEX(ActiveMonthlyRain,10)*RoofArea_m2*0.75*CollectionEff-DailyDemand_L*INDEX('Rainfall Data'!$E$15:$E$26,10),0),TankCapacity_L) -> 0 | T7: =MIN(MAX(S7+INDEX(ActiveMonthlyRain,11)*RoofArea_m2*0.75*CollectionEff-DailyDemand_L*INDEX('Rainfall Data'!$E$15:$E$26,11),0),TankCapacity_L) -> 0 | U7: =MIN(MAX(T7+INDEX(ActiveMonthlyRain,12)*RoofArea_m2*0.75*CollectionEff-DailyDemand_L*INDEX('Rainfall Data'!$E$15:$E$26,12),0),TankCapacity_L) -> 0
B8: Base | C8: 1 | D8: =MIN(DailyDemand_L*INDEX('Rainfall Data'!$E$15:$E$26,1),MAX(TankInitial_L+INDEX(ActiveMonthlyRain,1)*RoofArea_m2*CollectionEff-DeadStorage_L,0))+MIN(DailyDemand_L*INDEX('Rainfall Data'!$E$15:$E$26,2),MAX(J8+INDEX(ActiveMonthlyRain,2)*RoofArea_m2*CollectionEff-DeadStorage_L,0))+MIN(DailyDemand_L*INDEX('Rainfall Data'!$E$15:$E$26,3),MAX(K8+INDEX(ActiveMonthlyRain,3)*RoofArea_m2*CollectionEff-DeadStorage_L,0))+MIN(DailyDemand_L*INDEX('Rainfall Data'!$E$15:$E$26,4),MAX(L8+INDEX(ActiveMonthlyRain,4)*RoofArea_m2*CollectionEff-DeadStorage_L,0))+MIN(DailyDemand_L*INDEX('Rainfall Data'!$E$15:$E$26,5),MAX(M8+INDEX(ActiveMonthlyRain,5)*RoofArea_m2*CollectionEff-DeadStorage_L,0))+MIN(DailyDemand_L*INDEX('Rainfall Data'!$E$15:$E$26,6),MAX(N8+INDEX(ActiveMonthlyRain,6)*RoofArea_m2*CollectionEff-DeadStorage_L,0))+MIN(DailyDemand_L*INDEX('Rainfall Data'!$E$15:$E$26,7),MAX(O8+INDEX(ActiveMonthlyRain,7)*RoofArea_m2*CollectionEff-DeadStorage_L,0))+MIN(DailyDemand_L*INDEX('Rainfall Data'!$E$15:$E$26,8),MAX(P8+INDEX(ActiveMonthlyRain,8)*RoofArea_m2*CollectionEff-DeadStorage_L,0))+MIN(DailyDemand_L*INDEX('Rainfall Data'!$E$15:$E$26,9),MAX(Q8+INDEX(ActiveMonthlyRain,9)*RoofArea_m2*CollectionEff-DeadStorage_L,0))+MIN(DailyDemand_L*INDEX('Rainfall Data'!$E$15:$E$26,10),MAX(R8+INDEX(ActiveMonthlyRain,10)*RoofArea_m2*CollectionEff-DeadStorage_L,0))+MIN(DailyDemand_L*INDEX('Rainfall Data'!$E$15:$E$26,11),MAX(S8+INDEX(ActiveMonthlyRain,11)*RoofArea_m2*CollectionEff-DeadStorage_L,0))+MIN(DailyDemand_L*INDEX('Rainfall Data'!$E$15:$E$26,12),MAX(T8+INDEX(ActiveMonthlyRain,12)*RoofArea_m2*CollectionEff-DeadStorage_L,0)) -> 26109.677 | E8: =D8/(SUMPRODUCT(DailyDemand_L*'Rainfall Data'!$E$15:$E$26)) -> 0.26493838 | J8: =MIN(MAX(TankInitial_L+INDEX(ActiveMonthlyRain,1)*RoofArea_m2*CollectionEff-DailyDemand_L*INDEX('Rainfall Data'!$E$15:$E$26,1),0),TankCapacity_L) -> 0 | K8: =MIN(MAX(J8+INDEX(ActiveMonthlyRain,2)*RoofArea_m2*CollectionEff-DailyDemand_L*INDEX('Rainfall Data'!$E$15:$E$26,2),0),TankCapacity_L) -> 0 | L8: =MIN(MAX(K8+INDEX(ActiveMonthlyRain,3)*RoofArea_m2*CollectionEff-DailyDemand_L*INDEX('Rainfall Data'!$E$15:$E$26,3),0),TankCapacity_L) -> 0 | M8: =MIN(MAX(L8+INDEX(ActiveMonthlyRain,4)*RoofArea_m2*CollectionEff-DailyDemand_L*INDEX('Rainfall Data'!$E$15:$E$26,4),0),TankCapacity_L) -> 0 | N8: =MIN(MAX(M8+INDEX(ActiveMonthlyRain,5)*RoofArea_m2*CollectionEff-DailyDemand_L*INDEX('Rainfall Data'!$E$15:$E$26,5),0),TankCapacity_L) -> 0 | O8: =MIN(MAX(N8+INDEX(ActiveMonthlyRain,6)*RoofArea_m2*CollectionEff-DailyDemand_L*INDEX('Rainfall Data'!$E$15:$E$26,6),0),TankCapacity_L) -> 0 | P8: =MIN(MAX(O8+INDEX(ActiveMonthlyRain,7)*RoofArea_m2*CollectionEff-DailyDemand_L*INDEX('Rainfall Data'!$E$15:$E$26,7),0),TankCapacity_L) -> 2830.8325 | Q8: =MIN(MAX(P8+INDEX(ActiveMonthlyRain,8)*RoofArea_m2*CollectionEff-DailyDemand_L*INDEX('Rainfall Data'!$E$15:$E$26,8),0),TankCapacity_L) -> 4283.101 | R8: =MIN(MAX(Q8+INDEX(ActiveMonthlyRain,9)*RoofArea_m2*CollectionEff-DailyDemand_L*INDEX('Rainfall Data'!$E$15:$E$26,9),0),TankCapacity_L) -> 0 | S8: =MIN(MAX(R8+INDEX(ActiveMonthlyRain,10)*RoofArea_m2*CollectionEff-DailyDemand_L*INDEX('Rainfall Data'!$E$15:$E$26,10),0),TankCapacity_L) -> 0 | T8: =MIN(MAX(S8+INDEX(ActiveMonthlyRain,11)*RoofArea_m2*CollectionEff-DailyDemand_L*INDEX('Rainfall Data'!$E$15:$E$26,11),0),TankCapacity_L) -> 0 | U8: =MIN(MAX(T8+INDEX(ActiveMonthlyRain,12)*RoofArea_m2*CollectionEff-DailyDemand_L*INDEX('Rainfall Data'!$E$15:$E$26,12),0),TankCapacity_L) -> 0
B9: +25% | C9: 1.25 | D9: =MIN(DailyDemand_L*INDEX('Rainfall Data'!$E$15:$E$26,1),MAX(TankInitial_L+INDEX(ActiveMonthlyRain,1)*RoofArea_m2*1.25*CollectionEff-DeadStorage_L,0))+MIN(DailyDemand_L*INDEX('Rainfall Data'!$E$15:$E$26,2),MAX(J9+INDEX(ActiveMonthlyRain,2)*RoofArea_m2*1.25*CollectionEff-DeadStorage_L,0))+MIN(DailyDemand_L*INDEX('Rainfall Data'!$E$15:$E$26,3),MAX(K9+INDEX(ActiveMonthlyRain,3)*RoofArea_m2*1.25*CollectionEff-DeadStorage_L,0))+MIN(DailyDemand_L*INDEX('Rainfall Data'!$E$15:$E$26,4),MAX(L9+INDEX(ActiveMonthlyRain,4)*RoofArea_m2*1.25*CollectionEff-DeadStorage_L,0))+MIN(DailyDemand_L*INDEX('Rainfall Data'!$E$15:$E$26,5),MAX(M9+INDEX(ActiveMonthlyRain,5)*RoofArea_m2*1.25*CollectionEff-DeadStorage_L,0))+MIN(DailyDemand_L*INDEX('Rainfall Data'!$E$15:$E$26,6),MAX(N9+INDEX(ActiveMonthlyRain,6)*RoofArea_m2*1.25*CollectionEff-DeadStorage_L,0))+MIN(DailyDemand_L*INDEX('Rainfall Data'!$E$15:$E$26,7),MAX(O9+INDEX(ActiveMonthlyRain,7)*RoofArea_m2*1.25*CollectionEff-DeadStorage_L,0))+MIN(DailyDemand_L*INDEX('Rainfall Data'!$E$15:$E$26,8),MAX(P9+INDEX(ActiveMonthlyRain,8)*RoofArea_m2*1.25*CollectionEff-DeadStorage_L,0))+MIN(DailyDemand_L*INDEX('Rainfall Data'!$E$15:$E$26,9),MAX(Q9+INDEX(ActiveMonthlyRain,9)*RoofArea_m2*1.25*CollectionEff-DeadStorage_L,0))+MIN(DailyDemand_L*INDEX('Rainfall Data'!$E$15:$E$26,10),MAX(R9+INDEX(ActiveMonthlyRain,10)*RoofArea_m2*1.25*CollectionEff-DeadStorage_L,0))+MIN(DailyDemand_L*INDEX('Rainfall Data'!$E$15:$E$26,11),MAX(S9+INDEX(ActiveMonthlyRain,11)*RoofArea_m2*1.25*CollectionEff-DeadStorage_L,0))+MIN(DailyDemand_L*INDEX('Rainfall Data'!$E$15:$E$26,12),MAX(T9+INDEX(ActiveMonthlyRain,12)*RoofArea_m2*1.25*CollectionEff-DeadStorage_L,0)) -> 28410.031 | E9: =D9/(SUMPRODUCT(DailyDemand_L*'Rainfall Data'!$E$15:$E$26)) -> 0.28828038 | J9: =MIN(MAX(TankInitial_L+INDEX(ActiveMonthlyRain,1)*RoofArea_m2*1.25*CollectionEff-DailyDemand_L*INDEX('Rainfall Data'!$E$15:$E$26,1),0),TankCapacity_L) -> 0 | K9: =MIN(MAX(J9+INDEX(ActiveMonthlyRain,2)*RoofArea_m2*1.25*CollectionEff-DailyDemand_L*INDEX('Rainfall Data'!$E$15:$E$26,2),0),TankCapacity_L) -> 0 | L9: =MIN(MAX(K9+INDEX(ActiveMonthlyRain,3)*RoofArea_m2*1.25*CollectionEff-DailyDemand_L*INDEX('Rainfall Data'!$E$15:$E$26,3),0),TankCapacity_L) -> 0 | M9: =MIN(MAX(L9+INDEX(ActiveMonthlyRain,4)*RoofArea_m2*1.25*CollectionEff-DailyDemand_L*INDEX('Rainfall Data'!$E$15:$E$26,4),0),TankCapacity_L) -> 0 | N9: =MIN(MAX(M9+INDEX(ActiveMonthlyRain,5)*RoofArea_m2*1.25*CollectionEff-DailyDemand_L*INDEX('Rainfall Data'!$E$15:$E$26,5),0),TankCapacity_L) -> 0 | O9: =MIN(MAX(N9+INDEX(ActiveMonthlyRain,6)*RoofArea_m2*1.25*CollectionEff-DailyDemand_L*INDEX('Rainfall Data'!$E$15:$E$26,6),0),TankCapacity_L) -> 0 | P9: =MIN(MAX(O9+INDEX(ActiveMonthlyRain,7)*RoofArea_m2*1.25*CollectionEff-DailyDemand_L*INDEX('Rainfall Data'!$E$15:$E$26,7),0),TankCapacity_L) -> 5000 | Q9: =MIN(MAX(P9+INDEX(ActiveMonthlyRain,8)*RoofArea_m2*1.25*CollectionEff-DailyDemand_L*INDEX('Rainfall Data'!$E$15:$E$26,8),0),TankCapacity_L) -> 5000 | R9: =MIN(MAX(Q9+INDEX(ActiveMonthlyRain,9)*RoofArea_m2*1.25*CollectionEff-DailyDemand_L*INDEX('Rainfall Data'!$E$15:$E$26,9),0),TankCapacity_L) -> 131.00937 | S9: =MIN(MAX(R9+INDEX(ActiveMonthlyRain,10)*RoofArea_m2*1.25*CollectionEff-DailyDemand_L*INDEX('Rainfall Data'!$E$15:$E$26,10),0),TankCapacity_L) -> 0 | T9: =MIN(MAX(S9+INDEX(ActiveMonthlyRain,11)*RoofArea_m2*1.25*CollectionEff-DailyDemand_L*INDEX('Rainfall Data'!$E$15:$E$26,11),0),TankCapacity_L) -> 0 | U9: =MIN(MAX(T9+INDEX(ActiveMonthlyRain,12)*RoofArea_m2*1.25*CollectionEff-DailyDemand_L*INDEX('Rainfall Data'!$E$15:$E$26,12),0),TankCapacity_L) -> 0
B11: Rainfall (all months)
B12: -25% | C12: 0.75 | D12: =MIN(DailyDemand_L*INDEX('Rainfall Data'!$E$15:$E$26,1),MAX(TankInitial_L+(INDEX(ActiveMonthlyRain,1)*0.75)*RoofArea_m2*CollectionEff-DeadStorage_L,0))+MIN(DailyDemand_L*INDEX('Rainfall Data'!$E$15:$E$26,2),MAX(J12+(INDEX(ActiveMonthlyRain,2)*0.75)*RoofArea_m2*CollectionEff-DeadStorage_L,0))+MIN(DailyDemand_L*INDEX('Rainfall Data'!$E$15:$E$26,3),MAX(K12+(INDEX(ActiveMonthlyRain,3)*0.75)*RoofArea_m2*CollectionEff-DeadStorage_L,0))+MIN(DailyDemand_L*INDEX('Rainfall Data'!$E$15:$E$26,4),MAX(L12+(INDEX(ActiveMonthlyRain,4)*0.75)*RoofArea_m2*CollectionEff-DeadStorage_L,0))+MIN(DailyDemand_L*INDEX('Rainfall Data'!$E$15:$E$26,5),MAX(M12+(INDEX(ActiveMonthlyRain,5)*0.75)*RoofArea_m2*CollectionEff-DeadStorage_L,0))+MIN(DailyDemand_L*INDEX('Rainfall Data'!$E$15:$E$26,6),MAX(N12+(INDEX(ActiveMonthlyRain,6)*0.75)*RoofArea_m2*CollectionEff-DeadStorage_L,0))+MIN(DailyDemand_L*INDEX('Rainfall Data'!$E$15:$E$26,7),MAX(O12+(INDEX(ActiveMonthlyRain,7)*0.75)*RoofArea_m2*CollectionEff-DeadStorage_L,0))+MIN(DailyDemand_L*INDEX('Rainfall Data'!$E$15:$E$26,8),MAX(P12+(INDEX(ActiveMonthlyRain,8)*0.75)*RoofArea_m2*CollectionEff-DeadStorage_L,0))+MIN(DailyDemand_L*INDEX('Rainfall Data'!$E$15:$E$26,9),MAX(Q12+(INDEX(ActiveMonthlyRain,9)*0.75)*RoofArea_m2*CollectionEff-DeadStorage_L,0))+MIN(DailyDemand_L*INDEX('Rainfall Data'!$E$15:$E$26,10),MAX(R12+(INDEX(ActiveMonthlyRain,10)*0.75)*RoofArea_m2*CollectionEff-DeadStorage_L,0))+MIN(DailyDemand_L*INDEX('Rainfall Data'!$E$15:$E$26,11),MAX(S12+(INDEX(ActiveMonthlyRain,11)*0.75)*RoofArea_m2*CollectionEff-DeadStorage_L,0))+MIN(DailyDemand_L*INDEX('Rainfall Data'!$E$15:$E$26,12),MAX(T12+(INDEX(ActiveMonthlyRain,12)*0.75)*RoofArea_m2*CollectionEff-DeadStorage_L,0)) -> 19062.882 | E12: =D12/(SUMPRODUCT(DailyDemand_L*'Rainfall Data'!$E$15:$E$26)) -> 0.19343361 | J12: =MIN(MAX(TankInitial_L+(INDEX(ActiveMonthlyRain,1)*0.75)*RoofArea_m2*CollectionEff-DailyDemand_L*INDEX('Rainfall Data'!$E$15:$E$26,1),0),TankCapacity_L) -> 0 | K12: =MIN(MAX(J12+(INDEX(ActiveMonthlyRain,2)*0.75)*RoofArea_m2*CollectionEff-DailyDemand_L*INDEX('Rainfall Data'!$E$15:$E$26,2),0),TankCapacity_L) -> 0 | L12: =MIN(MAX(K12+(INDEX(ActiveMonthlyRain,3)*0.75)*RoofArea_m2*CollectionEff-DailyDemand_L*INDEX('Rainfall Data'!$E$15:$E$26,3),0),TankCapacity_L) -> 0 | M12: =MIN(MAX(L12+(INDEX(ActiveMonthlyRain,4)*0.75)*RoofArea_m2*CollectionEff-DailyDemand_L*INDEX('Rainfall Data'!$E$15:$E$26,4),0),TankCapacity_L) -> 0 | N12: =MIN(MAX(M12+(INDEX(ActiveMonthlyRain,5)*0.75)*RoofArea_m2*CollectionEff-DailyDemand_L*INDEX('Rainfall Data'!$E$15:$E$26,5),0),TankCapacity_L) -> 0 | O12: =MIN(MAX(N12+(INDEX(ActiveMonthlyRain,6)*0.75)*RoofArea_m2*CollectionEff-DailyDemand_L*INDEX('Rainfall Data'!$E$15:$E$26,6),0),TankCapacity_L) -> 0 | P12: =MIN(MAX(O12+(INDEX(ActiveMonthlyRain,7)*0.75)*RoofArea_m2*CollectionEff-DailyDemand_L*INDEX('Rainfall Data'!$E$15:$E$26,7),0),TankCapacity_L) -> 30.624375 | Q12: =MIN(MAX(P12+(INDEX(ActiveMonthlyRain,8)*0.75)*RoofArea_m2*CollectionEff-DailyDemand_L*INDEX('Rainfall Data'!$E$15:$E$26,8),0),TankCapacity_L) -> 0 | R12: =MIN(MAX(Q12+(INDEX(ActiveMonthlyRain,9)*0.75)*RoofArea_m2*CollectionEff-DailyDemand_L*INDEX('Rainfall Data'!$E$15:$E$26,9),0),TankCapacity_L) -> 0 | S12: =MIN(MAX(R12+(INDEX(ActiveMonthlyRain,10)*0.75)*RoofArea_m2*CollectionEff-DailyDemand_L*INDEX('Rainfall Data'!$E$15:$E$26,10),0),TankCapacity_L) -> 0 | T12: =MIN(MAX(S12+(INDEX(ActiveMonthlyRain,11)*0.75)*RoofArea_m2*CollectionEff-DailyDemand_L*INDEX('Rainfall Data'!$E$15:$E$26,11),0),TankCapacity_L) -> 0 | U12: =MIN(MAX(T12+(INDEX(ActiveMonthlyRain,12)*0.75)*RoofArea_m2*CollectionEff-DailyDemand_L*INDEX('Rainfall Data'!$E$15:$E$26,12),0),TankCapacity_L) -> 0
B13: Base | C13: 1 | D13: =MIN(DailyDemand_L*INDEX('Rainfall Data'!$E$15:$E$26,1),MAX(TankInitial_L+INDEX(ActiveMonthlyRain,1)*RoofArea_m2*CollectionEff-DeadStorage_L,0))+MIN(DailyDemand_L*INDEX('Rainfall Data'!$E$15:$E$26,2),MAX(J13+INDEX(ActiveMonthlyRain,2)*RoofArea_m2*CollectionEff-DeadStorage_L,0))+MIN(DailyDemand_L*INDEX('Rainfall Data'!$E$15:$E$26,3),MAX(K13+INDEX(ActiveMonthlyRain,3)*RoofArea_m2*CollectionEff-DeadStorage_L,0))+MIN(DailyDemand_L*INDEX('Rainfall Data'!$E$15:$E$26,4),MAX(L13+INDEX(ActiveMonthlyRain,4)*RoofArea_m2*CollectionEff-DeadStorage_L,0))+MIN(DailyDemand_L*INDEX('Rainfall Data'!$E$15:$E$26,5),MAX(M13+INDEX(ActiveMonthlyRain,5)*RoofArea_m2*CollectionEff-DeadStorage_L,0))+MIN(DailyDemand_L*INDEX('Rainfall Data'!$E$15:$E$26,6),MAX(N13+INDEX(ActiveMonthlyRain,6)*RoofArea_m2*CollectionEff-DeadStorage_L,0))+MIN(DailyDemand_L*INDEX('Rainfall Data'!$E$15:$E$26,7),MAX(O13+INDEX(ActiveMonthlyRain,7)*RoofArea_m2*CollectionEff-DeadStorage_L,0))+MIN(DailyDemand_L*INDEX('Rainfall Data'!$E$15:$E$26,8),MAX(P13+INDEX(ActiveMonthlyRain,8)*RoofArea_m2*CollectionEff-DeadStorage_L,0))+MIN(DailyDemand_L*INDEX('Rainfall Data'!$E$15:$E$26,9),MAX(Q13+INDEX(ActiveMonthlyRain,9)*RoofArea_m2*CollectionEff-DeadStorage_L,0))+MIN(DailyDemand_L*INDEX('Rainfall Data'!$E$15:$E$26,10),MAX(R13+INDEX(ActiveMonthlyRain,10)*RoofArea_m2*CollectionEff-DeadStorage_L,0))+MIN(DailyDemand_L*INDEX('Rainfall Data'!$E$15:$E$26,11),MAX(S13+INDEX(ActiveMonthlyRain,11)*RoofArea_m2*CollectionEff-DeadStorage_L,0))+MIN(DailyDemand_L*INDEX('Rainfall Data'!$E$15:$E$26,12),MAX(T13+INDEX(ActiveMonthlyRain,12)*RoofArea_m2*CollectionEff-DeadStorage_L,0)) -> 26109.677 | E13: =D13/(SUMPRODUCT(DailyDemand_L*'Rainfall Data'!$E$15:$E$26)) -> 0.26493838 | J13: =MIN(MAX(TankInitial_L+INDEX(ActiveMonthlyRain,1)*RoofArea_m2*CollectionEff-DailyDemand_L*INDEX('Rainfall Data'!$E$15:$E$26,1),0),TankCapacity_L) -> 0 | K13: =MIN(MAX(J13+INDEX(ActiveMonthlyRain,2)*RoofArea_m2*CollectionEff-DailyDemand_L*INDEX('Rainfall Data'!$E$15:$E$26,2),0),TankCapacity_L) -> 0 | L13: =MIN(MAX(K13+INDEX(ActiveMonthlyRain,3)*RoofArea_m2*CollectionEff-DailyDemand_L*INDEX('Rainfall Data'!$E$15:$E$26,3),0),TankCapacity_L) -> 0 | M13: =MIN(MAX(L13+INDEX(ActiveMonthlyRain,4)*RoofArea_m2*CollectionEff-DailyDemand_L*INDEX('Rainfall Data'!$E$15:$E$26,4),0),TankCapacity_L) -> 0 | N13: =MIN(MAX(M13+INDEX(ActiveMonthlyRain,5)*RoofArea_m2*CollectionEff-DailyDemand_L*INDEX('Rainfall Data'!$E$15:$E$26,5),0),TankCapacity_L) -> 0 | O13: =MIN(MAX(N13+INDEX(ActiveMonthlyRain,6)*RoofArea_m2*CollectionEff-DailyDemand_L*INDEX('Rainfall Data'!$E$15:$E$26,6),0),TankCapacity_L) -> 0 | P13: =MIN(MAX(O13+INDEX(ActiveMonthlyRain,7)*RoofArea_m2*CollectionEff-DailyDemand_L*INDEX('Rainfall Data'!$E$15:$E$26,7),0),TankCapacity_L) -> 2830.8325 | Q13: =MIN(MAX(P13+INDEX(ActiveMonthlyRain,8)*RoofArea_m2*CollectionEff-DailyDemand_L*INDEX('Rainfall Data'!$E$15:$E$26,8),0),TankCapacity_L) -> 4283.101 | R13: =MIN(MAX(Q13+INDEX(ActiveMonthlyRain,9)*RoofArea_m2*CollectionEff-DailyDemand_L*INDEX('Rainfall Data'!$E$15:$E$26,9),0),TankCapacity_L) -> 0 | S13: =MIN(MAX(R13+INDEX(ActiveMonthlyRain,10)*RoofArea_m2*CollectionEff-DailyDemand_L*INDEX('Rainfall Data'!$E$15:$E$26,10),0),TankCapacity_L) -> 0 | T13: =MIN(MAX(S13+INDEX(ActiveMonthlyRain,11)*RoofArea_m2*CollectionEff-DailyDemand_L*INDEX('Rainfall Data'!$E$15:$E$26,11),0),TankCapacity_L) -> 0 | U13: =MIN(MAX(T13+INDEX(ActiveMonthlyRain,12)*RoofArea_m2*CollectionEff-DailyDemand_L*INDEX('Rainfall Data'!$E$15:$E$26,12),0),TankCapacity_L) -> 0
B14: +25% | C14: 1.25 | D14: =MIN(DailyDemand_L*INDEX('Rainfall Data'!$E$15:$E$26,1),MAX(TankInitial_L+(INDEX(ActiveMonthlyRain,1)*1.25)*RoofArea_m2*CollectionEff-DeadStorage_L,0))+MIN(DailyDemand_L*INDEX('Rainfall Data'!$E$15:$E$26,2),MAX(J14+(INDEX(ActiveMonthlyRain,2)*1.25)*RoofArea_m2*CollectionEff-DeadStorage_L,0))+MIN(DailyDemand_L*INDEX('Rainfall Data'!$E$15:$E$26,3),MAX(K14+(INDEX(ActiveMonthlyRain,3)*1.25)*RoofArea_m2*CollectionEff-DeadStorage_L,0))+MIN(DailyDemand_L*INDEX('Rainfall Data'!$E$15:$E$26,4),MAX(L14+(INDEX(ActiveMonthlyRain,4)*1.25)*RoofArea_m2*CollectionEff-DeadStorage_L,0))+MIN(DailyDemand_L*INDEX('Rainfall Data'!$E$15:$E$26,5),MAX(M14+(INDEX(ActiveMonthlyRain,5)*1.25)*RoofArea_m2*CollectionEff-DeadStorage_L,0))+MIN(DailyDemand_L*INDEX('Rainfall Data'!$E$15:$E$26,6),MAX(N14+(INDEX(ActiveMonthlyRain,6)*1.25)*RoofArea_m2*CollectionEff-DeadStorage_L,0))+MIN(DailyDemand_L*INDEX('Rainfall Data'!$E$15:$E$26,7),MAX(O14+(INDEX(ActiveMonthlyRain,7)*1.25)*RoofArea_m2*CollectionEff-DeadStorage_L,0))+MIN(DailyDemand_L*INDEX('Rainfall Data'!$E$15:$E$26,8),MAX(P14+(INDEX(ActiveMonthlyRain,8)*1.25)*RoofArea_m2*CollectionEff-DeadStorage_L,0))+MIN(DailyDemand_L*INDEX('Rainfall Data'!$E$15:$E$26,9),MAX(Q14+(INDEX(ActiveMonthlyRain,9)*1.25)*RoofArea_m2*CollectionEff-DeadStorage_L,0))+MIN(DailyDemand_L*INDEX('Rainfall Data'!$E$15:$E$26,10),MAX(R14+(INDEX(ActiveMonthlyRain,10)*1.25)*RoofArea_m2*CollectionEff-DeadStorage_L,0))+MIN(DailyDemand_L*INDEX('Rainfall Data'!$E$15:$E$26,11),MAX(S14+(INDEX(ActiveMonthlyRain,11)*1.25)*RoofArea_m2*CollectionEff-DeadStorage_L,0))+MIN(DailyDemand_L*INDEX('Rainfall Data'!$E$15:$E$26,12),MAX(T14+(INDEX(ActiveMonthlyRain,12)*1.25)*RoofArea_m2*CollectionEff-DeadStorage_L,0)) -> 28410.031 | E14: =D14/(SUMPRODUCT(DailyDemand_L*'Rainfall Data'!$E$15:$E$26)) -> 0.28828038 | J14: =MIN(MAX(TankInitial_L+(INDEX(ActiveMonthlyRain,1)*1.25)*RoofArea_m2*CollectionEff-DailyDemand_L*INDEX('Rainfall Data'!$E$15:$E$26,1),0),TankCapacity_L) -> 0 | K14: =MIN(MAX(J14+(INDEX(ActiveMonthlyRain,2)*1.25)*RoofArea_m2*CollectionEff-DailyDemand_L*INDEX('Rainfall Data'!$E$15:$E$26,2),0),TankCapacity_L) -> 0 | L14: =MIN(MAX(K14+(INDEX(ActiveMonthlyRain,3)*1.25)*RoofArea_m2*CollectionEff-DailyDemand_L*INDEX('Rainfall Data'!$E$15:$E$26,3),0),TankCapacity_L) -> 0 | M14: =MIN(MAX(L14+(INDEX(ActiveMonthlyRain,4)*1.25)*RoofArea_m2*CollectionEff-DailyDemand_L*INDEX('Rainfall Data'!$E$15:$E$26,4),0),TankCapacity_L) -> 0 | N14: =MIN(MAX(M14+(INDEX(ActiveMonthlyRain,5)*1.25)*RoofArea_m2*CollectionEff-DailyDemand_L*INDEX('Rainfall Data'!$E$15:$E$26,5),0),TankCapacity_L) -> 0 | O14: =MIN(MAX(N14+(INDEX(ActiveMonthlyRain,6)*1.25)*RoofArea_m2*CollectionEff-DailyDemand_L*INDEX('Rainfall Data'!$E$15:$E$26,6),0),TankCapacity_L) -> 0 | P14: =MIN(MAX(O14+(INDEX(ActiveMonthlyRain,7)*1.25)*RoofArea_m2*CollectionEff-DailyDemand_L*INDEX('Rainfall Data'!$E$15:$E$26,7),0),TankCapacity_L) -> 5000 | Q14: =MIN(MAX(P14+(INDEX(ActiveMonthlyRain,8)*1.25)*RoofArea_m2*CollectionEff-DailyDemand_L*INDEX('Rainfall Data'!$E$15:$E$26,8),0),TankCapacity_L) -> 5000 | R14: =MIN(MAX(Q14+(INDEX(ActiveMonthlyRain,9)*1.25)*RoofArea_m2*CollectionEff-DailyDemand_L*INDEX('Rainfall Data'!$E$15:$E$26,9),0),TankCapacity_L) -> 131.00937 | S14: =MIN(MAX(R14+(INDEX(ActiveMonthlyRain,10)*1.25)*RoofArea_m2*CollectionEff-DailyDemand_L*INDEX('Rainfall Data'!$E$15:$E$26,10),0),TankCapacity_L) -> 0 | T14: =MIN(MAX(S14+(INDEX(ActiveMonthlyRain,11)*1.25)*RoofArea_m2*CollectionEff-DailyDemand_L*INDEX('Rainfall Data'!$E$15:$E$26,11),0),TankCapacity_L) -> 0 | U14: =MIN(MAX(T14+(INDEX(ActiveMonthlyRain,12)*1.25)*RoofArea_m2*CollectionEff-DailyDemand_L*INDEX('Rainfall Data'!$E$15:$E$26,12),0),TankCapacity_L) -> 0
B16: Water Demand
B17: -25% | C17: 0.75 | D17: =MIN((DailyDemand_L*0.75)*INDEX('Rainfall Data'!$E$15:$E$26,1),MAX(TankInitial_L+INDEX(ActiveMonthlyRain,1)*RoofArea_m2*CollectionEff-DeadStorage_L,0))+MIN((DailyDemand_L*0.75)*INDEX('Rainfall Data'!$E$15:$E$26,2),MAX(J17+INDEX(ActiveMonthlyRain,2)*RoofArea_m2*CollectionEff-DeadStorage_L,0))+MIN((DailyDemand_L*0.75)*INDEX('Rainfall Data'!$E$15:$E$26,3),MAX(K17+INDEX(ActiveMonthlyRain,3)*RoofArea_m2*CollectionEff-DeadStorage_L,0))+MIN((DailyDemand_L*0.75)*INDEX('Rainfall Data'!$E$15:$E$26,4),MAX(L17+INDEX(ActiveMonthlyRain,4)*RoofArea_m2*CollectionEff-DeadStorage_L,0))+MIN((DailyDemand_L*0.75)*INDEX('Rainfall Data'!$E$15:$E$26,5),MAX(M17+INDEX(ActiveMonthlyRain,5)*RoofArea_m2*CollectionEff-DeadStorage_L,0))+MIN((DailyDemand_L*0.75)*INDEX('Rainfall Data'!$E$15:$E$26,6),MAX(N17+INDEX(ActiveMonthlyRain,6)*RoofArea_m2*CollectionEff-DeadStorage_L,0))+MIN((DailyDemand_L*0.75)*INDEX('Rainfall Data'!$E$15:$E$26,7),MAX(O17+INDEX(ActiveMonthlyRain,7)*RoofArea_m2*CollectionEff-DeadStorage_L,0))+MIN((DailyDemand_L*0.75)*INDEX('Rainfall Data'!$E$15:$E$26,8),MAX(P17+INDEX(ActiveMonthlyRain,8)*RoofArea_m2*CollectionEff-DeadStorage_L,0))+MIN((DailyDemand_L*0.75)*INDEX('Rainfall Data'!$E$15:$E$26,9),MAX(Q17+INDEX(ActiveMonthlyRain,9)*RoofArea_m2*CollectionEff-DeadStorage_L,0))+MIN((DailyDemand_L*0.75)*INDEX('Rainfall Data'!$E$15:$E$26,10),MAX(R17+INDEX(ActiveMonthlyRain,10)*RoofArea_m2*CollectionEff-DeadStorage_L,0))+MIN((DailyDemand_L*0.75)*INDEX('Rainfall Data'!$E$15:$E$26,11),MAX(S17+INDEX(ActiveMonthlyRain,11)*RoofArea_m2*CollectionEff-DeadStorage_L,0))+MIN((DailyDemand_L*0.75)*INDEX('Rainfall Data'!$E$15:$E$26,12),MAX(T17+INDEX(ActiveMonthlyRain,12)*RoofArea_m2*CollectionEff-DeadStorage_L,0)) -> 22841.576 | E17: =D17/(SUMPRODUCT(DailyDemand_L*'Rainfall Data'!$E$15:$E$26)) -> 0.23177652 | J17: =MIN(MAX(TankInitial_L+INDEX(ActiveMonthlyRain,1)*RoofArea_m2*CollectionEff-(DailyDemand_L*0.75)*INDEX('Rainfall Data'!$E$15:$E$26,1),0),TankCapacity_L) -> 0 | K17: =MIN(MAX(J17+INDEX(ActiveMonthlyRain,2)*RoofArea_m2*CollectionEff-(DailyDemand_L*0.75)*INDEX('Rainfall Data'!$E$15:$E$26,2),0),TankCapacity_L) -> 0 | L17: =MIN(MAX(K17+INDEX(ActiveMonthlyRain,3)*RoofArea_m2*CollectionEff-(DailyDemand_L*0.75)*INDEX('Rainfall Data'!$E$15:$E$26,3),0),TankCapacity_L) -> 0 | M17: =MIN(MAX(L17+INDEX(ActiveMonthlyRain,4)*RoofArea_m2*CollectionEff-(DailyDemand_L*0.75)*INDEX('Rainfall Data'!$E$15:$E$26,4),0),TankCapacity_L) -> 0 | N17: =MIN(MAX(M17+INDEX(ActiveMonthlyRain,5)*RoofArea_m2*CollectionEff-(DailyDemand_L*0.75)*INDEX('Rainfall Data'!$E$15:$E$26,5),0),TankCapacity_L) -> 0 | O17: =MIN(MAX(N17+INDEX(ActiveMonthlyRain,6)*RoofArea_m2*CollectionEff-(DailyDemand_L*0.75)*INDEX('Rainfall Data'!$E$15:$E$26,6),0),TankCapacity_L) -> 0 | P17: =MIN(MAX(O17+INDEX(ActiveMonthlyRain,7)*RoofArea_m2*CollectionEff-(DailyDemand_L*0.75)*INDEX('Rainfall Data'!$E$15:$E$26,7),0),TankCapacity_L) -> 4923.3325 | Q17: =MIN(MAX(P17+INDEX(ActiveMonthlyRain,8)*RoofArea_m2*CollectionEff-(DailyDemand_L*0.75)*INDEX('Rainfall Data'!$E$15:$E$26,8),0),TankCapacity_L) -> 5000 | R17: =MIN(MAX(Q17+INDEX(ActiveMonthlyRain,9)*RoofArea_m2*CollectionEff-(DailyDemand_L*0.75)*INDEX('Rainfall Data'!$E$15:$E$26,9),0),TankCapacity_L) -> 1509.8075 | S17: =MIN(MAX(R17+INDEX(ActiveMonthlyRain,10)*RoofArea_m2*CollectionEff-(DailyDemand_L*0.75)*INDEX('Rainfall Data'!$E$15:$E$26,10),0),TankCapacity_L) -> 0 | T17: =MIN(MAX(S17+INDEX(ActiveMonthlyRain,11)*RoofArea_m2*CollectionEff-(DailyDemand_L*0.75)*INDEX('Rainfall Data'!$E$15:$E$26,11),0),TankCapacity_L) -> 0 | U17: =MIN(MAX(T17+INDEX(ActiveMonthlyRain,12)*RoofArea_m2*CollectionEff-(DailyDemand_L*0.75)*INDEX('Rainfall Data'!$E$15:$E$26,12),0),TankCapacity_L) -> 0
B18: Base | C18: 1 | D18: =MIN(DailyDemand_L*INDEX('Rainfall Data'!$E$15:$E$26,1),MAX(TankInitial_L+INDEX(ActiveMonthlyRain,1)*RoofArea_m2*CollectionEff-DeadStorage_L,0))+MIN(DailyDemand_L*INDEX('Rainfall Data'!$E$15:$E$26,2),MAX(J18+INDEX(ActiveMonthlyRain,2)*RoofArea_m2*CollectionEff-DeadStorage_L,0))+MIN(DailyDemand_L*INDEX('Rainfall Data'!$E$15:$E$26,3),MAX(K18+INDEX(ActiveMonthlyRain,3)*RoofArea_m2*CollectionEff-DeadStorage_L,0))+MIN(DailyDemand_L*INDEX('Rainfall Data'!$E$15:$E$26,4),MAX(L18+INDEX(ActiveMonthlyRain,4)*RoofArea_m2*CollectionEff-DeadStorage_L,0))+MIN(DailyDemand_L*INDEX('Rainfall Data'!$E$15:$E$26,5),MAX(M18+INDEX(ActiveMonthlyRain,5)*RoofArea_m2*CollectionEff-DeadStorage_L,0))+MIN(DailyDemand_L*INDEX('Rainfall Data'!$E$15:$E$26,6),MAX(N18+INDEX(ActiveMonthlyRain,6)*RoofArea_m2*CollectionEff-DeadStorage_L,0))+MIN(DailyDemand_L*INDEX('Rainfall Data'!$E$15:$E$26,7),MAX(O18+INDEX(ActiveMonthlyRain,7)*RoofArea_m2*CollectionEff-DeadStorage_L,0))+MIN(DailyDemand_L*INDEX('Rainfall Data'!$E$15:$E$26,8),MAX(P18+INDEX(ActiveMonthlyRain,8)*RoofArea_m2*CollectionEff-DeadStorage_L,0))+MIN(DailyDemand_L*INDEX('Rainfall Data'!$E$15:$E$26,9),MAX(Q18+INDEX(ActiveMonthlyRain,9)*RoofArea_m2*CollectionEff-DeadStorage_L,0))+MIN(DailyDemand_L*INDEX('Rainfall Data'!$E$15:$E$26,10),MAX(R18+INDEX(ActiveMonthlyRain,10)*RoofArea_m2*CollectionEff-DeadStorage_L,0))+MIN(DailyDemand_L*INDEX('Rainfall Data'!$E$15:$E$26,11),MAX(S18+INDEX(ActiveMonthlyRain,11)*RoofArea_m2*CollectionEff-DeadStorage_L,0))+MIN(DailyDemand_L*INDEX('Rainfall Data'!$E$15:$E$26,12),MAX(T18+INDEX(ActiveMonthlyRain,12)*RoofArea_m2*CollectionEff-DeadStorage_L,0)) -> 26109.677 | E18: =D18/(SUMPRODUCT(DailyDemand_L*'Rainfall Data'!$E$15:$E$26)) -> 0.26493838 | J18: =MIN(MAX(TankInitial_L+INDEX(ActiveMonthlyRain,1)*RoofArea_m2*CollectionEff-DailyDemand_L*INDEX('Rainfall Data'!$E$15:$E$26,1),0),TankCapacity_L) -> 0 | K18: =MIN(MAX(J18+INDEX(ActiveMonthlyRain,2)*RoofArea_m2*CollectionEff-DailyDemand_L*INDEX('Rainfall Data'!$E$15:$E$26,2),0),TankCapacity_L) -> 0 | L18: =MIN(MAX(K18+INDEX(ActiveMonthlyRain,3)*RoofArea_m2*CollectionEff-DailyDemand_L*INDEX('Rainfall Data'!$E$15:$E$26,3),0),TankCapacity_L) -> 0 | M18: =MIN(MAX(L18+INDEX(ActiveMonthlyRain,4)*RoofArea_m2*CollectionEff-DailyDemand_L*INDEX('Rainfall Data'!$E$15:$E$26,4),0),TankCapacity_L) -> 0 | N18: =MIN(MAX(M18+INDEX(ActiveMonthlyRain,5)*RoofArea_m2*CollectionEff-DailyDemand_L*INDEX('Rainfall Data'!$E$15:$E$26,5),0),TankCapacity_L) -> 0 | O18: =MIN(MAX(N18+INDEX(ActiveMonthlyRain,6)*RoofArea_m2*CollectionEff-DailyDemand_L*INDEX('Rainfall Data'!$E$15:$E$26,6),0),TankCapacity_L) -> 0 | P18: =MIN(MAX(O18+INDEX(ActiveMonthlyRain,7)*RoofArea_m2*CollectionEff-DailyDemand_L*INDEX('Rainfall Data'!$E$15:$E$26,7),0),TankCapacity_L) -> 2830.8325 | Q18: =MIN(MAX(P18+INDEX(ActiveMonthlyRain,8)*RoofArea_m2*CollectionEff-DailyDemand_L*INDEX('Rainfall Data'!$E$15:$E$26,8),0),TankCapacity_L) -> 4283.101 | R18: =MIN(MAX(Q18+INDEX(ActiveMonthlyRain,9)*RoofArea_m2*CollectionEff-DailyDemand_L*INDEX('Rainfall Data'!$E$15:$E$26,9),0),TankCapacity_L) -> 0 | S18: =MIN(MAX(R18+INDEX(ActiveMonthlyRain,10)*RoofArea_m2*CollectionEff-DailyDemand_L*INDEX('Rainfall Data'!$E$15:$E$26,10),0),TankCapacity_L) -> 0 | T18: =MIN(MAX(S18+INDEX(ActiveMonthlyRain,11)*RoofArea_m2*CollectionEff-DailyDemand_L*INDEX('Rainfall Data'!$E$15:$E$26,11),0),TankCapacity_L) -> 0 | U18: =MIN(MAX(T18+INDEX(ActiveMonthlyRain,12)*RoofArea_m2*CollectionEff-DailyDemand_L*INDEX('Rainfall Data'!$E$15:$E$26,12),0),TankCapacity_L) -> 0
B19: +25% | C19: 1.25 | D19: =MIN((DailyDemand_L*1.25)*INDEX('Rainfall Data'!$E$15:$E$26,1),MAX(TankInitial_L+INDEX(ActiveMonthlyRain,1)*RoofArea_m2*CollectionEff-DeadStorage_L,0))+MIN((DailyDemand_L*1.25)*INDEX('Rainfall Data'!$E$15:$E$26,2),MAX(J19+INDEX(ActiveMonthlyRain,2)*RoofArea_m2*CollectionEff-DeadStorage_L,0))+MIN((DailyDemand_L*1.25)*INDEX('Rainfall Data'!$E$15:$E$26,3),MAX(K19+INDEX(ActiveMonthlyRain,3)*RoofArea_m2*CollectionEff-DeadStorage_L,0))+MIN((DailyDemand_L*1.25)*INDEX('Rainfall Data'!$E$15:$E$26,4),MAX(L19+INDEX(ActiveMonthlyRain,4)*RoofArea_m2*CollectionEff-DeadStorage_L,0))+MIN((DailyDemand_L*1.25)*INDEX('Rainfall Data'!$E$15:$E$26,5),MAX(M19+INDEX(ActiveMonthlyRain,5)*RoofArea_m2*CollectionEff-DeadStorage_L,0))+MIN((DailyDemand_L*1.25)*INDEX('Rainfall Data'!$E$15:$E$26,6),MAX(N19+INDEX(ActiveMonthlyRain,6)*RoofArea_m2*CollectionEff-DeadStorage_L,0))+MIN((DailyDemand_L*1.25)*INDEX('Rainfall Data'!$E$15:$E$26,7),MAX(O19+INDEX(ActiveMonthlyRain,7)*RoofArea_m2*CollectionEff-DeadStorage_L,0))+MIN((DailyDemand_L*1.25)*INDEX('Rainfall Data'!$E$15:$E$26,8),MAX(P19+INDEX(ActiveMonthlyRain,8)*RoofArea_m2*CollectionEff-DeadStorage_L,0))+MIN((DailyDemand_L*1.25)*INDEX('Rainfall Data'!$E$15:$E$26,9),MAX(Q19+INDEX(ActiveMonthlyRain,9)*RoofArea_m2*CollectionEff-DeadStorage_L,0))+MIN((DailyDemand_L*1.25)*INDEX('Rainfall Data'!$E$15:$E$26,10),MAX(R19+INDEX(ActiveMonthlyRain,10)*RoofArea_m2*CollectionEff-DeadStorage_L,0))+MIN((DailyDemand_L*1.25)*INDEX('Rainfall Data'!$E$15:$E$26,11),MAX(S19+INDEX(ActiveMonthlyRain,11)*RoofArea_m2*CollectionEff-DeadStorage_L,0))+MIN((DailyDemand_L*1.25)*INDEX('Rainfall Data'!$E$15:$E$26,12),MAX(T19+INDEX(ActiveMonthlyRain,12)*RoofArea_m2*CollectionEff-DeadStorage_L,0)) -> 26007.778 | E19: =D19/(SUMPRODUCT(DailyDemand_L*'Rainfall Data'!$E$15:$E$26)) -> 0.2639044 | J19: =MIN(MAX(TankInitial_L+INDEX(ActiveMonthlyRain,1)*RoofArea_m2*CollectionEff-(DailyDemand_L*1.25)*INDEX('Rainfall Data'!$E$15:$E$26,1),0),TankCapacity_L) -> 0 | K19: =MIN(MAX(J19+INDEX(ActiveMonthlyRain,2)*RoofArea_m2*CollectionEff-(DailyDemand_L*1.25)*INDEX('Rainfall Data'!$E$15:$E$26,2),0),TankCapacity_L) -> 0 | L19: =MIN(MAX(K19+INDEX(ActiveMonthlyRain,3)*RoofArea_m2*CollectionEff-(DailyDemand_L*1.25)*INDEX('Rainfall Data'!$E$15:$E$26,3),0),TankCapacity_L) -> 0 | M19: =MIN(MAX(L19+INDEX(ActiveMonthlyRain,4)*RoofArea_m2*CollectionEff-(DailyDemand_L*1.25)*INDEX('Rainfall Data'!$E$15:$E$26,4),0),TankCapacity_L) -> 0 | N19: =MIN(MAX(M19+INDEX(ActiveMonthlyRain,5)*RoofArea_m2*CollectionEff-(DailyDemand_L*1.25)*INDEX('Rainfall Data'!$E$15:$E$26,5),0),TankCapacity_L) -> 0 | O19: =MIN(MAX(N19+INDEX(ActiveMonthlyRain,6)*RoofArea_m2*CollectionEff-(DailyDemand_L*1.25)*INDEX('Rainfall Data'!$E$15:$E$26,6),0),TankCapacity_L) -> 0 | P19: =MIN(MAX(O19+INDEX(ActiveMonthlyRain,7)*RoofArea_m2*CollectionEff-(DailyDemand_L*1.25)*INDEX('Rainfall Data'!$E$15:$E$26,7),0),TankCapacity_L) -> 738.3325 | Q19: =MIN(MAX(P19+INDEX(ActiveMonthlyRain,8)*RoofArea_m2*CollectionEff-(DailyDemand_L*1.25)*INDEX('Rainfall Data'!$E$15:$E$26,8),0),TankCapacity_L) -> 98.101 | R19: =MIN(MAX(Q19+INDEX(ActiveMonthlyRain,9)*RoofArea_m2*CollectionEff-(DailyDemand_L*1.25)*INDEX('Rainfall Data'!$E$15:$E$26,9),0),TankCapacity_L) -> 0 | S19: =MIN(MAX(R19+INDEX(ActiveMonthlyRain,10)*RoofArea_m2*CollectionEff-(DailyDemand_L*1.25)*INDEX('Rainfall Data'!$E$15:$E$26,10),0),TankCapacity_L) -> 0 | T19: =MIN(MAX(S19+INDEX(ActiveMonthlyRain,11)*RoofArea_m2*CollectionEff-(DailyDemand_L*1.25)*INDEX('Rainfall Data'!$E$15:$E$26,11),0),TankCapacity_L) -> 0 | U19: =MIN(MAX(T19+INDEX(ActiveMonthlyRain,12)*RoofArea_m2*CollectionEff-(DailyDemand_L*1.25)*INDEX('Rainfall Data'!$E$15:$E$26,12),0),TankCapacity_L) -> 0
B21: Collection Efficiency
B22: -25% | C22: 0.75 | D22: =MIN(DailyDemand_L*INDEX('Rainfall Data'!$E$15:$E$26,1),MAX(TankInitial_L+INDEX(ActiveMonthlyRain,1)*RoofArea_m2*CollectionEff*0.75-DeadStorage_L,0))+MIN(DailyDemand_L*INDEX('Rainfall Data'!$E$15:$E$26,2),MAX(J22+INDEX(ActiveMonthlyRain,2)*RoofArea_m2*CollectionEff*0.75-DeadStorage_L,0))+MIN(DailyDemand_L*INDEX('Rainfall Data'!$E$15:$E$26,3),MAX(K22+INDEX(ActiveMonthlyRain,3)*RoofArea_m2*CollectionEff*0.75-DeadStorage_L,0))+MIN(DailyDemand_L*INDEX('Rainfall Data'!$E$15:$E$26,4),MAX(L22+INDEX(ActiveMonthlyRain,4)*RoofArea_m2*CollectionEff*0.75-DeadStorage_L,0))+MIN(DailyDemand_L*INDEX('Rainfall Data'!$E$15:$E$26,5),MAX(M22+INDEX(ActiveMonthlyRain,5)*RoofArea_m2*CollectionEff*0.75-DeadStorage_L,0))+MIN(DailyDemand_L*INDEX('Rainfall Data'!$E$15:$E$26,6),MAX(N22+INDEX(ActiveMonthlyRain,6)*RoofArea_m2*CollectionEff*0.75-DeadStorage_L,0))+MIN(DailyDemand_L*INDEX('Rainfall Data'!$E$15:$E$26,7),MAX(O22+INDEX(ActiveMonthlyRain,7)*RoofArea_m2*CollectionEff*0.75-DeadStorage_L,0))+MIN(DailyDemand_L*INDEX('Rainfall Data'!$E$15:$E$26,8),MAX(P22+INDEX(ActiveMonthlyRain,8)*RoofArea_m2*CollectionEff*0.75-DeadStorage_L,0))+MIN(DailyDemand_L*INDEX('Rainfall Data'!$E$15:$E$26,9),MAX(Q22+INDEX(ActiveMonthlyRain,9)*RoofArea_m2*CollectionEff*0.75-DeadStorage_L,0))+MIN(DailyDemand_L*INDEX('Rainfall Data'!$E$15:$E$26,10),MAX(R22+INDEX(ActiveMonthlyRain,10)*RoofArea_m2*CollectionEff*0.75-DeadStorage_L,0))+MIN(DailyDemand_L*INDEX('Rainfall Data'!$E$15:$E$26,11),MAX(S22+INDEX(ActiveMonthlyRain,11)*RoofArea_m2*CollectionEff*0.75-DeadStorage_L,0))+MIN(DailyDemand_L*INDEX('Rainfall Data'!$E$15:$E$26,12),MAX(T22+INDEX(ActiveMonthlyRain,12)*RoofArea_m2*CollectionEff*0.75-DeadStorage_L,0)) -> 19062.882 | E22: =D22/(SUMPRODUCT(DailyDemand_L*'Rainfall Data'!$E$15:$E$26)) -> 0.19343361 | J22: =MIN(MAX(TankInitial_L+INDEX(ActiveMonthlyRain,1)*RoofArea_m2*CollectionEff*0.75-DailyDemand_L*INDEX('Rainfall Data'!$E$15:$E$26,1),0),TankCapacity_L) -> 0 | K22: =MIN(MAX(J22+INDEX(ActiveMonthlyRain,2)*RoofArea_m2*CollectionEff*0.75-DailyDemand_L*INDEX('Rainfall Data'!$E$15:$E$26,2),0),TankCapacity_L) -> 0 | L22: =MIN(MAX(K22+INDEX(ActiveMonthlyRain,3)*RoofArea_m2*CollectionEff*0.75-DailyDemand_L*INDEX('Rainfall Data'!$E$15:$E$26,3),0),TankCapacity_L) -> 0 | M22: =MIN(MAX(L22+INDEX(ActiveMonthlyRain,4)*RoofArea_m2*CollectionEff*0.75-DailyDemand_L*INDEX('Rainfall Data'!$E$15:$E$26,4),0),TankCapacity_L) -> 0 | N22: =MIN(MAX(M22+INDEX(ActiveMonthlyRain,5)*RoofArea_m2*CollectionEff*0.75-DailyDemand_L*INDEX('Rainfall Data'!$E$15:$E$26,5),0),TankCapacity_L) -> 0 | O22: =MIN(MAX(N22+INDEX(ActiveMonthlyRain,6)*RoofArea_m2*CollectionEff*0.75-DailyDemand_L*INDEX('Rainfall Data'!$E$15:$E$26,6),0),TankCapacity_L) -> 0 | P22: =MIN(MAX(O22+INDEX(ActiveMonthlyRain,7)*RoofArea_m2*CollectionEff*0.75-DailyDemand_L*INDEX('Rainfall Data'!$E$15:$E$26,7),0),TankCapacity_L) -> 30.624375 | Q22: =MIN(MAX(P22+INDEX(ActiveMonthlyRain,8)*RoofArea_m2*CollectionEff*0.75-DailyDemand_L*INDEX('Rainfall Data'!$E$15:$E$26,8),0),TankCapacity_L) -> 0 | R22: =MIN(MAX(Q22+INDEX(ActiveMonthlyRain,9)*RoofArea_m2*CollectionEff*0.75-DailyDemand_L*INDEX('Rainfall Data'!$E$15:$E$26,9),0),TankCapacity_L) -> 0 | S22: =MIN(MAX(R22+INDEX(ActiveMonthlyRain,10)*RoofArea_m2*CollectionEff*0.75-DailyDemand_L*INDEX('Rainfall Data'!$E$15:$E$26,10),0),TankCapacity_L) -> 0 | T22: =MIN(MAX(S22+INDEX(ActiveMonthlyRain,11)*RoofArea_m2*CollectionEff*0.75-DailyDemand_L*INDEX('Rainfall Data'!$E$15:$E$26,11),0),TankCapacity_L) -> 0 | U22: =MIN(MAX(T22+INDEX(ActiveMonthlyRain,12)*RoofArea_m2*CollectionEff*0.75-DailyDemand_L*INDEX('Rainfall Data'!$E$15:$E$26,12),0),TankCapacity_L) -> 0
B23: Base | C23: 1 | D23: =MIN(DailyDemand_L*INDEX('Rainfall Data'!$E$15:$E$26,1),MAX(TankInitial_L+INDEX(ActiveMonthlyRain,1)*RoofArea_m2*CollectionEff-DeadStorage_L,0))+MIN(DailyDemand_L*INDEX('Rainfall Data'!$E$15:$E$26,2),MAX(J23+INDEX(ActiveMonthlyRain,2)*RoofArea_m2*CollectionEff-DeadStorage_L,0))+MIN(DailyDemand_L*INDEX('Rainfall Data'!$E$15:$E$26,3),MAX(K23+INDEX(ActiveMonthlyRain,3)*RoofArea_m2*CollectionEff-DeadStorage_L,0))+MIN(DailyDemand_L*INDEX('Rainfall Data'!$E$15:$E$26,4),MAX(L23+INDEX(ActiveMonthlyRain,4)*RoofArea_m2*CollectionEff-DeadStorage_L,0))+MIN(DailyDemand_L*INDEX('Rainfall Data'!$E$15:$E$26,5),MAX(M23+INDEX(ActiveMonthlyRain,5)*RoofArea_m2*CollectionEff-DeadStorage_L,0))+MIN(DailyDemand_L*INDEX('Rainfall Data'!$E$15:$E$26,6),MAX(N23+INDEX(ActiveMonthlyRain,6)*RoofArea_m2*CollectionEff-DeadStorage_L,0))+MIN(DailyDemand_L*INDEX('Rainfall Data'!$E$15:$E$26,7),MAX(O23+INDEX(ActiveMonthlyRain,7)*RoofArea_m2*CollectionEff-DeadStorage_L,0))+MIN(DailyDemand_L*INDEX('Rainfall Data'!$E$15:$E$26,8),MAX(P23+INDEX(ActiveMonthlyRain,8)*RoofArea_m2*CollectionEff-DeadStorage_L,0))+MIN(DailyDemand_L*INDEX('Rainfall Data'!$E$15:$E$26,9),MAX(Q23+INDEX(ActiveMonthlyRain,9)*RoofArea_m2*CollectionEff-DeadStorage_L,0))+MIN(DailyDemand_L*INDEX('Rainfall Data'!$E$15:$E$26,10),MAX(R23+INDEX(ActiveMonthlyRain,10)*RoofArea_m2*CollectionEff-DeadStorage_L,0))+MIN(DailyDemand_L*INDEX('Rainfall Data'!$E$15:$E$26,11),MAX(S23+INDEX(ActiveMonthlyRain,11)*RoofArea_m2*CollectionEff-DeadStorage_L,0))+MIN(DailyDemand_L*INDEX('Rainfall Data'!$E$15:$E$26,12),MAX(T23+INDEX(ActiveMonthlyRain,12)*RoofArea_m2*CollectionEff-DeadStorage_L,0)) -> 26109.677 | E23: =D23/(SUMPRODUCT(DailyDemand_L*'Rainfall Data'!$E$15:$E$26)) -> 0.26493838 | J23: =MIN(MAX(TankInitial_L+INDEX(ActiveMonthlyRain,1)*RoofArea_m2*CollectionEff-DailyDemand_L*INDEX('Rainfall Data'!$E$15:$E$26,1),0),TankCapacity_L) -> 0 | K23: =MIN(MAX(J23+INDEX(ActiveMonthlyRain,2)*RoofArea_m2*CollectionEff-DailyDemand_L*INDEX('Rainfall Data'!$E$15:$E$26,2),0),TankCapacity_L) -> 0 | L23: =MIN(MAX(K23+INDEX(ActiveMonthlyRain,3)*RoofArea_m2*CollectionEff-DailyDemand_L*INDEX('Rainfall Data'!$E$15:$E$26,3),0),TankCapacity_L) -> 0 | M23: =MIN(MAX(L23+INDEX(ActiveMonthlyRain,4)*RoofArea_m2*CollectionEff-DailyDemand_L*INDEX('Rainfall Data'!$E$15:$E$26,4),0),TankCapacity_L) -> 0 | N23: =MIN(MAX(M23+INDEX(ActiveMonthlyRain,5)*RoofArea_m2*CollectionEff-DailyDemand_L*INDEX('Rainfall Data'!$E$15:$E$26,5),0),TankCapacity_L) -> 0 | O23: =MIN(MAX(N23+INDEX(ActiveMonthlyRain,6)*RoofArea_m2*CollectionEff-DailyDemand_L*INDEX('Rainfall Data'!$E$15:$E$26,6),0),TankCapacity_L) -> 0 | P23: =MIN(MAX(O23+INDEX(ActiveMonthlyRain,7)*RoofArea_m2*CollectionEff-DailyDemand_L*INDEX('Rainfall Data'!$E$15:$E$26,7),0),TankCapacity_L) -> 2830.8325 | Q23: =MIN(MAX(P23+INDEX(ActiveMonthlyRain,8)*RoofArea_m2*CollectionEff-DailyDemand_L*INDEX('Rainfall Data'!$E$15:$E$26,8),0),TankCapacity_L) -> 4283.101 | R23: =MIN(MAX(Q23+INDEX(ActiveMonthlyRain,9)*RoofArea_m2*CollectionEff-DailyDemand_L*INDEX('Rainfall Data'!$E$15:$E$26,9),0),TankCapacity_L) -> 0 | S23: =MIN(MAX(R23+INDEX(ActiveMonthlyRain,10)*RoofArea_m2*CollectionEff-DailyDemand_L*INDEX('Rainfall Data'!$E$15:$E$26,10),0),TankCapacity_L) -> 0 | T23: =MIN(MAX(S23+INDEX(ActiveMonthlyRain,11)*RoofArea_m2*CollectionEff-DailyDemand_L*INDEX('Rainfall Data'!$E$15:$E$26,11),0),TankCapacity_L) -> 0 | U23: =MIN(MAX(T23+INDEX(ActiveMonthlyRain,12)*RoofArea_m2*CollectionEff-DailyDemand_L*INDEX('Rainfall Data'!$E$15:$E$26,12),0),TankCapacity_L) -> 0
B24: +25% | C24: 1.25 | D24: =MIN(DailyDemand_L*INDEX('Rainfall Data'!$E$15:$E$26,1),MAX(TankInitial_L+INDEX(ActiveMonthlyRain,1)*RoofArea_m2*CollectionEff*1.25-DeadStorage_L,0))+MIN(DailyDemand_L*INDEX('Rainfall Data'!$E$15:$E$26,2),MAX(J24+INDEX(ActiveMonthlyRain,2)*RoofArea_m2*CollectionEff*1.25-DeadStorage_L,0))+MIN(DailyDemand_L*INDEX('Rainfall Data'!$E$15:$E$26,3),MAX(K24+INDEX(ActiveMonthlyRain,3)*RoofArea_m2*CollectionEff*1.25-DeadStorage_L,0))+MIN(DailyDemand_L*INDEX('Rainfall Data'!$E$15:$E$26,4),MAX(L24+INDEX(ActiveMonthlyRain,4)*RoofArea_m2*CollectionEff*1.25-DeadStorage_L,0))+MIN(DailyDemand_L*INDEX('Rainfall Data'!$E$15:$E$26,5),MAX(M24+INDEX(ActiveMonthlyRain,5)*RoofArea_m2*CollectionEff*1.25-DeadStorage_L,0))+MIN(DailyDemand_L*INDEX('Rainfall Data'!$E$15:$E$26,6),MAX(N24+INDEX(ActiveMonthlyRain,6)*RoofArea_m2*CollectionEff*1.25-DeadStorage_L,0))+MIN(DailyDemand_L*INDEX('Rainfall Data'!$E$15:$E$26,7),MAX(O24+INDEX(ActiveMonthlyRain,7)*RoofArea_m2*CollectionEff*1.25-DeadStorage_L,0))+MIN(DailyDemand_L*INDEX('Rainfall Data'!$E$15:$E$26,8),MAX(P24+INDEX(ActiveMonthlyRain,8)*RoofArea_m2*CollectionEff*1.25-DeadStorage_L,0))+MIN(DailyDemand_L*INDEX('Rainfall Data'!$E$15:$E$26,9),MAX(Q24+INDEX(ActiveMonthlyRain,9)*RoofArea_m2*CollectionEff*1.25-DeadStorage_L,0))+MIN(DailyDemand_L*INDEX('Rainfall Data'!$E$15:$E$26,10),MAX(R24+INDEX(ActiveMonthlyRain,10)*RoofArea_m2*CollectionEff*1.25-DeadStorage_L,0))+MIN(DailyDemand_L*INDEX('Rainfall Data'!$E$15:$E$26,11),MAX(S24+INDEX(ActiveMonthlyRain,11)*RoofArea_m2*CollectionEff*1.25-DeadStorage_L,0))+MIN(DailyDemand_L*INDEX('Rainfall Data'!$E$15:$E$26,12),MAX(T24+INDEX(ActiveMonthlyRain,12)*RoofArea_m2*CollectionEff*1.25-DeadStorage_L,0)) -> 28410.031 | E24: =D24/(SUMPRODUCT(DailyDemand_L*'Rainfall Data'!$E$15:$E$26)) -> 0.28828038 | J24: =MIN(MAX(TankInitial_L+INDEX(ActiveMonthlyRain,1)*RoofArea_m2*CollectionEff*1.25-DailyDemand_L*INDEX('Rainfall Data'!$E$15:$E$26,1),0),TankCapacity_L) -> 0 | K24: =MIN(MAX(J24+INDEX(ActiveMonthlyRain,2)*RoofArea_m2*CollectionEff*1.25-DailyDemand_L*INDEX('Rainfall Data'!$E$15:$E$26,2),0),TankCapacity_L) -> 0 | L24: =MIN(MAX(K24+INDEX(ActiveMonthlyRain,3)*RoofArea_m2*CollectionEff*1.25-DailyDemand_L*INDEX('Rainfall Data'!$E$15:$E$26,3),0),TankCapacity_L) -> 0 | M24: =MIN(MAX(L24+INDEX(ActiveMonthlyRain,4)*RoofArea_m2*CollectionEff*1.25-DailyDemand_L*INDEX('Rainfall Data'!$E$15:$E$26,4),0),TankCapacity_L) -> 0 | N24: =MIN(MAX(M24+INDEX(ActiveMonthlyRain,5)*RoofArea_m2*CollectionEff*1.25-DailyDemand_L*INDEX('Rainfall Data'!$E$15:$E$26,5),0),TankCapacity_L) -> 0 | O24: =MIN(MAX(N24+INDEX(ActiveMonthlyRain,6)*RoofArea_m2*CollectionEff*1.25-DailyDemand_L*INDEX('Rainfall Data'!$E$15:$E$26,6),0),TankCapacity_L) -> 0 | P24: =MIN(MAX(O24+INDEX(ActiveMonthlyRain,7)*RoofArea_m2*CollectionEff*1.25-DailyDemand_L*INDEX('Rainfall Data'!$E$15:$E$26,7),0),TankCapacity_L) -> 5000 | Q24: =MIN(MAX(P24+INDEX(ActiveMonthlyRain,8)*RoofArea_m2*CollectionEff*1.25-DailyDemand_L*INDEX('Rainfall Data'!$E$15:$E$26,8),0),TankCapacity_L) -> 5000 | R24: =MIN(MAX(Q24+INDEX(ActiveMonthlyRain,9)*RoofArea_m2*CollectionEff*1.25-DailyDemand_L*INDEX('Rainfall Data'!$E$15:$E$26,9),0),TankCapacity_L) -> 131.00937 | S24: =MIN(MAX(R24+INDEX(ActiveMonthlyRain,10)*RoofArea_m2*CollectionEff*1.25-DailyDemand_L*INDEX('Rainfall Data'!$E$15:$E$26,10),0),TankCapacity_L) -> 0 | T24: =MIN(MAX(S24+INDEX(ActiveMonthlyRain,11)*RoofArea_m2*CollectionEff*1.25-DailyDemand_L*INDEX('Rainfall Data'!$E$15:$E$26,11),0),TankCapacity_L) -> 0 | U24: =MIN(MAX(T24+INDEX(ActiveMonthlyRain,12)*RoofArea_m2*CollectionEff*1.25-DailyDemand_L*INDEX('Rainfall Data'!$E$15:$E$26,12),0),TankCapacity_L) -> 0
B26: Tank Capacity
B27: -25% | C27: 0.75 | D27: =MIN(DailyDemand_L*INDEX('Rainfall Data'!$E$15:$E$26,1),MAX(TankInitial_L+INDEX(ActiveMonthlyRain,1)*RoofArea_m2*CollectionEff-DeadStorage_L,0))+MIN(DailyDemand_L*INDEX('Rainfall Data'!$E$15:$E$26,2),MAX(J27+INDEX(ActiveMonthlyRain,2)*RoofArea_m2*CollectionEff-DeadStorage_L,0))+MIN(DailyDemand_L*INDEX('Rainfall Data'!$E$15:$E$26,3),MAX(K27+INDEX(ActiveMonthlyRain,3)*RoofArea_m2*CollectionEff-DeadStorage_L,0))+MIN(DailyDemand_L*INDEX('Rainfall Data'!$E$15:$E$26,4),MAX(L27+INDEX(ActiveMonthlyRain,4)*RoofArea_m2*CollectionEff-DeadStorage_L,0))+MIN(DailyDemand_L*INDEX('Rainfall Data'!$E$15:$E$26,5),MAX(M27+INDEX(ActiveMonthlyRain,5)*RoofArea_m2*CollectionEff-DeadStorage_L,0))+MIN(DailyDemand_L*INDEX('Rainfall Data'!$E$15:$E$26,6),MAX(N27+INDEX(ActiveMonthlyRain,6)*RoofArea_m2*CollectionEff-DeadStorage_L,0))+MIN(DailyDemand_L*INDEX('Rainfall Data'!$E$15:$E$26,7),MAX(O27+INDEX(ActiveMonthlyRain,7)*RoofArea_m2*CollectionEff-DeadStorage_L,0))+MIN(DailyDemand_L*INDEX('Rainfall Data'!$E$15:$E$26,8),MAX(P27+INDEX(ActiveMonthlyRain,8)*RoofArea_m2*CollectionEff-DeadStorage_L,0))+MIN(DailyDemand_L*INDEX('Rainfall Data'!$E$15:$E$26,9),MAX(Q27+INDEX(ActiveMonthlyRain,9)*RoofArea_m2*CollectionEff-DeadStorage_L,0))+MIN(DailyDemand_L*INDEX('Rainfall Data'!$E$15:$E$26,10),MAX(R27+INDEX(ActiveMonthlyRain,10)*RoofArea_m2*CollectionEff-DeadStorage_L,0))+MIN(DailyDemand_L*INDEX('Rainfall Data'!$E$15:$E$26,11),MAX(S27+INDEX(ActiveMonthlyRain,11)*RoofArea_m2*CollectionEff-DeadStorage_L,0))+MIN(DailyDemand_L*INDEX('Rainfall Data'!$E$15:$E$26,12),MAX(T27+INDEX(ActiveMonthlyRain,12)*RoofArea_m2*CollectionEff-DeadStorage_L,0)) -> 25576.576 | E27: =D27/(SUMPRODUCT(DailyDemand_L*'Rainfall Data'!$E$15:$E$26)) -> 0.25952893 | J27: =MIN(MAX(TankInitial_L+INDEX(ActiveMonthlyRain,1)*RoofArea_m2*CollectionEff-DailyDemand_L*INDEX('Rainfall Data'!$E$15:$E$26,1),0),(TankCapacity_L*0.75)) -> 0 | K27: =MIN(MAX(J27+INDEX(ActiveMonthlyRain,2)*RoofArea_m2*CollectionEff-DailyDemand_L*INDEX('Rainfall Data'!$E$15:$E$26,2),0),(TankCapacity_L*0.75)) -> 0 | L27: =MIN(MAX(K27+INDEX(ActiveMonthlyRain,3)*RoofArea_m2*CollectionEff-DailyDemand_L*INDEX('Rainfall Data'!$E$15:$E$26,3),0),(TankCapacity_L*0.75)) -> 0 | M27: =MIN(MAX(L27+INDEX(ActiveMonthlyRain,4)*RoofArea_m2*CollectionEff-DailyDemand_L*INDEX('Rainfall Data'!$E$15:$E$26,4),0),(TankCapacity_L*0.75)) -> 0 | N27: =MIN(MAX(M27+INDEX(ActiveMonthlyRain,5)*RoofArea_m2*CollectionEff-DailyDemand_L*INDEX('Rainfall Data'!$E$15:$E$26,5),0),(TankCapacity_L*0.75)) -> 0 | O27: =MIN(MAX(N27+INDEX(ActiveMonthlyRain,6)*RoofArea_m2*CollectionEff-DailyDemand_L*INDEX('Rainfall Data'!$E$15:$E$26,6),0),(TankCapacity_L*0.75)) -> 0 | P27: =MIN(MAX(O27+INDEX(ActiveMonthlyRain,7)*RoofArea_m2*CollectionEff-DailyDemand_L*INDEX('Rainfall Data'!$E$15:$E$26,7),0),(TankCapacity_L*0.75)) -> 2830.8325 | Q27: =MIN(MAX(P27+INDEX(ActiveMonthlyRain,8)*RoofArea_m2*CollectionEff-DailyDemand_L*INDEX('Rainfall Data'!$E$15:$E$26,8),0),(TankCapacity_L*0.75)) -> 3750 | R27: =MIN(MAX(Q27+INDEX(ActiveMonthlyRain,9)*RoofArea_m2*CollectionEff-DailyDemand_L*INDEX('Rainfall Data'!$E$15:$E$26,9),0),(TankCapacity_L*0.75)) -> 0 | S27: =MIN(MAX(R27+INDEX(ActiveMonthlyRain,10)*RoofArea_m2*CollectionEff-DailyDemand_L*INDEX('Rainfall Data'!$E$15:$E$26,10),0),(TankCapacity_L*0.75)) -> 0 | T27: =MIN(MAX(S27+INDEX(ActiveMonthlyRain,11)*RoofArea_m2*CollectionEff-DailyDemand_L*INDEX('Rainfall Data'!$E$15:$E$26,11),0),(TankCapacity_L*0.75)) -> 0 | U27: =MIN(MAX(T27+INDEX(ActiveMonthlyRain,12)*RoofArea_m2*CollectionEff-DailyDemand_L*INDEX('Rainfall Data'!$E$15:$E$26,12),0),(TankCapacity_L*0.75)) -> 0
B28: Base | C28: 1 | D28: =MIN(DailyDemand_L*INDEX('Rainfall Data'!$E$15:$E$26,1),MAX(TankInitial_L+INDEX(ActiveMonthlyRain,1)*RoofArea_m2*CollectionEff-DeadStorage_L,0))+MIN(DailyDemand_L*INDEX('Rainfall Data'!$E$15:$E$26,2),MAX(J28+INDEX(ActiveMonthlyRain,2)*RoofArea_m2*CollectionEff-DeadStorage_L,0))+MIN(DailyDemand_L*INDEX('Rainfall Data'!$E$15:$E$26,3),MAX(K28+INDEX(ActiveMonthlyRain,3)*RoofArea_m2*CollectionEff-DeadStorage_L,0))+MIN(DailyDemand_L*INDEX('Rainfall Data'!$E$15:$E$26,4),MAX(L28+INDEX(ActiveMonthlyRain,4)*RoofArea_m2*CollectionEff-DeadStorage_L,0))+MIN(DailyDemand_L*INDEX('Rainfall Data'!$E$15:$E$26,5),MAX(M28+INDEX(ActiveMonthlyRain,5)*RoofArea_m2*CollectionEff-DeadStorage_L,0))+MIN(DailyDemand_L*INDEX('Rainfall Data'!$E$15:$E$26,6),MAX(N28+INDEX(ActiveMonthlyRain,6)*RoofArea_m2*CollectionEff-DeadStorage_L,0))+MIN(DailyDemand_L*INDEX('Rainfall Data'!$E$15:$E$26,7),MAX(O28+INDEX(ActiveMonthlyRain,7)*RoofArea_m2*CollectionEff-DeadStorage_L,0))+MIN(DailyDemand_L*INDEX('Rainfall Data'!$E$15:$E$26,8),MAX(P28+INDEX(ActiveMonthlyRain,8)*RoofArea_m2*CollectionEff-DeadStorage_L,0))+MIN(DailyDemand_L*INDEX('Rainfall Data'!$E$15:$E$26,9),MAX(Q28+INDEX(ActiveMonthlyRain,9)*RoofArea_m2*CollectionEff-DeadStorage_L,0))+MIN(DailyDemand_L*INDEX('Rainfall Data'!$E$15:$E$26,10),MAX(R28+INDEX(ActiveMonthlyRain,10)*RoofArea_m2*CollectionEff-DeadStorage_L,0))+MIN(DailyDemand_L*INDEX('Rainfall Data'!$E$15:$E$26,11),MAX(S28+INDEX(ActiveMonthlyRain,11)*RoofArea_m2*CollectionEff-DeadStorage_L,0))+MIN(DailyDemand_L*INDEX('Rainfall Data'!$E$15:$E$26,12),MAX(T28+INDEX(ActiveMonthlyRain,12)*RoofArea_m2*CollectionEff-DeadStorage_L,0)) -> 26109.677 | E28: =D28/(SUMPRODUCT(DailyDemand_L*'Rainfall Data'!$E$15:$E$26)) -> 0.26493838 | J28: =MIN(MAX(TankInitial_L+INDEX(ActiveMonthlyRain,1)*RoofArea_m2*CollectionEff-DailyDemand_L*INDEX('Rainfall Data'!$E$15:$E$26,1),0),(TankCapacity_L*1)) -> 0 | K28: =MIN(MAX(J28+INDEX(ActiveMonthlyRain,2)*RoofArea_m2*CollectionEff-DailyDemand_L*INDEX('Rainfall Data'!$E$15:$E$26,2),0),(TankCapacity_L*1)) -> 0 | L28: =MIN(MAX(K28+INDEX(ActiveMonthlyRain,3)*RoofArea_m2*CollectionEff-DailyDemand_L*INDEX('Rainfall Data'!$E$15:$E$26,3),0),(TankCapacity_L*1)) -> 0 | M28: =MIN(MAX(L28+INDEX(ActiveMonthlyRain,4)*RoofArea_m2*CollectionEff-DailyDemand_L*INDEX('Rainfall Data'!$E$15:$E$26,4),0),(TankCapacity_L*1)) -> 0 | N28: =MIN(MAX(M28+INDEX(ActiveMonthlyRain,5)*RoofArea_m2*CollectionEff-DailyDemand_L*INDEX('Rainfall Data'!$E$15:$E$26,5),0),(TankCapacity_L*1)) -> 0 | O28: =MIN(MAX(N28+INDEX(ActiveMonthlyRain,6)*RoofArea_m2*CollectionEff-DailyDemand_L*INDEX('Rainfall Data'!$E$15:$E$26,6),0),(TankCapacity_L*1)) -> 0 | P28: =MIN(MAX(O28+INDEX(ActiveMonthlyRain,7)*RoofArea_m2*CollectionEff-DailyDemand_L*INDEX('Rainfall Data'!$E$15:$E$26,7),0),(TankCapacity_L*1)) -> 2830.8325 | Q28: =MIN(MAX(P28+INDEX(ActiveMonthlyRain,8)*RoofArea_m2*CollectionEff-DailyDemand_L*INDEX('Rainfall Data'!$E$15:$E$26,8),0),(TankCapacity_L*1)) -> 4283.101 | R28: =MIN(MAX(Q28+INDEX(ActiveMonthlyRain,9)*RoofArea_m2*CollectionEff-DailyDemand_L*INDEX('Rainfall Data'!$E$15:$E$26,9),0),(TankCapacity_L*1)) -> 0 | S28: =MIN(MAX(R28+INDEX(ActiveMonthlyRain,10)*RoofArea_m2*CollectionEff-DailyDemand_L*INDEX('Rainfall Data'!$E$15:$E$26,10),0),(TankCapacity_L*1)) -> 0 | T28: =MIN(MAX(S28+INDEX(ActiveMonthlyRain,11)*RoofArea_m2*CollectionEff-DailyDemand_L*INDEX('Rainfall Data'!$E$15:$E$26,11),0),(TankCapacity_L*1)) -> 0 | U28: =MIN(MAX(T28+INDEX(ActiveMonthlyRain,12)*RoofArea_m2*CollectionEff-DailyDemand_L*INDEX('Rainfall Data'!$E$15:$E$26,12),0),(TankCapacity_L*1)) -> 0
B29: +25% | C29: 1.25 | D29: =MIN(DailyDemand_L*INDEX('Rainfall Data'!$E$15:$E$26,1),MAX(TankInitial_L+INDEX(ActiveMonthlyRain,1)*RoofArea_m2*CollectionEff-DeadStorage_L,0))+MIN(DailyDemand_L*INDEX('Rainfall Data'!$E$15:$E$26,2),MAX(J29+INDEX(ActiveMonthlyRain,2)*RoofArea_m2*CollectionEff-DeadStorage_L,0))+MIN(DailyDemand_L*INDEX('Rainfall Data'!$E$15:$E$26,3),MAX(K29+INDEX(ActiveMonthlyRain,3)*RoofArea_m2*CollectionEff-DeadStorage_L,0))+MIN(DailyDemand_L*INDEX('Rainfall Data'!$E$15:$E$26,4),MAX(L29+INDEX(ActiveMonthlyRain,4)*RoofArea_m2*CollectionEff-DeadStorage_L,0))+MIN(DailyDemand_L*INDEX('Rainfall Data'!$E$15:$E$26,5),MAX(M29+INDEX(ActiveMonthlyRain,5)*RoofArea_m2*CollectionEff-DeadStorage_L,0))+MIN(DailyDemand_L*INDEX('Rainfall Data'!$E$15:$E$26,6),MAX(N29+INDEX(ActiveMonthlyRain,6)*RoofArea_m2*CollectionEff-DeadStorage_L,0))+MIN(DailyDemand_L*INDEX('Rainfall Data'!$E$15:$E$26,7),MAX(O29+INDEX(ActiveMonthlyRain,7)*RoofArea_m2*CollectionEff-DeadStorage_L,0))+MIN(DailyDemand_L*INDEX('Rainfall Data'!$E$15:$E$26,8),MAX(P29+INDEX(ActiveMonthlyRain,8)*RoofArea_m2*CollectionEff-DeadStorage_L,0))+MIN(DailyDemand_L*INDEX('Rainfall Data'!$E$15:$E$26,9),MAX(Q29+INDEX(ActiveMonthlyRain,9)*RoofArea_m2*CollectionEff-DeadStorage_L,0))+MIN(DailyDemand_L*INDEX('Rainfall Data'!$E$15:$E$26,10),MAX(R29+INDEX(ActiveMonthlyRain,10)*RoofArea_m2*CollectionEff-DeadStorage_L,0))+MIN(DailyDemand_L*INDEX('Rainfall Data'!$E$15:$E$26,11),MAX(S29+INDEX(ActiveMonthlyRain,11)*RoofArea_m2*CollectionEff-DeadStorage_L,0))+MIN(DailyDemand_L*INDEX('Rainfall Data'!$E$15:$E$26,12),MAX(T29+INDEX(ActiveMonthlyRain,12)*RoofArea_m2*CollectionEff-DeadStorage_L,0)) -> 26109.677 | E29: =D29/(SUMPRODUCT(DailyDemand_L*'Rainfall Data'!$E$15:$E$26)) -> 0.26493838 | J29: =MIN(MAX(TankInitial_L+INDEX(ActiveMonthlyRain,1)*RoofArea_m2*CollectionEff-DailyDemand_L*INDEX('Rainfall Data'!$E$15:$E$26,1),0),(TankCapacity_L*1.25)) -> 0 | K29: =MIN(MAX(J29+INDEX(ActiveMonthlyRain,2)*RoofArea_m2*CollectionEff-DailyDemand_L*INDEX('Rainfall Data'!$E$15:$E$26,2),0),(TankCapacity_L*1.25)) -> 0 | L29: =MIN(MAX(K29+INDEX(ActiveMonthlyRain,3)*RoofArea_m2*CollectionEff-DailyDemand_L*INDEX('Rainfall Data'!$E$15:$E$26,3),0),(TankCapacity_L*1.25)) -> 0 | M29: =MIN(MAX(L29+INDEX(ActiveMonthlyRain,4)*RoofArea_m2*CollectionEff-DailyDemand_L*INDEX('Rainfall Data'!$E$15:$E$26,4),0),(TankCapacity_L*1.25)) -> 0 | N29: =MIN(MAX(M29+INDEX(ActiveMonthlyRain,5)*RoofArea_m2*CollectionEff-DailyDemand_L*INDEX('Rainfall Data'!$E$15:$E$26,5),0),(TankCapacity_L*1.25)) -> 0 | O29: =MIN(MAX(N29+INDEX(ActiveMonthlyRain,6)*RoofArea_m2*CollectionEff-DailyDemand_L*INDEX('Rainfall Data'!$E$15:$E$26,6),0),(TankCapacity_L*1.25)) -> 0 | P29: =MIN(MAX(O29+INDEX(ActiveMonthlyRain,7)*RoofArea_m2*CollectionEff-DailyDemand_L*INDEX('Rainfall Data'!$E$15:$E$26,7),0),(TankCapacity_L*1.25)) -> 2830.8325 | Q29: =MIN(MAX(P29+INDEX(ActiveMonthlyRain,8)*RoofArea_m2*CollectionEff-DailyDemand_L*INDEX('Rainfall Data'!$E$15:$E$26,8),0),(TankCapacity_L*1.25)) -> 4283.101 | R29: =MIN(MAX(Q29+INDEX(ActiveMonthlyRain,9)*RoofArea_m2*CollectionEff-DailyDemand_L*INDEX('Rainfall Data'!$E$15:$E$26,9),0),(TankCapacity_L*1.25)) -> 0 | S29: =MIN(MAX(R29+INDEX(ActiveMonthlyRain,10)*RoofArea_m2*CollectionEff-DailyDemand_L*INDEX('Rainfall Data'!$E$15:$E$26,10),0),(TankCapacity_L*1.25)) -> 0 | T29: =MIN(MAX(S29+INDEX(ActiveMonthlyRain,11)*RoofArea_m2*CollectionEff-DailyDemand_L*INDEX('Rainfall Data'!$E$15:$E$26,11),0),(TankCapacity_L*1.25)) -> 0 | U29: =MIN(MAX(T29+INDEX(ActiveMonthlyRain,12)*RoofArea_m2*CollectionEff-DailyDemand_L*INDEX('Rainfall Data'!$E$15:$E$26,12),0),(TankCapacity_L*1.25)) -> 0
B32: TORNADO SUMMARY -Reliability Swing (percentage points)
B33: Parameter | C33: Low Reliability | D33: High Reliability | E33: Swing (pp)
B34: Roof Area | C34: =E7 -> 0.19343361 | D34: =E9 -> 0.28828038 | E34: =(E9-E7)*100 -> 9.4846766
B35: Rainfall (all months) | C35: =E12 -> 0.19343361 | D35: =E14 -> 0.28828038 | E35: =(E14-E12)*100 -> 9.4846766
B36: Water Demand | C36: =E17 -> 0.23177652 | D36: =E19 -> 0.2639044 | E36: =(E19-E17)*100 -> 3.2127874
B37: Collection Efficiency | C37: =E22 -> 0.19343361 | D37: =E24 -> 0.28828038 | E37: =(E24-E22)*100 -> 9.4846766
B38: Tank Capacity | C38: =E27 -> 0.25952893 | D38: =E29 -> 0.26493838 | E38: =(E29-E27)*100 -> 0.5409447

Sheet Economics
B2: ECONOMIC ANALYSIS - Capital, Operating, and Life-Cycle Cost
B4: CAPITAL & OPERATING COST
B5: Tank Capital Cost | C5: =TankCost_PKR -> 85000
B6: Installation Cost | C6: =InstallCost_PKR -> 45000
B7: Total Capital Cost (Year 0) | C7: =C5+C6 -> 130000
B9: PUMP ENERGY COST (if pump-fed distribution is used)
B10: Est. Pump Power Draw | C10: 0.37 | D10: Typical small domestic booster pump; edit if a different pump is specified.
B11: Est. Daily Pump Run Time | C11: 0.5
B12: Annual Pumping Energy Cost | C12: =C10*C11*365*ElecTariff_PKR_kWh/PumpEff -> 3798.2813
B14: Total Annual Operating Cost | C14: =MaintCost_PKR+C12 -> 9798.2812
B16: ANNUAL SAVINGS
B17: Annual Water Supplied by System | C17: =('Monthly Summary'!F18) -> 23546.306
B18: Water Tariff (avoided cost) | C18: =WaterTariff_PKR_L -> 1.2
B19: Gross Annual Water Bill Savings | C19: =C17*C18 -> 28255.567
B20: Net Annual Savings (after operating cost) | C20: =C19-C14 -> 18457.286
B22: SIMPLE PAYBACK PERIOD
B23: Simple Payback Period | C23: =C7/C20 -> 7.043289 | D23: Total Capital Cost / Net Annual Savings
B25: NET PRESENT VALUE & INTERNAL RATE OF RETURN
B26: Discount Rate | C26: =DiscountRate -> 0.12
B27: Analysis Horizon | C27: =ProjectLife_yrs -> 20
B28: Net Present Value (NPV) | C28: =NPV(DiscountRate,CF_Range)-C7 -> 7865.6569
B29: Internal Rate of Return (IRR) | C29: =IRR(IRR_Range) -> 0.12956193
B31: 20-YEAR LIFE-CYCLE CASH FLOW
B32: Year 0 = capital outlay (negative). Years 1-20 = net annual savings, held constant in real terms (no inflation escalation modeled -see assumption).
B34: Year | C34: Capital Outflow (PKR) | D34: Maintenance + Energy (PKR) | E34: Water Bill Savings (PKR) | F34: Net Cash Flow (PKR) | G34: Cumulative Cash Flow (PKR)
B35: 0 | C35: =-C7 -> -130000 | D35: 0 | E35: 0 | F35: =C35-D35+E35 -> -130000 | G35: =F35 -> -130000
B36: 1 | C36: 0 | D36: =$C$14 -> 9798.2812 | E36: =$C$19 -> 28255.567 | F36: =E36-D36-C36 -> 18457.286 | G36: =G35+F36 -> -111542.71
B37: 2 | C37: 0 | D37: =$C$14 -> 9798.2812 | E37: =$C$19 -> 28255.567 | F37: =E37-D37-C37 -> 18457.286 | G37: =G36+F37 -> -93085.428
B38: 3 | C38: 0 | D38: =$C$14 -> 9798.2812 | E38: =$C$19 -> 28255.567 | F38: =E38-D38-C38 -> 18457.286 | G38: =G37+F38 -> -74628.142
B39: 4 | C39: 0 | D39: =$C$14 -> 9798.2812 | E39: =$C$19 -> 28255.567 | F39: =E39-D39-C39 -> 18457.286 | G39: =G38+F39 -> -56170.856
B40: 5 | C40: 0 | D40: =$C$14 -> 9798.2812 | E40: =$C$19 -> 28255.567 | F40: =E40-D40-C40 -> 18457.286 | G40: =G39+F40 -> -37713.57
B41: 6 | C41: 0 | D41: =$C$14 -> 9798.2812 | E41: =$C$19 -> 28255.567 | F41: =E41-D41-C41 -> 18457.286 | G41: =G40+F41 -> -19256.284
B42: 7 | C42: 0 | D42: =$C$14 -> 9798.2812 | E42: =$C$19 -> 28255.567 | F42: =E42-D42-C42 -> 18457.286 | G42: =G41+F42 -> -798.99835
B43: 8 | C43: 0 | D43: =$C$14 -> 9798.2812 | E43: =$C$19 -> 28255.567 | F43: =E43-D43-C43 -> 18457.286 | G43: =G42+F43 -> 17658.288
B44: 9 | C44: 0 | D44: =$C$14 -> 9798.2812 | E44: =$C$19 -> 28255.567 | F44: =E44-D44-C44 -> 18457.286 | G44: =G43+F44 -> 36115.574
B45: 10 | C45: 0 | D45: =$C$14 -> 9798.2812 | E45: =$C$19 -> 28255.567 | F45: =E45-D45-C45 -> 18457.286 | G45: =G44+F45 -> 54572.86
B46: 11 | C46: 0 | D46: =$C$14 -> 9798.2812 | E46: =$C$19 -> 28255.567 | F46: =E46-D46-C46 -> 18457.286 | G46: =G45+F46 -> 73030.145
B47: 12 | C47: 0 | D47: =$C$14 -> 9798.2812 | E47: =$C$19 -> 28255.567 | F47: =E47-D47-C47 -> 18457.286 | G47: =G46+F47 -> 91487.431
... B55: 20 | C55: 0 | D55: =$C$14 -> 9798.2812 | E55: =$C$19 -> 28255.567 | F55: =E55-D55-C55 -> 18457.286 | G55: =G54+F55 -> 239145.72
B57: LIFE-CYCLE COST SUMMARY
B58: Total Life-Cycle Cost (Capital + O&M, undiscounted) | C58: =C7+SUM(D36:D55) -> 325965.62
B59: Total Life-Cycle Water Bill Savings (undiscounted) | C59: =SUM(E36:E55) -> 565111.34
B60: Net Lifetime Benefit (undiscounted) | C60: =G55 -> 239145.72

Sheet Charts
B2: CHARTS - Full Chart Set for Presentation
